Workbook
Name RampaStress: 'Stress Test & Sensibilidad'!$E$19
Name FactorADR: 'Stress Test & Sensibilidad'!$E$17
Name FactorCuota: 'Stress Test & Sensibilidad'!$E$24
Name ChurnEsc: Supuestos!$E$19
Name TasaISR: 'Valuación Contrato Bravante'!$B$10
Name Tramo3: Supuestos!$B$11
Name RampaEsc: Supuestos!$E$17
Name DeltaCobranza: 'Stress Test & Sensibilidad'!$E$29
Name Tramo2: Supuestos!$B$10
Name AnioBase: Supuestos!$B$7
Name Escenario: Supuestos!$B$13
Name CrecimientoADR: Supuestos!$B$25
Name FactorCosto: 'Stress Test & Sensibilidad'!$E$33
Name PctConvenio: Supuestos!$B$2
Name FactorOcc: 'Stress Test & Sensibilidad'!$E$18
Name FilaVentaEsc: Supuestos!$E$15
Name ChurnNeto: Supuestos!$B$24
Name PctCapexRep: 'Valuación Contrato Bravante'!$B$30
Name EscenarioStress: 'Stress Test & Sensibilidad'!$B$3
Name CapexStress: 'Stress Test & Sensibilidad'!$E$28
Name CACporLlave: Supuestos!$B$26
Name CuotaSeg2: Supuestos!$B$5
Name Tramo1: Supuestos!$B$9
Name VidaUtilDep: 'Valuación Contrato Bravante'!$B$29
Name EV_Parametrico: 'Stress Test & Sensibilidad'!$B$125
Name FactorNomina: 'Stress Test & Sensibilidad'!$E$27
Name DiasCapTrab: 'Valuación Contrato Bravante'!$B$31
Name LagStress: 'Stress Test & Sensibilidad'!$E$22
Name ConvenioStress: 'Stress Test & Sensibilidad'!$E$25
Name MultSalida: 'Valuación Contrato Bravante'!$B$28
Name ModoStress: 'Stress Test & Sensibilidad'!$B$5
Name FactorLlaves: 'Stress Test & Sensibilidad'!$E$32
Name TopeLlaves: Supuestos!$B$27
Name InflacionStress: 'Stress Test & Sensibilidad'!$E$26
Name ChurnStress: 'Stress Test & Sensibilidad'!$E$20
Name UsoPropEsc: Supuestos!$E$18
Name WACCStress: 'Stress Test & Sensibilidad'!$E$30
Name WACC: 'Valuación Contrato Bravante'!$B$18
Name RepartoStress: 'Stress Test & Sensibilidad'!$E$23
Name ChurnBruto: Supuestos!$B$21
Name ReposicionStress: 'Stress Test & Sensibilidad'!$E$21
Name LagReposicion: Supuestos!$B$23
Name InflacionAnual: Supuestos!$B$6
Name TasaReposicion: Supuestos!$B$22
Name PctReparto: Supuestos!$B$3
Name CrecMercadoEsc: Supuestos!$E$16
Name PlazoContrato: 'Valuación Contrato Bravante'!$B$22
Name CuotaSeg1: Supuestos!$B$4
Name InflacionEsc: Supuestos!$E$20

Sheet Supuestos
A1: SUPUESTOS DEL MODELO — BRAVANTE
A2: % Convenio Limpieza & Mantenimiento (s/ venta) | B2: 0.0833
A3: % Reparto base a Propietarios (s/ venta) | B3: 0.75
A4: Cuota fija por unidad — Segmento No. 1 | B4: 1785
A5: Cuota fija por unidad — Segmento No. 2 | B5: 2870.45
A6: Inflación anual (gastos fijos) | B6: =InflacionEsc -> 0.045
A7: Año base | B7: 2025
A9: Nómina — tramo 1 (hasta 40 unidades): multiplicador | B9: 1
A10: Nómina — tramo 2 (41 a 80 unidades): multiplicador | B10: 1.6
A11: Nómina — tramo 3 (81+ unidades): multiplicador | B11: 2.2
A13: ESCENARIOS | B13: 2 | C13: (1 = Bear, 2 = Base, 3 = Bull)
A14: Driver | B14: Bear | C14: Base | D14: Bull | E14: Activo
A15: Fila de venta en archivo de mercado | B15: 9 | C15: 8 | D15: 7 | E15: {=INDEX(B15:D15,1,Escenario)} -> 8
A16: Crecimiento anual mercado (ADR) | B16: 0.02 | C16: 0.04 | D16: 0.06 | E16: {=INDEX(B16:D16,1,Escenario)} -> 0.04
A17: Meses de rampa | B17: 24 | C17: 18 | D17: 12 | E17: {=INDEX(B17:D17,1,Escenario)} -> 18
A18: Uso de propietario (% noches) | B18: 0.08 | C18: 0.05 | D18: 0.03 | E18: {=INDEX(B18:D18,1,Escenario)} -> 0.05
A19: Churn neto anual | B19: 0.1 | C19: 0.06 | D19: 0.03 | E19: {=INDEX(B19:D19,1,Escenario)} -> 0.06
A20: Inflación anual (gastos fijos) | B20: 0.06 | C20: 0.045 | D20: 0.035 | E20: {=INDEX(B20:D20,1,Escenario)} -> 0.045
A21: Churn bruto anual (salidas de propietarios) | B21: 0.06
A22: Tasa de reposición de llaves | B22: 0.6 | C22: El 60% es una base provisional; el canal de reventa y refirma está confirmado como real pero la tasa aún no se ha medido.
A23: Lag de reposición (meses de vacancia) | B23: 3
A24: Churn neto efectivo (calculado) | B24: =B21*(1-B22) -> 0.024
A25: Crecimiento de ADR largo plazo | B25: {=INDEX(B16:D16,1,$B$13)} -> 0.04
A26: CAC por llave repuesta | B26: ='Paso 5 Resumen Desglose de Inve'!$D$68/89 -> 8251.4607
A27: Tope físico de llaves (edificio) | B27: 117
A28: Churn bruto | B28: 0.1 | C28: 0.06 | D28: 0.03 | E28: =INDEX(B28:D28,1,$B$13) -> 0.06
A29: Tasa de reposición | B29: 0.3 | C29: 0.6 | D29: 0.85 | E29: =INDEX(B29:D29,1,$B$13) -> 0.6
A30: Lag de reposición | B30: 5 | C30: 3 | D30: 2 | E30: =INDEX(B30:D30,1,$B$13) -> 3

Sheet Profit & Loss
A2: Fechas | D2: ="Q"&ROUNDUP(MONTH(D$3)/3, 0)&" "&YEAR(D$3) -> Q1 2025 | G2: ="Q"&ROUNDUP(MONTH(G$3)/3, 0)&" "&YEAR(G$3) -> Q2 2025 | J2: ="Q"&ROUNDUP(MONTH(J$3)/3, 0)&" "&YEAR(J$3) -> Q3 2025 | M2: ="Q"&ROUNDUP(MONTH(M$3)/3, 0)&" "&YEAR(M$3) -> Q4 2025
D3: 45658 | E3: =EDATE(D3,1) -> 45689 | F3: =EDATE(E3,1) -> 45717 | G3: =EDATE(F3,1) -> 45748 | H3: =EDATE(G3,1) -> 45778 | I3: =EDATE(H3,1) -> 45809 | J3: =EDATE(I3,1) -> 45839 | K3: =EDATE(J3,1) -> 45870 | L3: =EDATE(K3,1) -> 45901 | ... BK3: =EDATE(BJ3,1) -> 47453 | BL3: TOTAL | BM3: PROMEDIO
A4: Factor Stress Venta | D4: =IF(ModoStress="ON", FactorADR*FactorOcc*FactorLlaves, 1) -> 1 | E4: =IF(ModoStress="ON", FactorADR*FactorOcc*FactorLlaves, 1) -> 1 | F4: =IF(ModoStress="ON", FactorADR*FactorOcc*FactorLlaves, 1) -> 1 | G4: =IF(ModoStress="ON", FactorADR*FactorOcc*FactorLlaves, 1) -> 1 | H4: =IF(ModoStress="ON", FactorADR*FactorOcc*FactorLlaves, 1) -> 1 | I4: =IF(ModoStress="ON", FactorADR*FactorOcc*FactorLlaves, 1) -> 1 | J4: =IF(ModoStress="ON", FactorADR*FactorOcc*FactorLlaves, 1) -> 1 | K4: =IF(ModoStress="ON", FactorADR*FactorOcc*FactorLlaves, 1) -> 1 | ... BK4: =IF(ModoStress="ON", FactorADR*FactorOcc*FactorLlaves, 1) -> 1
A5: Factor Stress Costo | D5: =IF(ModoStress="ON", FactorCosto, 1) -> 1 | E5: =IF(ModoStress="ON", FactorCosto, 1) -> 1 | F5: =IF(ModoStress="ON", FactorCosto, 1) -> 1 | G5: =IF(ModoStress="ON", FactorCosto, 1) -> 1 | H5: =IF(ModoStress="ON", FactorCosto, 1) -> 1 | I5: =IF(ModoStress="ON", FactorCosto, 1) -> 1 | J5: =IF(ModoStress="ON", FactorCosto, 1) -> 1 | K5: =IF(ModoStress="ON", FactorCosto, 1) -> 1 | ... BK5: =IF(ModoStress="ON", FactorCosto, 1) -> 1
A6: Factor Reposición Llaves | D6: =IF(ModoStress="ON", ((1-ChurnNeto)/(1-ChurnBruto))^(YEAR(D$3)-AnioBase), 1) -> 1 | E6: =IF(ModoStress="ON", ((1-ChurnNeto)/(1-ChurnBruto))^(YEAR(E$3)-AnioBase), 1) -> 1 | F6: =IF(ModoStress="ON", ((1-ChurnNeto)/(1-ChurnBruto))^(YEAR(F$3)-AnioBase), 1) -> 1 | G6: =IF(ModoStress="ON", ((1-ChurnNeto)/(1-ChurnBruto))^(YEAR(G$3)-AnioBase), 1) -> 1 | H6: =IF(ModoStress="ON", ((1-ChurnNeto)/(1-ChurnBruto))^(YEAR(H$3)-AnioBase), 1) -> 1 | I6: =IF(ModoStress="ON", ((1-ChurnNeto)/(1-ChurnBruto))^(YEAR(I$3)-AnioBase), 1) -> 1 | J6: =IF(ModoStress="ON", ((1-ChurnNeto)/(1-ChurnBruto))^(YEAR(J$3)-AnioBase), 1) -> 1 | K6: =IF(ModoStress="ON", ((1-ChurnNeto)/(1-ChurnBruto))^(YEAR(K$3)-AnioBase), 1) -> 1 | ... BK6: =IF(ModoStress="ON", ((1-ChurnNeto)/(1-ChurnBruto))^(YEAR(BK$3)-AnioBase), 1) -> 1
A7: Venta Total (Despues de Comisiones OTAs + Pasarelas de Pago, IVA e Impuestos) | D7: =IFERROR(D8+D13,"Revise Error") -> 1000411.7 | E7: =IFERROR(E8+E13,"Revise Error") -> 1047043.8 | F7: =IFERROR(F8+F13,"Revise Error") -> 1066178.5 | G7: =IFERROR(G8+G13,"Revise Error") -> 1013043.5 | H7: =IFERROR(H8+H13,"Revise Error") -> 1037076 | I7: =IFERROR(I8+I13,"Revise Error") -> 1035263.9 | J7: =IFERROR(J8+J13,"Revise Error") -> 1090332 | K7: =IFERROR(K8+K13,"Revise Error") -> 1084090.5 | ... BK7: =IFERROR(BK8+BK13,"Revise Error") -> 907885.76 | BL7: =SUM(D7:BK7) -> 58754723 | BM7: =AVERAGE(D7:BK7) -> 979245.38
B8: ({UO} | AT-AMP-02) - Analisis de Mercado [No. 1 - KIVA] | D8: =IFERROR(__xludf.DUMMYFUNCTION("IFERROR(IMPORTRANGE(""https://docs.google.com/spreadsheets/d/10OcXjkVvXdQ20Dikey2wLwZD9Qs97Ke_ckzbHR2FA6E/edit?usp=sharing"", ""P1!E"" & FilaVentaEsc & "":BL"" & FilaVentaEsc))"),584744.4227656598) -> 584744.42 | E8: =IFERROR(__xludf.DUMMYFUNCTION("""COMPUTED_VALUE"""),632467.9730076719) -> 632467.97 | F8: =IFERROR(__xludf.DUMMYFUNCTION("""COMPUTED_VALUE"""),562671.2386455302) -> 562671.24 | G8: =IFERROR(__xludf.DUMMYFUNCTION("""COMPUTED_VALUE"""),606607.4703135559) -> 606607.47 | H8: =IFERROR(__xludf.DUMMYFUNCTION("""COMPUTED_VALUE"""),621981.6067745518) -> 621981.61 | I8: =IFERROR(__xludf.DUMMYFUNCTION("""COMPUTED_VALUE"""),622790.5486921028) -> 622790.55 | J8: =IFERROR(__xludf.DUMMYFUNCTION("""COMPUTED_VALUE"""),620667.8985979322) -> 620667.9 | K8: =IFERROR(__xludf.DUMMYFUNCTION("""COMPUTED_VALUE"""),599013.773384289) -> 599013.77 | L8: =IFERROR(__xludf.DUMMYFUNCTION("""COMPUTED_VALUE"""),582469.4162353423) -> 582469.42 | M8: =IFERROR(__xludf.DUMMYFUNCTION("""COMPUTED_VALUE"""),564299.5817159889) -> 564299.58 | N8: =IFERROR(__xludf.DUMMYFUNCTION("""COMPUTED_VALUE"""),629444.6701355868) -> 629444.67 | O8: =IFERROR(__xludf.DUMMYFUNCTION("""COMPUTED_VALUE"""),594748.7661271) -> 594748.77 | P8: =IFERROR(__xludf.DUMMYFUNCTION("""COMPUTED_VALUE"""),571646.1476957088) -> 571646.15 | Q8: =IFERROR(__xludf.DUMMYFUNCTION("""COMPUTED_VALUE"""),618300.6904123) -> 618300.69 | R8: =IFERROR(__xludf.DUMMYFUNCTION("""COMPUTED_VALUE"""),550067.4028998703) -> 550067.4 | S8: =IFERROR(__xludf.DUMMYFUNCTION("""COMPUTED_VALUE"""),593019.4629785322) -> 593019.46 | T8: =IFERROR(__xludf.DUMMYFUNCTION("""COMPUTED_VALUE"""),608049.2187828018) -> 608049.22 | U8: =IFERROR(__xludf.DUMMYFUNCTION("""COMPUTED_VALUE"""),608840.0404013997) -> 608840.04 | V8: =IFERROR(__xludf.DUMMYFUNCTION("""COMPUTED_VALUE"""),606764.9376693384) -> 606764.94 | W8: =IFERROR(__xludf.DUMMYFUNCTION("""COMPUTED_VALUE"""),585595.864860481) -> 585595.86 | X8: =IFERROR(__xludf.DUMMYFUNCTION("""COMPUTED_VALUE"""),569422.1013116706) -> 569422.1 | Y8: =IFERROR(__xludf.DUMMYFUNCTION("""COMPUTED_VALUE"""),551659.2710855508) -> 551659.27 | Z8: =IFERROR(__xludf.DUMMYFUNCTION("""COMPUTED_VALUE"""),615345.1095245496) -> 615345.11 | AA8: =IFERROR(__xludf.DUMMYFUNCTION("""COMPUTED_VALUE"""),581426.3937658529) -> 581426.39 | AB8: =IFERROR(__xludf.DUMMYFUNCTION("""COMPUTED_VALUE"""),558841.2739873251) -> 558841.27 | AC8: =IFERROR(__xludf.DUMMYFUNCTION("""COMPUTED_VALUE"""),604450.7549470644) -> 604450.75 | AD8: =IFERROR(__xludf.DUMMYFUNCTION("""COMPUTED_VALUE"""),537745.8930749132) -> 537745.89 | AE8: =IFERROR(__xludf.DUMMYFUNCTION("""COMPUTED_VALUE"""),579735.8270078131) -> 579735.83 | AF8: =IFERROR(__xludf.DUMMYFUNCTION("""COMPUTED_VALUE"""),594428.916282067) -> 594428.92 | AG8: =IFERROR(__xludf.DUMMYFUNCTION("""COMPUTED_VALUE"""),595202.0234964084) -> 595202.02 | AH8: =IFERROR(__xludf.DUMMYFUNCTION("""COMPUTED_VALUE"""),593173.4030655453) -> 593173.4 | AI8: =IFERROR(__xludf.DUMMYFUNCTION("""COMPUTED_VALUE"""),572478.517487606) -> 572478.52 | AJ8: =IFERROR(__xludf.DUMMYFUNCTION("""COMPUTED_VALUE"""),556667.0462422892) -> 556667.05 | AK8: =IFERROR(__xludf.DUMMYFUNCTION("""COMPUTED_VALUE"""),539302.1034132345) -> 539302.1 | AL8: =IFERROR(__xludf.DUMMYFUNCTION("""COMPUTED_VALUE"""),601561.3790711998) -> 601561.38 | AM8: =IFERROR(__xludf.DUMMYFUNCTION("""COMPUTED_VALUE"""),568402.4425454979) -> 568402.44 | AN8: =IFERROR(__xludf.DUMMYFUNCTION("""COMPUTED_VALUE"""),546323.229450009) -> 546323.23 | AO8: =IFERROR(__xludf.DUMMYFUNCTION("""COMPUTED_VALUE"""),612015.0243946877) -> 612015.02 | AP8: =IFERROR(__xludf.DUMMYFUNCTION("""COMPUTED_VALUE"""),525611.2750244924) -> 525611.28 | AQ8: =IFERROR(__xludf.DUMMYFUNCTION("""COMPUTED_VALUE"""),566653.6762717877) -> 566653.68 | AR8: =IFERROR(__xludf.DUMMYFUNCTION("""COMPUTED_VALUE"""),581015.2055497313) -> 581015.21 | AS8: =IFERROR(__xludf.DUMMYFUNCTION("""COMPUTED_VALUE"""),581770.8670506254) -> 581770.87 | AT8: =IFERROR(__xludf.DUMMYFUNCTION("""COMPUTED_VALUE"""),579788.0238807601) -> 579788.02 | AU8: =IFERROR(__xludf.DUMMYFUNCTION("""COMPUTED_VALUE"""),559560.133095937) -> 559560.13 | AV8: =IFERROR(__xludf.DUMMYFUNCTION("""COMPUTED_VALUE"""),544105.4589305196) -> 544105.46 | AW8: =IFERROR(__xludf.DUMMYFUNCTION("""COMPUTED_VALUE"""),527132.3683711179) -> 527132.37 | AX8: =IFERROR(__xludf.DUMMYFUNCTION("""COMPUTED_VALUE"""),587986.719249676) -> 587986.72 | AY8: =IFERROR(__xludf.DUMMYFUNCTION("""COMPUTED_VALUE"""),555576.0376802264) -> 555576.04 | AZ8: =IFERROR(__xludf.DUMMYFUNCTION("""COMPUTED_VALUE"""),533995.0577116064) -> 533995.06 | BA8: =IFERROR(__xludf.DUMMYFUNCTION("""COMPUTED_VALUE"""),577576.7302740464) -> 577576.73 | BB8: =IFERROR(__xludf.DUMMYFUNCTION("""COMPUTED_VALUE"""),513837.58246394387) -> 513837.58 | BC8: =IFERROR(__xludf.DUMMYFUNCTION("""COMPUTED_VALUE"""),553960.6339232996) -> 553960.63 | BD8: =IFERROR(__xludf.DUMMYFUNCTION("""COMPUTED_VALUE"""),568000.4649454176) -> 568000.46 | BE8: =IFERROR(__xludf.DUMMYFUNCTION("""COMPUTED_VALUE"""),568739.1996286915) -> 568739.2 | BF8: =IFERROR(__xludf.DUMMYFUNCTION("""COMPUTED_VALUE"""),566800.772145831) -> 566800.77 | BG8: =IFERROR(__xludf.DUMMYFUNCTION("""COMPUTED_VALUE"""),547025.986114588) -> 547025.99 | BH8: =IFERROR(__xludf.DUMMYFUNCTION("""COMPUTED_VALUE"""),531917.4966504759) -> 531917.5 | BI8: =IFERROR(__xludf.DUMMYFUNCTION("""COMPUTED_VALUE"""),515324.6033196048) -> 515324.6 | BJ8: =IFERROR(__xludf.DUMMYFUNCTION("""COMPUTED_VALUE"""),574815.8167384833) -> 574815.82 | BK8: =IFERROR(__xludf.DUMMYFUNCTION("""COMPUTED_VALUE"""),543131.1344361893) -> 543131.13 | BL8: =SUM(D8:BK8) -> 34546697 | BM8: =AVERAGE(D8:BK8) -> 575778.28
C9: Property Count | D9: =IFERROR(__xludf.DUMMYFUNCTION("IF(IMPORTRANGE(""https://docs.google.com/spreadsheets/d/10OcXjkVvXdQ20Dikey2wLwZD9Qs97Ke_ckzbHR2FA6E/edit?usp=sharing"", ""P1!$B$11"")=1, IFERROR(INDEX(IMPORTRANGE(""https://docs.google.com/spreadsheets/d/10OcXjkVvXdQ20Dikey2wLwZD9Qs97Ke_ckzbHR2FA6E/"&"edit?usp=sharing"", ""P1!$E$6:$BL$6""), MATCH(D3, IMPORTRANGE(""https://docs.google.com/spreadsheets/d/10OcXjkVvXdQ20Dikey2wLwZD9Qs97Ke_ckzbHR2FA6E/edit?usp=sharing"", ""P1!$E$4:$BL$4""), 0)), ""Unknown""), IF(IMPORTRANGE(""https://docs.google."&"com/spreadsheets/d/10OcXjkVvXdQ20Dikey2wLwZD9Qs97Ke_ckzbHR2FA6E/edit?usp=sharing"", ""P1!$B$11"")=2, 0, ""Unknown""))"),24.7) -> 24.7 | E9: =IFERROR(__xludf.DUMMYFUNCTION("IF(IMPORTRANGE(""https://docs.google.com/spreadsheets/d/10OcXjkVvXdQ20Dikey2wLwZD9Qs97Ke_ckzbHR2FA6E/edit?usp=sharing"", ""P1!$B$11"")=1, IFERROR(INDEX(IMPORTRANGE(""https://docs.google.com/spreadsheets/d/10OcXjkVvXdQ20Dikey2wLwZD9Qs97Ke_ckzbHR2FA6E/"&"edit?usp=sharing"", ""P1!$E$6:$BL$6""), MATCH(E3, IMPORTRANGE(""https://docs.google.com/spreadsheets/d/10OcXjkVvXdQ20Dikey2wLwZD9Qs97Ke_ckzbHR2FA6E/edit?usp=sharing"", ""P1!$E$4:$BL$4""), 0)), ""Unknown""), IF(IMPORTRANGE(""https://docs.google."&"com/spreadsheets/d/10OcXjkVvXdQ20Dikey2wLwZD9Qs97Ke_ckzbHR2FA6E/edit?usp=sharing"", ""P1!$B$11"")=2, 0, ""Unknown""))"),24.5705377406331) -> 24.570538 | F9: =IFERROR(__xludf.DUMMYFUNCTION("IF(IMPORTRANGE(""https://docs.google.com/spreadsheets/d/10OcXjkVvXdQ20Dikey2wLwZD9Qs97Ke_ckzbHR2FA6E/edit?usp=sharing"", ""P1!$B$11"")=1, IFERROR(INDEX(IMPORTRANGE(""https://docs.google.com/spreadsheets/d/10OcXjkVvXdQ20Dikey2wLwZD9Qs97Ke_ckzbHR2FA6E/"&"edit?usp=sharing"", ""P1!$E$6:$BL$6""), MATCH(F3, IMPORTRANGE(""https://docs.google.com/spreadsheets/d/10OcXjkVvXdQ20Dikey2wLwZD9Qs97Ke_ckzbHR2FA6E/edit?usp=sharing"", ""P1!$E$4:$BL$4""), 0)), ""Unknown""), IF(IMPORTRANGE(""https://docs.google."&"com/spreadsheets/d/10OcXjkVvXdQ20Dikey2wLwZD9Qs97Ke_ckzbHR2FA6E/edit?usp=sharing"", ""P1!$B$11"")=2, 0, ""Unknown""))"),24.45418742411264) -> 24.454187 | G9: =IFERROR(__xludf.DUMMYFUNCTION("IF(IMPORTRANGE(""https://docs.google.com/spreadsheets/d/10OcXjkVvXdQ20Dikey2wLwZD9Qs97Ke_ckzbHR2FA6E/edit?usp=sharing"", ""P1!$B$11"")=1, IFERROR(INDEX(IMPORTRANGE(""https://docs.google.com/spreadsheets/d/10OcXjkVvXdQ20Dikey2wLwZD9Qs97Ke_ckzbHR2FA6E/"&"edit?usp=sharing"", ""P1!$E$6:$BL$6""), MATCH(G3, IMPORTRANGE(""https://docs.google.com/spreadsheets/d/10OcXjkVvXdQ20Dikey2wLwZD9Qs97Ke_ckzbHR2FA6E/edit?usp=sharing"", ""P1!$E$4:$BL$4""), 0)), ""Unknown""), IF(IMPORTRANGE(""https://docs.google."&"com/spreadsheets/d/10OcXjkVvXdQ20Dikey2wLwZD9Qs97Ke_ckzbHR2FA6E/edit?usp=sharing"", ""P1!$B$11"")=2, 0, ""Unknown""))"),24.32601356359008) -> 24.326014 | H9: =IFERROR(__xludf.DUMMYFUNCTION("IF(IMPORTRANGE(""https://docs.google.com/spreadsheets/d/10OcXjkVvXdQ20Dikey2wLwZD9Qs97Ke_ckzbHR2FA6E/edit?usp=sharing"", ""P1!$B$11"")=1, IFERROR(INDEX(IMPORTRANGE(""https://docs.google.com/spreadsheets/d/10OcXjkVvXdQ20Dikey2wLwZD9Qs97Ke_ckzbHR2FA6E/"&"edit?usp=sharing"", ""P1!$E$6:$BL$6""), MATCH(H3, IMPORTRANGE(""https://docs.google.com/spreadsheets/d/10OcXjkVvXdQ20Dikey2wLwZD9Qs97Ke_ckzbHR2FA6E/edit?usp=sharing"", ""P1!$E$4:$BL$4""), 0)), ""Unknown""), IF(IMPORTRANGE(""https://docs.google."&"com/spreadsheets/d/10OcXjkVvXdQ20Dikey2wLwZD9Qs97Ke_ckzbHR2FA6E/edit?usp=sharing"", ""P1!$B$11"")=2, 0, ""Unknown""))"),24.20261403129571) -> 24.202614 | I9: =IFERROR(__xludf.DUMMYFUNCTION("IF(IMPORTRANGE(""https://docs.google.com/spreadsheets/d/10OcXjkVvXdQ20Dikey2wLwZD9Qs97Ke_ckzbHR2FA6E/edit?usp=sharing"", ""P1!$B$11"")=1, IFERROR(INDEX(IMPORTRANGE(""https://docs.google.com/spreadsheets/d/10OcXjkVvXdQ20Dikey2wLwZD9Qs97Ke_ckzbHR2FA6E/"&"edit?usp=sharing"", ""P1!$E$6:$BL$6""), MATCH(I3, IMPORTRANGE(""https://docs.google.com/spreadsheets/d/10OcXjkVvXdQ20Dikey2wLwZD9Qs97Ke_ckzbHR2FA6E/edit?usp=sharing"", ""P1!$E$4:$BL$4""), 0)), ""Unknown""), IF(IMPORTRANGE(""https://docs.google."&"com/spreadsheets/d/10OcXjkVvXdQ20Dikey2wLwZD9Qs97Ke_ckzbHR2FA6E/edit?usp=sharing"", ""P1!$B$11"")=2, 0, ""Unknown""))"),24.07575876428856) -> 24.075759 | J9: =IFERROR(__xludf.DUMMYFUNCTION("IF(IMPORTRANGE(""https://docs.google.com/spreadsheets/d/10OcXjkVvXdQ20Dikey2wLwZD9Qs97Ke_ckzbHR2FA6E/edit?usp=sharing"", ""P1!$B$11"")=1, IFERROR(INDEX(IMPORTRANGE(""https://docs.google.com/spreadsheets/d/10OcXjkVvXdQ20Dikey2wLwZD9Qs97Ke_ckzbHR2FA6E/"&"edit?usp=sharing"", ""P1!$E$6:$BL$6""), MATCH(J3, IMPORTRANGE(""https://docs.google.com/spreadsheets/d/10OcXjkVvXdQ20Dikey2wLwZD9Qs97Ke_ckzbHR2FA6E/edit?usp=sharing"", ""P1!$E$4:$BL$4""), 0)), ""Unknown""), IF(IMPORTRANGE(""https://docs.google."&"com/spreadsheets/d/10OcXjkVvXdQ20Dikey2wLwZD9Qs97Ke_ckzbHR2FA6E/edit?usp=sharing"", ""P1!$B$11"")=2, 0, ""Unknown""))"),23.953628709424493) -> 23.953629 | K9: =IFERROR(__xludf.DUMMYFUNCTION("IF(IMPORTRANGE(""https://docs.google.com/spreadsheets/d/10OcXjkVvXdQ20Dikey2wLwZD9Qs97Ke_ckzbHR2FA6E/edit?usp=sharing"", ""P1!$B$11"")=1, IFERROR(INDEX(IMPORTRANGE(""https://docs.google.com/spreadsheets/d/10OcXjkVvXdQ20Dikey2wLwZD9Qs97Ke_ckzbHR2FA6E/"&"edit?usp=sharing"", ""P1!$E$6:$BL$6""), MATCH(K3, IMPORTRANGE(""https://docs.google.com/spreadsheets/d/10OcXjkVvXdQ20Dikey2wLwZD9Qs97Ke_ckzbHR2FA6E/edit?usp=sharing"", ""P1!$E$4:$BL$4""), 0)), ""Unknown""), IF(IMPORTRANGE(""https://docs.google."&"com/spreadsheets/d/10OcXjkVvXdQ20Dikey2wLwZD9Qs97Ke_ckzbHR2FA6E/edit?usp=sharing"", ""P1!$B$11"")=2, 0, ""Unknown""))"),23.8280784708513) -> 23.828078 | L9: =IFERROR(__xludf.DUMMYFUNCTION("IF(IMPORTRANGE(""https://docs.google.com/spreadsheets/d/10OcXjkVvXdQ20Dikey2wLwZD9Qs97Ke_ckzbHR2FA6E/edit?usp=sharing"", ""P1!$B$11"")=1, IFERROR(INDEX(IMPORTRANGE(""https://docs.google.com/spreadsheets/d/10OcXjkVvXdQ20Dikey2wLwZD9Qs97Ke_ckzbHR2FA6E/"&"edit?usp=sharing"", ""P1!$E$6:$BL$6""), MATCH(L3, IMPORTRANGE(""https://docs.google.com/spreadsheets/d/10OcXjkVvXdQ20Dikey2wLwZD9Qs97Ke_ckzbHR2FA6E/edit?usp=sharing"", ""P1!$E$4:$BL$4""), 0)), ""Unknown""), IF(IMPORTRANGE(""https://docs.google."&"com/spreadsheets/d/10OcXjkVvXdQ20Dikey2wLwZD9Qs97Ke_ckzbHR2FA6E/edit?usp=sharing"", ""P1!$B$11"")=2, 0, ""Unknown""))"),23.703186289668782) -> 23.703186 | M9: =IFERROR(__xludf.DUMMYFUNCTION("IF(IMPORTRANGE(""https://docs.google.com/spreadsheets/d/10OcXjkVvXdQ20Dikey2wLwZD9Qs97Ke_ckzbHR2FA6E/edit?usp=sharing"", ""P1!$B$11"")=1, IFERROR(INDEX(IMPORTRANGE(""https://docs.google.com/spreadsheets/d/10OcXjkVvXdQ20Dikey2wLwZD9Qs97Ke_ckzbHR2FA6E/"&"edit?usp=sharing"", ""P1!$E$6:$BL$6""), MATCH(M3, IMPORTRANGE(""https://docs.google.com/spreadsheets/d/10OcXjkVvXdQ20Dikey2wLwZD9Qs97Ke_ckzbHR2FA6E/edit?usp=sharing"", ""P1!$E$4:$BL$4""), 0)), ""Unknown""), IF(IMPORTRANGE(""https://docs.google."&"com/spreadsheets/d/10OcXjkVvXdQ20Dikey2wLwZD9Qs97Ke_ckzbHR2FA6E/edit?usp=sharing"", ""P1!$B$11"")=2, 0, ""Unknown""))"),23.582946197950285) -> 23.582946 | N9: =IFERROR(__xludf.DUMMYFUNCTION("IF(IMPORTRANGE(""https://docs.google.com/spreadsheets/d/10OcXjkVvXdQ20Dikey2wLwZD9Qs97Ke_ckzbHR2FA6E/edit?usp=sharing"", ""P1!$B$11"")=1, IFERROR(INDEX(IMPORTRANGE(""https://docs.google.com/spreadsheets/d/10OcXjkVvXdQ20Dikey2wLwZD9Qs97Ke_ckzbHR2FA6E/"&"edit?usp=sharing"", ""P1!$E$6:$BL$6""), MATCH(N3, IMPORTRANGE(""https://docs.google.com/spreadsheets/d/10OcXjkVvXdQ20Dikey2wLwZD9Qs97Ke_ckzbHR2FA6E/edit?usp=sharing"", ""P1!$E$4:$BL$4""), 0)), ""Unknown""), IF(IMPORTRANGE(""https://docs.google."&"com/spreadsheets/d/10OcXjkVvXdQ20Dikey2wLwZD9Qs97Ke_ckzbHR2FA6E/edit?usp=sharing"", ""P1!$B$11"")=2, 0, ""Unknown""))"),23.45933884988087) -> 23.459339 | O9: =IFERROR(__xludf.DUMMYFUNCTION("IF(IMPORTRANGE(""https://docs.google.com/spreadsheets/d/10OcXjkVvXdQ20Dikey2wLwZD9Qs97Ke_ckzbHR2FA6E/edit?usp=sharing"", ""P1!$B$11"")=1, IFERROR(INDEX(IMPORTRANGE(""https://docs.google.com/spreadsheets/d/10OcXjkVvXdQ20Dikey2wLwZD9Qs97Ke_ckzbHR2FA6E/"&"edit?usp=sharing"", ""P1!$E$6:$BL$6""), MATCH(O3, IMPORTRANGE(""https://docs.google.com/spreadsheets/d/10OcXjkVvXdQ20Dikey2wLwZD9Qs97Ke_ckzbHR2FA6E/edit?usp=sharing"", ""P1!$E$4:$BL$4""), 0)), ""Unknown""), IF(IMPORTRANGE(""https://docs.google."&"com/spreadsheets/d/10OcXjkVvXdQ20Dikey2wLwZD9Qs97Ke_ckzbHR2FA6E/edit?usp=sharing"", ""P1!$B$11"")=2, 0, ""Unknown""))"),23.34033573272634) -> 23.340336 | P9: =IFERROR(__xludf.DUMMYFUNCTION("IF(IMPORTRANGE(""https://docs.google.com/spreadsheets/d/10OcXjkVvXdQ20Dikey2wLwZD9Qs97Ke_ckzbHR2FA6E/edit?usp=sharing"", ""P1!$B$11"")=1, IFERROR(INDEX(IMPORTRANGE(""https://docs.google.com/spreadsheets/d/10OcXjkVvXdQ20Dikey2wLwZD9Qs97Ke_ckzbHR2FA6E/"&"edit?usp=sharing"", ""P1!$E$6:$BL$6""), MATCH(P3, IMPORTRANGE(""https://docs.google.com/spreadsheets/d/10OcXjkVvXdQ20Dikey2wLwZD9Qs97Ke_ckzbHR2FA6E/edit?usp=sharing"", ""P1!$E$4:$BL$4""), 0)), ""Unknown""), IF(IMPORTRANGE(""https://docs.google."&"com/spreadsheets/d/10OcXjkVvXdQ20Dikey2wLwZD9Qs97Ke_ckzbHR2FA6E/edit?usp=sharing"", ""P1!$B$11"")=2, 0, ""Unknown""))"),23.217999999999996) -> 23.218 | Q9: =IFERROR(__xludf.DUMMYFUNCTION("IF(IMPORTRANGE(""https://docs.google.com/spreadsheets/d/10OcXjkVvXdQ20Dikey2wLwZD9Qs97Ke_ckzbHR2FA6E/edit?usp=sharing"", ""P1!$B$11"")=1, IFERROR(INDEX(IMPORTRANGE(""https://docs.google.com/spreadsheets/d/10OcXjkVvXdQ20Dikey2wLwZD9Qs97Ke_ckzbHR2FA6E/"&"edit?usp=sharing"", ""P1!$E$6:$BL$6""), MATCH(Q3, IMPORTRANGE(""https://docs.google.com/spreadsheets/d/10OcXjkVvXdQ20Dikey2wLwZD9Qs97Ke_ckzbHR2FA6E/edit?usp=sharing"", ""P1!$E$4:$BL$4""), 0)), ""Unknown""), IF(IMPORTRANGE(""https://docs.google."&"com/spreadsheets/d/10OcXjkVvXdQ20Dikey2wLwZD9Qs97Ke_ckzbHR2FA6E/edit?usp=sharing"", ""P1!$B$11"")=2, 0, ""Unknown""))"),23.096305476195113) -> 23.096305 | R9: =IFERROR(__xludf.DUMMYFUNCTION("IF(IMPORTRANGE(""https://docs.google.com/spreadsheets/d/10OcXjkVvXdQ20Dikey2wLwZD9Qs97Ke_ckzbHR2FA6E/edit?usp=sharing"", ""P1!$B$11"")=1, IFERROR(INDEX(IMPORTRANGE(""https://docs.google.com/spreadsheets/d/10OcXjkVvXdQ20Dikey2wLwZD9Qs97Ke_ckzbHR2FA6E/"&"edit?usp=sharing"", ""P1!$E$6:$BL$6""), MATCH(R3, IMPORTRANGE(""https://docs.google.com/spreadsheets/d/10OcXjkVvXdQ20Dikey2wLwZD9Qs97Ke_ckzbHR2FA6E/edit?usp=sharing"", ""P1!$E$4:$BL$4""), 0)), ""Unknown""), IF(IMPORTRANGE(""https://docs.google."&"com/spreadsheets/d/10OcXjkVvXdQ20Dikey2wLwZD9Qs97Ke_ckzbHR2FA6E/edit?usp=sharing"", ""P1!$B$11"")=2, 0, ""Unknown""))"),22.98693617866588) -> 22.986936 | S9: =IFERROR(__xludf.DUMMYFUNCTION("IF(IMPORTRANGE(""https://docs.google.com/spreadsheets/d/10OcXjkVvXdQ20Dikey2wLwZD9Qs97Ke_ckzbHR2FA6E/edit?usp=sharing"", ""P1!$B$11"")=1, IFERROR(INDEX(IMPORTRANGE(""https://docs.google.com/spreadsheets/d/10OcXjkVvXdQ20Dikey2wLwZD9Qs97Ke_ckzbHR2FA6E/"&"edit?usp=sharing"", ""P1!$E$6:$BL$6""), MATCH(S3, IMPORTRANGE(""https://docs.google.com/spreadsheets/d/10OcXjkVvXdQ20Dikey2wLwZD9Qs97Ke_ckzbHR2FA6E/edit?usp=sharing"", ""P1!$E$4:$BL$4""), 0)), ""Unknown""), IF(IMPORTRANGE(""https://docs.google."&"com/spreadsheets/d/10OcXjkVvXdQ20Dikey2wLwZD9Qs97Ke_ckzbHR2FA6E/edit?usp=sharing"", ""P1!$B$11"")=2, 0, ""Unknown""))"),22.866452749774673) -> 22.866453 | T9: =IFERROR(__xludf.DUMMYFUNCTION("IF(IMPORTRANGE(""https://docs.google.com/spreadsheets/d/10OcXjkVvXdQ20Dikey2wLwZD9Qs97Ke_ckzbHR2FA6E/edit?usp=sharing"", ""P1!$B$11"")=1, IFERROR(INDEX(IMPORTRANGE(""https://docs.google.com/spreadsheets/d/10OcXjkVvXdQ20Dikey2wLwZD9Qs97Ke_ckzbHR2FA6E/"&"edit?usp=sharing"", ""P1!$E$6:$BL$6""), MATCH(T3, IMPORTRANGE(""https://docs.google.com/spreadsheets/d/10OcXjkVvXdQ20Dikey2wLwZD9Qs97Ke_ckzbHR2FA6E/edit?usp=sharing"", ""P1!$E$4:$BL$4""), 0)), ""Unknown""), IF(IMPORTRANGE(""https://docs.google."&"com/spreadsheets/d/10OcXjkVvXdQ20Dikey2wLwZD9Qs97Ke_ckzbHR2FA6E/edit?usp=sharing"", ""P1!$B$11"")=2, 0, ""Unknown""))"),22.750457189417965) -> 22.750457 | U9: =IFERROR(__xludf.DUMMYFUNCTION("IF(IMPORTRANGE(""https://docs.google.com/spreadsheets/d/10OcXjkVvXdQ20Dikey2wLwZD9Qs97Ke_ckzbHR2FA6E/edit?usp=sharing"", ""P1!$B$11"")=1, IFERROR(INDEX(IMPORTRANGE(""https://docs.google.com/spreadsheets/d/10OcXjkVvXdQ20Dikey2wLwZD9Qs97Ke_ckzbHR2FA6E/"&"edit?usp=sharing"", ""P1!$E$6:$BL$6""), MATCH(U3, IMPORTRANGE(""https://docs.google.com/spreadsheets/d/10OcXjkVvXdQ20Dikey2wLwZD9Qs97Ke_ckzbHR2FA6E/edit?usp=sharing"", ""P1!$E$4:$BL$4""), 0)), ""Unknown""), IF(IMPORTRANGE(""https://docs.google."&"com/spreadsheets/d/10OcXjkVvXdQ20Dikey2wLwZD9Qs97Ke_ckzbHR2FA6E/edit?usp=sharing"", ""P1!$B$11"")=2, 0, ""Unknown""))"),22.631213238431247) -> 22.631213 | V9: =IFERROR(__xludf.DUMMYFUNCTION("IF(IMPORTRANGE(""https://docs.google.com/spreadsheets/d/10OcXjkVvXdQ20Dikey2wLwZD9Qs97Ke_ckzbHR2FA6E/edit?usp=sharing"", ""P1!$B$11"")=1, IFERROR(INDEX(IMPORTRANGE(""https://docs.google.com/spreadsheets/d/10OcXjkVvXdQ20Dikey2wLwZD9Qs97Ke_ckzbHR2FA6E/"&"edit?usp=sharing"", ""P1!$E$6:$BL$6""), MATCH(V3, IMPORTRANGE(""https://docs.google.com/spreadsheets/d/10OcXjkVvXdQ20Dikey2wLwZD9Qs97Ke_ckzbHR2FA6E/edit?usp=sharing"", ""P1!$E$4:$BL$4""), 0)), ""Unknown""), IF(IMPORTRANGE(""https://docs.google."&"com/spreadsheets/d/10OcXjkVvXdQ20Dikey2wLwZD9Qs97Ke_ckzbHR2FA6E/edit?usp=sharing"", ""P1!$B$11"")=2, 0, ""Unknown""))"),22.51641098685902) -> 22.516411 | W9: =IFERROR(__xludf.DUMMYFUNCTION("IF(IMPORTRANGE(""https://docs.google.com/spreadsheets/d/10OcXjkVvXdQ20Dikey2wLwZD9Qs97Ke_ckzbHR2FA6E/edit?usp=sharing"", ""P1!$B$11"")=1, IFERROR(INDEX(IMPORTRANGE(""https://docs.google.com/spreadsheets/d/10OcXjkVvXdQ20Dikey2wLwZD9Qs97Ke_ckzbHR2FA6E/"&"edit?usp=sharing"", ""P1!$E$6:$BL$6""), MATCH(W3, IMPORTRANGE(""https://docs.google.com/spreadsheets/d/10OcXjkVvXdQ20Dikey2wLwZD9Qs97Ke_ckzbHR2FA6E/edit?usp=sharing"", ""P1!$E$4:$BL$4""), 0)), ""Unknown""), IF(IMPORTRANGE(""https://docs.google."&"com/spreadsheets/d/10OcXjkVvXdQ20Dikey2wLwZD9Qs97Ke_ckzbHR2FA6E/edit?usp=sharing"", ""P1!$B$11"")=2, 0, ""Unknown""))"),22.39839376260022) -> 22.398394 | X9: =IFERROR(__xludf.DUMMYFUNCTION("IF(IMPORTRANGE(""https://docs.google.com/spreadsheets/d/10OcXjkVvXdQ20Dikey2wLwZD9Qs97Ke_ckzbHR2FA6E/edit?usp=sharing"", ""P1!$B$11"")=1, IFERROR(INDEX(IMPORTRANGE(""https://docs.google.com/spreadsheets/d/10OcXjkVvXdQ20Dikey2wLwZD9Qs97Ke_ckzbHR2FA6E/"&"edit?usp=sharing"", ""P1!$E$6:$BL$6""), MATCH(X3, IMPORTRANGE(""https://docs.google.com/spreadsheets/d/10OcXjkVvXdQ20Dikey2wLwZD9Qs97Ke_ckzbHR2FA6E/edit?usp=sharing"", ""P1!$E$4:$BL$4""), 0)), ""Unknown""), IF(IMPORTRANGE(""https://docs.google."&"com/spreadsheets/d/10OcXjkVvXdQ20Dikey2wLwZD9Qs97Ke_ckzbHR2FA6E/edit?usp=sharing"", ""P1!$B$11"")=2, 0, ""Unknown""))"),22.280995112288654) -> 22.280995 | Y9: =IFERROR(__xludf.DUMMYFUNCTION("IF(IMPORTRANGE(""https://docs.google.com/spreadsheets/d/10OcXjkVvXdQ20Dikey2wLwZD9Qs97Ke_ckzbHR2FA6E/edit?usp=sharing"", ""P1!$B$11"")=1, IFERROR(INDEX(IMPORTRANGE(""https://docs.google.com/spreadsheets/d/10OcXjkVvXdQ20Dikey2wLwZD9Qs97Ke_ckzbHR2FA6E/"&"edit?usp=sharing"", ""P1!$E$6:$BL$6""), MATCH(Y3, IMPORTRANGE(""https://docs.google.com/spreadsheets/d/10OcXjkVvXdQ20Dikey2wLwZD9Qs97Ke_ckzbHR2FA6E/edit?usp=sharing"", ""P1!$E$4:$BL$4""), 0)), ""Unknown""), IF(IMPORTRANGE(""https://docs.google."&"com/spreadsheets/d/10OcXjkVvXdQ20Dikey2wLwZD9Qs97Ke_ckzbHR2FA6E/edit?usp=sharing"", ""P1!$B$11"")=2, 0, ""Unknown""))"),22.16796942607327) -> 22.167969 | Z9: =IFERROR(__xludf.DUMMYFUNCTION("IF(IMPORTRANGE(""https://docs.google.com/spreadsheets/d/10OcXjkVvXdQ20Dikey2wLwZD9Qs97Ke_ckzbHR2FA6E/edit?usp=sharing"", ""P1!$B$11"")=1, IFERROR(INDEX(IMPORTRANGE(""https://docs.google.com/spreadsheets/d/10OcXjkVvXdQ20Dikey2wLwZD9Qs97Ke_ckzbHR2FA6E/"&"edit?usp=sharing"", ""P1!$E$6:$BL$6""), MATCH(Z3, IMPORTRANGE(""https://docs.google.com/spreadsheets/d/10OcXjkVvXdQ20Dikey2wLwZD9Qs97Ke_ckzbHR2FA6E/edit?usp=sharing"", ""P1!$E$4:$BL$4""), 0)), ""Unknown""), IF(IMPORTRANGE(""https://docs.google."&"com/spreadsheets/d/10OcXjkVvXdQ20Dikey2wLwZD9Qs97Ke_ckzbHR2FA6E/edit?usp=sharing"", ""P1!$B$11"")=2, 0, ""Unknown""))"),22.051778518888014) -> 22.051779 | AA9: =IFERROR(__xludf.DUMMYFUNCTION("IF(IMPORTRANGE(""https://docs.google.com/spreadsheets/d/10OcXjkVvXdQ20Dikey2wLwZD9Qs97Ke_ckzbHR2FA6E/edit?usp=sharing"", ""P1!$B$11"")=1, IFERROR(INDEX(IMPORTRANGE(""https://docs.google.com/spreadsheets/d/10OcXjkVvXdQ20Dikey2wLwZD9Qs97Ke_ckzbHR2FA6E/"&"edit?usp=sharing"", ""P1!$E$6:$BL$6""), MATCH(AA3, IMPORTRANGE(""https://docs.google.com/spreadsheets/d/10OcXjkVvXdQ20Dikey2wLwZD9Qs97Ke_ckzbHR2FA6E/edit?usp=sharing"", ""P1!$E$4:$BL$4""), 0)), ""Unknown""), IF(IMPORTRANGE(""https://docs.google"&".com/spreadsheets/d/10OcXjkVvXdQ20Dikey2wLwZD9Qs97Ke_ckzbHR2FA6E/edit?usp=sharing"", ""P1!$B$11"")=2, 0, ""Unknown""))"),21.93991558876276) -> 21.939916 | AB9: =IFERROR(__xludf.DUMMYFUNCTION("IF(IMPORTRANGE(""https://docs.google.com/spreadsheets/d/10OcXjkVvXdQ20Dikey2wLwZD9Qs97Ke_ckzbHR2FA6E/edit?usp=sharing"", ""P1!$B$11"")=1, IFERROR(INDEX(IMPORTRANGE(""https://docs.google.com/spreadsheets/d/10OcXjkVvXdQ20Dikey2wLwZD9Qs97Ke_ckzbHR2FA6E/"&"edit?usp=sharing"", ""P1!$E$6:$BL$6""), MATCH(AB3, IMPORTRANGE(""https://docs.google.com/spreadsheets/d/10OcXjkVvXdQ20Dikey2wLwZD9Qs97Ke_ckzbHR2FA6E/edit?usp=sharing"", ""P1!$E$4:$BL$4""), 0)), ""Unknown""), IF(IMPORTRANGE(""https://docs.google"&".com/spreadsheets/d/10OcXjkVvXdQ20Dikey2wLwZD9Qs97Ke_ckzbHR2FA6E/edit?usp=sharing"", ""P1!$B$11"")=2, 0, ""Unknown""))"),21.82492) -> 21.82492 | AC9: =IFERROR(__xludf.DUMMYFUNCTION("IF(IMPORTRANGE(""https://docs.google.com/spreadsheets/d/10OcXjkVvXdQ20Dikey2wLwZD9Qs97Ke_ckzbHR2FA6E/edit?usp=sharing"", ""P1!$B$11"")=1, IFERROR(INDEX(IMPORTRANGE(""https://docs.google.com/spreadsheets/d/10OcXjkVvXdQ20Dikey2wLwZD9Qs97Ke_ckzbHR2FA6E/"&"edit?usp=sharing"", ""P1!$E$6:$BL$6""), MATCH(AC3, IMPORTRANGE(""https://docs.google.com/spreadsheets/d/10OcXjkVvXdQ20Dikey2wLwZD9Qs97Ke_ckzbHR2FA6E/edit?usp=sharing"", ""P1!$E$4:$BL$4""), 0)), ""Unknown""), IF(IMPORTRANGE(""https://docs.google"&".com/spreadsheets/d/10OcXjkVvXdQ20Dikey2wLwZD9Qs97Ke_ckzbHR2FA6E/edit?usp=sharing"", ""P1!$B$11"")=2, 0, ""Unknown""))"),21.710527147623406) -> 21.710527 | AD9: =IFERROR(__xludf.DUMMYFUNCTION("IF(IMPORTRANGE(""https://docs.google.com/spreadsheets/d/10OcXjkVvXdQ20Dikey2wLwZD9Qs97Ke_ckzbHR2FA6E/edit?usp=sharing"", ""P1!$B$11"")=1, IFERROR(INDEX(IMPORTRANGE(""https://docs.google.com/spreadsheets/d/10OcXjkVvXdQ20Dikey2wLwZD9Qs97Ke_ckzbHR2FA6E/"&"edit?usp=sharing"", ""P1!$E$6:$BL$6""), MATCH(AD3, IMPORTRANGE(""https://docs.google.com/spreadsheets/d/10OcXjkVvXdQ20Dikey2wLwZD9Qs97Ke_ckzbHR2FA6E/edit?usp=sharing"", ""P1!$E$4:$BL$4""), 0)), ""Unknown""), IF(IMPORTRANGE(""https://docs.google"&".com/spreadsheets/d/10OcXjkVvXdQ20Dikey2wLwZD9Qs97Ke_ckzbHR2FA6E/edit?usp=sharing"", ""P1!$B$11"")=2, 0, ""Unknown""))"),21.607720007945925) -> 21.60772 | AE9: =IFERROR(__xludf.DUMMYFUNCTION("IF(IMPORTRANGE(""https://docs.google.com/spreadsheets/d/10OcXjkVvXdQ20Dikey2wLwZD9Qs97Ke_ckzbHR2FA6E/edit?usp=sharing"", ""P1!$B$11"")=1, IFERROR(INDEX(IMPORTRANGE(""https://docs.google.com/spreadsheets/d/10OcXjkVvXdQ20Dikey2wLwZD9Qs97Ke_ckzbHR2FA6E/"&"edit?usp=sharing"", ""P1!$E$6:$BL$6""), MATCH(AE3, IMPORTRANGE(""https://docs.google.com/spreadsheets/d/10OcXjkVvXdQ20Dikey2wLwZD9Qs97Ke_ckzbHR2FA6E/edit?usp=sharing"", ""P1!$E$4:$BL$4""), 0)), ""Unknown""), IF(IMPORTRANGE(""https://docs.google"&".com/spreadsheets/d/10OcXjkVvXdQ20Dikey2wLwZD9Qs97Ke_ckzbHR2FA6E/edit?usp=sharing"", ""P1!$B$11"")=2, 0, ""Unknown""))"),21.494465584788195) -> 21.494466 | AF9: =IFERROR(__xludf.DUMMYFUNCTION("IF(IMPORTRANGE(""https://docs.google.com/spreadsheets/d/10OcXjkVvXdQ20Dikey2wLwZD9Qs97Ke_ckzbHR2FA6E/edit?usp=sharing"", ""P1!$B$11"")=1, IFERROR(INDEX(IMPORTRANGE(""https://docs.google.com/spreadsheets/d/10OcXjkVvXdQ20Dikey2wLwZD9Qs97Ke_ckzbHR2FA6E/"&"edit?usp=sharing"", ""P1!$E$6:$BL$6""), MATCH(AF3, IMPORTRANGE(""https://docs.google.com/spreadsheets/d/10OcXjkVvXdQ20Dikey2wLwZD9Qs97Ke_ckzbHR2FA6E/edit?usp=sharing"", ""P1!$E$4:$BL$4""), 0)), ""Unknown""), IF(IMPORTRANGE(""https://docs.google"&".com/spreadsheets/d/10OcXjkVvXdQ20Dikey2wLwZD9Qs97Ke_ckzbHR2FA6E/edit?usp=sharing"", ""P1!$B$11"")=2, 0, ""Unknown""))"),21.385429758052886) -> 21.38543 | AG9: =IFERROR(__xludf.DUMMYFUNCTION("IF(IMPORTRANGE(""https://docs.google.com/spreadsheets/d/10OcXjkVvXdQ20Dikey2wLwZD9Qs97Ke_ckzbHR2FA6E/edit?usp=sharing"", ""P1!$B$11"")=1, IFERROR(INDEX(IMPORTRANGE(""https://docs.google.com/spreadsheets/d/10OcXjkVvXdQ20Dikey2wLwZD9Qs97Ke_ckzbHR2FA6E/"&"edit?usp=sharing"", ""P1!$E$6:$BL$6""), MATCH(AG3, IMPORTRANGE(""https://docs.google.com/spreadsheets/d/10OcXjkVvXdQ20Dikey2wLwZD9Qs97Ke_ckzbHR2FA6E/edit?usp=sharing"", ""P1!$E$4:$BL$4""), 0)), ""Unknown""), IF(IMPORTRANGE(""https://docs.google"&".com/spreadsheets/d/10OcXjkVvXdQ20Dikey2wLwZD9Qs97Ke_ckzbHR2FA6E/edit?usp=sharing"", ""P1!$B$11"")=2, 0, ""Unknown""))"),21.27334044412537) -> 21.27334 | AH9: =IFERROR(__xludf.DUMMYFUNCTION("IF(IMPORTRANGE(""https://docs.google.com/spreadsheets/d/10OcXjkVvXdQ20Dikey2wLwZD9Qs97Ke_ckzbHR2FA6E/edit?usp=sharing"", ""P1!$B$11"")=1, IFERROR(INDEX(IMPORTRANGE(""https://docs.google.com/spreadsheets/d/10OcXjkVvXdQ20Dikey2wLwZD9Qs97Ke_ckzbHR2FA6E/"&"edit?usp=sharing"", ""P1!$E$6:$BL$6""), MATCH(AH3, IMPORTRANGE(""https://docs.google.com/spreadsheets/d/10OcXjkVvXdQ20Dikey2wLwZD9Qs97Ke_ckzbHR2FA6E/edit?usp=sharing"", ""P1!$E$4:$BL$4""), 0)), ""Unknown""), IF(IMPORTRANGE(""https://docs.google"&".com/spreadsheets/d/10OcXjkVvXdQ20Dikey2wLwZD9Qs97Ke_ckzbHR2FA6E/edit?usp=sharing"", ""P1!$B$11"")=2, 0, ""Unknown""))"),21.16542632764748) -> 21.165426 | AI9: =IFERROR(__xludf.DUMMYFUNCTION("IF(IMPORTRANGE(""https://docs.google.com/spreadsheets/d/10OcXjkVvXdQ20Dikey2wLwZD9Qs97Ke_ckzbHR2FA6E/edit?usp=sharing"", ""P1!$B$11"")=1, IFERROR(INDEX(IMPORTRANGE(""https://docs.google.com/spreadsheets/d/10OcXjkVvXdQ20Dikey2wLwZD9Qs97Ke_ckzbHR2FA6E/"&"edit?usp=sharing"", ""P1!$E$6:$BL$6""), MATCH(AI3, IMPORTRANGE(""https://docs.google.com/spreadsheets/d/10OcXjkVvXdQ20Dikey2wLwZD9Qs97Ke_ckzbHR2FA6E/edit?usp=sharing"", ""P1!$E$4:$BL$4""), 0)), ""Unknown""), IF(IMPORTRANGE(""https://docs.google"&".com/spreadsheets/d/10OcXjkVvXdQ20Dikey2wLwZD9Qs97Ke_ckzbHR2FA6E/edit?usp=sharing"", ""P1!$B$11"")=2, 0, ""Unknown""))"),21.054490136844205) -> 21.05449 | AJ9: =IFERROR(__xludf.DUMMYFUNCTION("IF(IMPORTRANGE(""https://docs.google.com/spreadsheets/d/10OcXjkVvXdQ20Dikey2wLwZD9Qs97Ke_ckzbHR2FA6E/edit?usp=sharing"", ""P1!$B$11"")=1, IFERROR(INDEX(IMPORTRANGE(""https://docs.google.com/spreadsheets/d/10OcXjkVvXdQ20Dikey2wLwZD9Qs97Ke_ckzbHR2FA6E/"&"edit?usp=sharing"", ""P1!$E$6:$BL$6""), MATCH(AJ3, IMPORTRANGE(""https://docs.google.com/spreadsheets/d/10OcXjkVvXdQ20Dikey2wLwZD9Qs97Ke_ckzbHR2FA6E/edit?usp=sharing"", ""P1!$E$4:$BL$4""), 0)), ""Unknown""), IF(IMPORTRANGE(""https://docs.google"&".com/spreadsheets/d/10OcXjkVvXdQ20Dikey2wLwZD9Qs97Ke_ckzbHR2FA6E/edit?usp=sharing"", ""P1!$B$11"")=2, 0, ""Unknown""))"),20.944135405551336) -> 20.944135 | AK9: =IFERROR(__xludf.DUMMYFUNCTION("IF(IMPORTRANGE(""https://docs.google.com/spreadsheets/d/10OcXjkVvXdQ20Dikey2wLwZD9Qs97Ke_ckzbHR2FA6E/edit?usp=sharing"", ""P1!$B$11"")=1, IFERROR(INDEX(IMPORTRANGE(""https://docs.google.com/spreadsheets/d/10OcXjkVvXdQ20Dikey2wLwZD9Qs97Ke_ckzbHR2FA6E/"&"edit?usp=sharing"", ""P1!$E$6:$BL$6""), MATCH(AK3, IMPORTRANGE(""https://docs.google.com/spreadsheets/d/10OcXjkVvXdQ20Dikey2wLwZD9Qs97Ke_ckzbHR2FA6E/edit?usp=sharing"", ""P1!$E$4:$BL$4""), 0)), ""Unknown""), IF(IMPORTRANGE(""https://docs.google"&".com/spreadsheets/d/10OcXjkVvXdQ20Dikey2wLwZD9Qs97Ke_ckzbHR2FA6E/edit?usp=sharing"", ""P1!$B$11"")=2, 0, ""Unknown""))"),20.837891260508872) -> 20.837891 | AL9: =IFERROR(__xludf.DUMMYFUNCTION("IF(IMPORTRANGE(""https://docs.google.com/spreadsheets/d/10OcXjkVvXdQ20Dikey2wLwZD9Qs97Ke_ckzbHR2FA6E/edit?usp=sharing"", ""P1!$B$11"")=1, IFERROR(INDEX(IMPORTRANGE(""https://docs.google.com/spreadsheets/d/10OcXjkVvXdQ20Dikey2wLwZD9Qs97Ke_ckzbHR2FA6E/"&"edit?usp=sharing"", ""P1!$E$6:$BL$6""), MATCH(AL3, IMPORTRANGE(""https://docs.google.com/spreadsheets/d/10OcXjkVvXdQ20Dikey2wLwZD9Qs97Ke_ckzbHR2FA6E/edit?usp=sharing"", ""P1!$E$4:$BL$4""), 0)), ""Unknown""), IF(IMPORTRANGE(""https://docs.google"&".com/spreadsheets/d/10OcXjkVvXdQ20Dikey2wLwZD9Qs97Ke_ckzbHR2FA6E/edit?usp=sharing"", ""P1!$B$11"")=2, 0, ""Unknown""))"),20.728671807754733) -> 20.728672 | AM9: =IFERROR(__xludf.DUMMYFUNCTION("IF(IMPORTRANGE(""https://docs.google.com/spreadsheets/d/10OcXjkVvXdQ20Dikey2wLwZD9Qs97Ke_ckzbHR2FA6E/edit?usp=sharing"", ""P1!$B$11"")=1, IFERROR(INDEX(IMPORTRANGE(""https://docs.google.com/spreadsheets/d/10OcXjkVvXdQ20Dikey2wLwZD9Qs97Ke_ckzbHR2FA6E/"&"edit?usp=sharing"", ""P1!$E$6:$BL$6""), MATCH(AM3, IMPORTRANGE(""https://docs.google.com/spreadsheets/d/10OcXjkVvXdQ20Dikey2wLwZD9Qs97Ke_ckzbHR2FA6E/edit?usp=sharing"", ""P1!$E$4:$BL$4""), 0)), ""Unknown""), IF(IMPORTRANGE(""https://docs.google"&".com/spreadsheets/d/10OcXjkVvXdQ20Dikey2wLwZD9Qs97Ke_ckzbHR2FA6E/edit?usp=sharing"", ""P1!$B$11"")=2, 0, ""Unknown""))"),20.623520653436994) -> 20.623521 | AN9: =IFERROR(__xludf.DUMMYFUNCTION("IF(IMPORTRANGE(""https://docs.google.com/spreadsheets/d/10OcXjkVvXdQ20Dikey2wLwZD9Qs97Ke_ckzbHR2FA6E/edit?usp=sharing"", ""P1!$B$11"")=1, IFERROR(INDEX(IMPORTRANGE(""https://docs.google.com/spreadsheets/d/10OcXjkVvXdQ20Dikey2wLwZD9Qs97Ke_ckzbHR2FA6E/"&"edit?usp=sharing"", ""P1!$E$6:$BL$6""), MATCH(AN3, IMPORTRANGE(""https://docs.google.com/spreadsheets/d/10OcXjkVvXdQ20Dikey2wLwZD9Qs97Ke_ckzbHR2FA6E/edit?usp=sharing"", ""P1!$E$4:$BL$4""), 0)), ""Unknown""), IF(IMPORTRANGE(""https://docs.google"&".com/spreadsheets/d/10OcXjkVvXdQ20Dikey2wLwZD9Qs97Ke_ckzbHR2FA6E/edit?usp=sharing"", ""P1!$B$11"")=2, 0, ""Unknown""))"),20.515424799999998) -> 20.515425 | AO9: =IFERROR(__xludf.DUMMYFUNCTION("IF(IMPORTRANGE(""https://docs.google.com/spreadsheets/d/10OcXjkVvXdQ20Dikey2wLwZD9Qs97Ke_ckzbHR2FA6E/edit?usp=sharing"", ""P1!$B$11"")=1, IFERROR(INDEX(IMPORTRANGE(""https://docs.google.com/spreadsheets/d/10OcXjkVvXdQ20Dikey2wLwZD9Qs97Ke_ckzbHR2FA6E/"&"edit?usp=sharing"", ""P1!$E$6:$BL$6""), MATCH(AO3, IMPORTRANGE(""https://docs.google.com/spreadsheets/d/10OcXjkVvXdQ20Dikey2wLwZD9Qs97Ke_ckzbHR2FA6E/edit?usp=sharing"", ""P1!$E$4:$BL$4""), 0)), ""Unknown""), IF(IMPORTRANGE(""https://docs.google"&".com/spreadsheets/d/10OcXjkVvXdQ20Dikey2wLwZD9Qs97Ke_ckzbHR2FA6E/edit?usp=sharing"", ""P1!$B$11"")=2, 0, ""Unknown""))"),20.407895518766) -> 20.407896 | AP9: =IFERROR(__xludf.DUMMYFUNCTION("IF(IMPORTRANGE(""https://docs.google.com/spreadsheets/d/10OcXjkVvXdQ20Dikey2wLwZD9Qs97Ke_ckzbHR2FA6E/edit?usp=sharing"", ""P1!$B$11"")=1, IFERROR(INDEX(IMPORTRANGE(""https://docs.google.com/spreadsheets/d/10OcXjkVvXdQ20Dikey2wLwZD9Qs97Ke_ckzbHR2FA6E/"&"edit?usp=sharing"", ""P1!$E$6:$BL$6""), MATCH(AP3, IMPORTRANGE(""https://docs.google.com/spreadsheets/d/10OcXjkVvXdQ20Dikey2wLwZD9Qs97Ke_ckzbHR2FA6E/edit?usp=sharing"", ""P1!$E$4:$BL$4""), 0)), ""Unknown""), IF(IMPORTRANGE(""https://docs.google"&".com/spreadsheets/d/10OcXjkVvXdQ20Dikey2wLwZD9Qs97Ke_ckzbHR2FA6E/edit?usp=sharing"", ""P1!$B$11"")=2, 0, ""Unknown""))"),20.307813901451702) -> 20.307814 | AQ9: =IFERROR(__xludf.DUMMYFUNCTION("IF(IMPORTRANGE(""https://docs.google.com/spreadsheets/d/10OcXjkVvXdQ20Dikey2wLwZD9Qs97Ke_ckzbHR2FA6E/edit?usp=sharing"", ""P1!$B$11"")=1, IFERROR(INDEX(IMPORTRANGE(""https://docs.google.com/spreadsheets/d/10OcXjkVvXdQ20Dikey2wLwZD9Qs97Ke_ckzbHR2FA6E/"&"edit?usp=sharing"", ""P1!$E$6:$BL$6""), MATCH(AQ3, IMPORTRANGE(""https://docs.google.com/spreadsheets/d/10OcXjkVvXdQ20Dikey2wLwZD9Qs97Ke_ckzbHR2FA6E/edit?usp=sharing"", ""P1!$E$4:$BL$4""), 0)), ""Unknown""), IF(IMPORTRANGE(""https://docs.google"&".com/spreadsheets/d/10OcXjkVvXdQ20Dikey2wLwZD9Qs97Ke_ckzbHR2FA6E/edit?usp=sharing"", ""P1!$B$11"")=2, 0, ""Unknown""))"),20.201372789286342) -> 20.201373 | AR9: =IFERROR(__xludf.DUMMYFUNCTION("IF(IMPORTRANGE(""https://docs.google.com/spreadsheets/d/10OcXjkVvXdQ20Dikey2wLwZD9Qs97Ke_ckzbHR2FA6E/edit?usp=sharing"", ""P1!$B$11"")=1, IFERROR(INDEX(IMPORTRANGE(""https://docs.google.com/spreadsheets/d/10OcXjkVvXdQ20Dikey2wLwZD9Qs97Ke_ckzbHR2FA6E/"&"edit?usp=sharing"", ""P1!$E$6:$BL$6""), MATCH(AR3, IMPORTRANGE(""https://docs.google.com/spreadsheets/d/10OcXjkVvXdQ20Dikey2wLwZD9Qs97Ke_ckzbHR2FA6E/edit?usp=sharing"", ""P1!$E$4:$BL$4""), 0)), ""Unknown""), IF(IMPORTRANGE(""https://docs.google"&".com/spreadsheets/d/10OcXjkVvXdQ20Dikey2wLwZD9Qs97Ke_ckzbHR2FA6E/edit?usp=sharing"", ""P1!$B$11"")=2, 0, ""Unknown""))"),20.098896485580198) -> 20.098896 | AS9: =IFERROR(__xludf.DUMMYFUNCTION("IF(IMPORTRANGE(""https://docs.google.com/spreadsheets/d/10OcXjkVvXdQ20Dikey2wLwZD9Qs97Ke_ckzbHR2FA6E/edit?usp=sharing"", ""P1!$B$11"")=1, IFERROR(INDEX(IMPORTRANGE(""https://docs.google.com/spreadsheets/d/10OcXjkVvXdQ20Dikey2wLwZD9Qs97Ke_ckzbHR2FA6E/"&"edit?usp=sharing"", ""P1!$E$6:$BL$6""), MATCH(AS3, IMPORTRANGE(""https://docs.google.com/spreadsheets/d/10OcXjkVvXdQ20Dikey2wLwZD9Qs97Ke_ckzbHR2FA6E/edit?usp=sharing"", ""P1!$E$4:$BL$4""), 0)), ""Unknown""), IF(IMPORTRANGE(""https://docs.google"&".com/spreadsheets/d/10OcXjkVvXdQ20Dikey2wLwZD9Qs97Ke_ckzbHR2FA6E/edit?usp=sharing"", ""P1!$B$11"")=2, 0, ""Unknown""))"),19.993550390446412) -> 19.99355 | AT9: =IFERROR(__xludf.DUMMYFUNCTION("IF(IMPORTRANGE(""https://docs.google.com/spreadsheets/d/10OcXjkVvXdQ20Dikey2wLwZD9Qs97Ke_ckzbHR2FA6E/edit?usp=sharing"", ""P1!$B$11"")=1, IFERROR(INDEX(IMPORTRANGE(""https://docs.google.com/spreadsheets/d/10OcXjkVvXdQ20Dikey2wLwZD9Qs97Ke_ckzbHR2FA6E/"&"edit?usp=sharing"", ""P1!$E$6:$BL$6""), MATCH(AT3, IMPORTRANGE(""https://docs.google.com/spreadsheets/d/10OcXjkVvXdQ20Dikey2wLwZD9Qs97Ke_ckzbHR2FA6E/edit?usp=sharing"", ""P1!$E$4:$BL$4""), 0)), ""Unknown""), IF(IMPORTRANGE(""https://docs.google"&".com/spreadsheets/d/10OcXjkVvXdQ20Dikey2wLwZD9Qs97Ke_ckzbHR2FA6E/edit?usp=sharing"", ""P1!$B$11"")=2, 0, ""Unknown""))"),19.89212831565246) -> 19.892128 | AU9: =IFERROR(__xludf.DUMMYFUNCTION("IF(IMPORTRANGE(""https://docs.google.com/spreadsheets/d/10OcXjkVvXdQ20Dikey2wLwZD9Qs97Ke_ckzbHR2FA6E/edit?usp=sharing"", ""P1!$B$11"")=1, IFERROR(INDEX(IMPORTRANGE(""https://docs.google.com/spreadsheets/d/10OcXjkVvXdQ20Dikey2wLwZD9Qs97Ke_ckzbHR2FA6E/"&"edit?usp=sharing"", ""P1!$E$6:$BL$6""), MATCH(AU3, IMPORTRANGE(""https://docs.google.com/spreadsheets/d/10OcXjkVvXdQ20Dikey2wLwZD9Qs97Ke_ckzbHR2FA6E/edit?usp=sharing"", ""P1!$E$4:$BL$4""), 0)), ""Unknown""), IF(IMPORTRANGE(""https://docs.google"&".com/spreadsheets/d/10OcXjkVvXdQ20Dikey2wLwZD9Qs97Ke_ckzbHR2FA6E/edit?usp=sharing"", ""P1!$B$11"")=2, 0, ""Unknown""))"),19.787865972520454) -> 19.787866 | AV9: =IFERROR(__xludf.DUMMYFUNCTION("IF(IMPORTRANGE(""https://docs.google.com/spreadsheets/d/10OcXjkVvXdQ20Dikey2wLwZD9Qs97Ke_ckzbHR2FA6E/edit?usp=sharing"", ""P1!$B$11"")=1, IFERROR(INDEX(IMPORTRANGE(""https://docs.google.com/spreadsheets/d/10OcXjkVvXdQ20Dikey2wLwZD9Qs97Ke_ckzbHR2FA6E/"&"edit?usp=sharing"", ""P1!$E$6:$BL$6""), MATCH(AV3, IMPORTRANGE(""https://docs.google.com/spreadsheets/d/10OcXjkVvXdQ20Dikey2wLwZD9Qs97Ke_ckzbHR2FA6E/edit?usp=sharing"", ""P1!$E$4:$BL$4""), 0)), ""Unknown""), IF(IMPORTRANGE(""https://docs.google"&".com/spreadsheets/d/10OcXjkVvXdQ20Dikey2wLwZD9Qs97Ke_ckzbHR2FA6E/edit?usp=sharing"", ""P1!$B$11"")=2, 0, ""Unknown""))"),19.6841501086803) -> 19.68415 | AW9: =IFERROR(__xludf.DUMMYFUNCTION("IF(IMPORTRANGE(""https://docs.google.com/spreadsheets/d/10OcXjkVvXdQ20Dikey2wLwZD9Qs97Ke_ckzbHR2FA6E/edit?usp=sharing"", ""P1!$B$11"")=1, IFERROR(INDEX(IMPORTRANGE(""https://docs.google.com/spreadsheets/d/10OcXjkVvXdQ20Dikey2wLwZD9Qs97Ke_ckzbHR2FA6E/"&"edit?usp=sharing"", ""P1!$E$6:$BL$6""), MATCH(AW3, IMPORTRANGE(""https://docs.google.com/spreadsheets/d/10OcXjkVvXdQ20Dikey2wLwZD9Qs97Ke_ckzbHR2FA6E/edit?usp=sharing"", ""P1!$E$4:$BL$4""), 0)), ""Unknown""), IF(IMPORTRANGE(""https://docs.google"&".com/spreadsheets/d/10OcXjkVvXdQ20Dikey2wLwZD9Qs97Ke_ckzbHR2FA6E/edit?usp=sharing"", ""P1!$B$11"")=2, 0, ""Unknown""))"),19.584297540947667) -> 19.584298 | AX9: =IFERROR(__xludf.DUMMYFUNCTION("IF(IMPORTRANGE(""https://docs.google.com/spreadsheets/d/10OcXjkVvXdQ20Dikey2wLwZD9Qs97Ke_ckzbHR2FA6E/edit?usp=sharing"", ""P1!$B$11"")=1, IFERROR(INDEX(IMPORTRANGE(""https://docs.google.com/spreadsheets/d/10OcXjkVvXdQ20Dikey2wLwZD9Qs97Ke_ckzbHR2FA6E/"&"edit?usp=sharing"", ""P1!$E$6:$BL$6""), MATCH(AX3, IMPORTRANGE(""https://docs.google.com/spreadsheets/d/10OcXjkVvXdQ20Dikey2wLwZD9Qs97Ke_ckzbHR2FA6E/edit?usp=sharing"", ""P1!$E$4:$BL$4""), 0)), ""Unknown""), IF(IMPORTRANGE(""https://docs.google"&".com/spreadsheets/d/10OcXjkVvXdQ20Dikey2wLwZD9Qs97Ke_ckzbHR2FA6E/edit?usp=sharing"", ""P1!$B$11"")=2, 0, ""Unknown""))"),19.48164865804221) -> 19.481649 | AY9: =IFERROR(__xludf.DUMMYFUNCTION("IF(IMPORTRANGE(""https://docs.google.com/spreadsheets/d/10OcXjkVvXdQ20Dikey2wLwZD9Qs97Ke_ckzbHR2FA6E/edit?usp=sharing"", ""P1!$B$11"")=1, IFERROR(INDEX(IMPORTRANGE(""https://docs.google.com/spreadsheets/d/10OcXjkVvXdQ20Dikey2wLwZD9Qs97Ke_ckzbHR2FA6E/"&"edit?usp=sharing"", ""P1!$E$6:$BL$6""), MATCH(AY3, IMPORTRANGE(""https://docs.google.com/spreadsheets/d/10OcXjkVvXdQ20Dikey2wLwZD9Qs97Ke_ckzbHR2FA6E/edit?usp=sharing"", ""P1!$E$4:$BL$4""), 0)), ""Unknown""), IF(IMPORTRANGE(""https://docs.google"&".com/spreadsheets/d/10OcXjkVvXdQ20Dikey2wLwZD9Qs97Ke_ckzbHR2FA6E/edit?usp=sharing"", ""P1!$B$11"")=2, 0, ""Unknown""))"),19.38282332743712) -> 19.382823 | AZ9: =IFERROR(__xludf.DUMMYFUNCTION("IF(IMPORTRANGE(""https://docs.google.com/spreadsheets/d/10OcXjkVvXdQ20Dikey2wLwZD9Qs97Ke_ckzbHR2FA6E/edit?usp=sharing"", ""P1!$B$11"")=1, IFERROR(INDEX(IMPORTRANGE(""https://docs.google.com/spreadsheets/d/10OcXjkVvXdQ20Dikey2wLwZD9Qs97Ke_ckzbHR2FA6E/"&"edit?usp=sharing"", ""P1!$E$6:$BL$6""), MATCH(AZ3, IMPORTRANGE(""https://docs.google.com/spreadsheets/d/10OcXjkVvXdQ20Dikey2wLwZD9Qs97Ke_ckzbHR2FA6E/edit?usp=sharing"", ""P1!$E$4:$BL$4""), 0)), ""Unknown""), IF(IMPORTRANGE(""https://docs.google"&".com/spreadsheets/d/10OcXjkVvXdQ20Dikey2wLwZD9Qs97Ke_ckzbHR2FA6E/edit?usp=sharing"", ""P1!$B$11"")=2, 0, ""Unknown""))"),19.281230448859006) -> 19.28123 | BA9: =IFERROR(__xludf.DUMMYFUNCTION("IF(IMPORTRANGE(""https://docs.google.com/spreadsheets/d/10OcXjkVvXdQ20Dikey2wLwZD9Qs97Ke_ckzbHR2FA6E/edit?usp=sharing"", ""P1!$B$11"")=1, IFERROR(INDEX(IMPORTRANGE(""https://docs.google.com/spreadsheets/d/10OcXjkVvXdQ20Dikey2wLwZD9Qs97Ke_ckzbHR2FA6E/"&"edit?usp=sharing"", ""P1!$E$6:$BL$6""), MATCH(BA3, IMPORTRANGE(""https://docs.google.com/spreadsheets/d/10OcXjkVvXdQ20Dikey2wLwZD9Qs97Ke_ckzbHR2FA6E/edit?usp=sharing"", ""P1!$E$4:$BL$4""), 0)), ""Unknown""), IF(IMPORTRANGE(""https://docs.google"&".com/spreadsheets/d/10OcXjkVvXdQ20Dikey2wLwZD9Qs97Ke_ckzbHR2FA6E/edit?usp=sharing"", ""P1!$B$11"")=2, 0, ""Unknown""))"),19.180170057875884) -> 19.18017 | BB9: =IFERROR(__xludf.DUMMYFUNCTION("IF(IMPORTRANGE(""https://docs.google.com/spreadsheets/d/10OcXjkVvXdQ20Dikey2wLwZD9Qs97Ke_ckzbHR2FA6E/edit?usp=sharing"", ""P1!$B$11"")=1, IFERROR(INDEX(IMPORTRANGE(""https://docs.google.com/spreadsheets/d/10OcXjkVvXdQ20Dikey2wLwZD9Qs97Ke_ckzbHR2FA6E/"&"edit?usp=sharing"", ""P1!$E$6:$BL$6""), MATCH(BB3, IMPORTRANGE(""https://docs.google.com/spreadsheets/d/10OcXjkVvXdQ20Dikey2wLwZD9Qs97Ke_ckzbHR2FA6E/edit?usp=sharing"", ""P1!$E$4:$BL$4""), 0)), ""Unknown""), IF(IMPORTRANGE(""https://docs.google"&".com/spreadsheets/d/10OcXjkVvXdQ20Dikey2wLwZD9Qs97Ke_ckzbHR2FA6E/edit?usp=sharing"", ""P1!$B$11"")=2, 0, ""Unknown""))"),19.0893450673646) -> 19.089345 | BC9: =IFERROR(__xludf.DUMMYFUNCTION("IF(IMPORTRANGE(""https://docs.google.com/spreadsheets/d/10OcXjkVvXdQ20Dikey2wLwZD9Qs97Ke_ckzbHR2FA6E/edit?usp=sharing"", ""P1!$B$11"")=1, IFERROR(INDEX(IMPORTRANGE(""https://docs.google.com/spreadsheets/d/10OcXjkVvXdQ20Dikey2wLwZD9Qs97Ke_ckzbHR2FA6E/"&"edit?usp=sharing"", ""P1!$E$6:$BL$6""), MATCH(BC3, IMPORTRANGE(""https://docs.google.com/spreadsheets/d/10OcXjkVvXdQ20Dikey2wLwZD9Qs97Ke_ckzbHR2FA6E/edit?usp=sharing"", ""P1!$E$4:$BL$4""), 0)), ""Unknown""), IF(IMPORTRANGE(""https://docs.google"&".com/spreadsheets/d/10OcXjkVvXdQ20Dikey2wLwZD9Qs97Ke_ckzbHR2FA6E/edit?usp=sharing"", ""P1!$B$11"")=2, 0, ""Unknown""))"),18.98929042192916) -> 18.98929 | BD9: =IFERROR(__xludf.DUMMYFUNCTION("IF(IMPORTRANGE(""https://docs.google.com/spreadsheets/d/10OcXjkVvXdQ20Dikey2wLwZD9Qs97Ke_ckzbHR2FA6E/edit?usp=sharing"", ""P1!$B$11"")=1, IFERROR(INDEX(IMPORTRANGE(""https://docs.google.com/spreadsheets/d/10OcXjkVvXdQ20Dikey2wLwZD9Qs97Ke_ckzbHR2FA6E/"&"edit?usp=sharing"", ""P1!$E$6:$BL$6""), MATCH(BD3, IMPORTRANGE(""https://docs.google.com/spreadsheets/d/10OcXjkVvXdQ20Dikey2wLwZD9Qs97Ke_ckzbHR2FA6E/edit?usp=sharing"", ""P1!$E$4:$BL$4""), 0)), ""Unknown""), IF(IMPORTRANGE(""https://docs.google"&".com/spreadsheets/d/10OcXjkVvXdQ20Dikey2wLwZD9Qs97Ke_ckzbHR2FA6E/edit?usp=sharing"", ""P1!$B$11"")=2, 0, ""Unknown""))"),18.89296269644539) -> 18.892963 | BE9: =IFERROR(__xludf.DUMMYFUNCTION("IF(IMPORTRANGE(""https://docs.google.com/spreadsheets/d/10OcXjkVvXdQ20Dikey2wLwZD9Qs97Ke_ckzbHR2FA6E/edit?usp=sharing"", ""P1!$B$11"")=1, IFERROR(INDEX(IMPORTRANGE(""https://docs.google.com/spreadsheets/d/10OcXjkVvXdQ20Dikey2wLwZD9Qs97Ke_ckzbHR2FA6E/"&"edit?usp=sharing"", ""P1!$E$6:$BL$6""), MATCH(BE3, IMPORTRANGE(""https://docs.google.com/spreadsheets/d/10OcXjkVvXdQ20Dikey2wLwZD9Qs97Ke_ckzbHR2FA6E/edit?usp=sharing"", ""P1!$E$4:$BL$4""), 0)), ""Unknown""), IF(IMPORTRANGE(""https://docs.google"&".com/spreadsheets/d/10OcXjkVvXdQ20Dikey2wLwZD9Qs97Ke_ckzbHR2FA6E/edit?usp=sharing"", ""P1!$B$11"")=2, 0, ""Unknown""))"),18.793937367019627) -> 18.793937 | BF9: =IFERROR(__xludf.DUMMYFUNCTION("IF(IMPORTRANGE(""https://docs.google.com/spreadsheets/d/10OcXjkVvXdQ20Dikey2wLwZD9Qs97Ke_ckzbHR2FA6E/edit?usp=sharing"", ""P1!$B$11"")=1, IFERROR(INDEX(IMPORTRANGE(""https://docs.google.com/spreadsheets/d/10OcXjkVvXdQ20Dikey2wLwZD9Qs97Ke_ckzbHR2FA6E/"&"edit?usp=sharing"", ""P1!$E$6:$BL$6""), MATCH(BF3, IMPORTRANGE(""https://docs.google.com/spreadsheets/d/10OcXjkVvXdQ20Dikey2wLwZD9Qs97Ke_ckzbHR2FA6E/edit?usp=sharing"", ""P1!$E$4:$BL$4""), 0)), ""Unknown""), IF(IMPORTRANGE(""https://docs.google"&".com/spreadsheets/d/10OcXjkVvXdQ20Dikey2wLwZD9Qs97Ke_ckzbHR2FA6E/edit?usp=sharing"", ""P1!$B$11"")=2, 0, ""Unknown""))"),18.69860061671331) -> 18.698601 | BG9: =IFERROR(__xludf.DUMMYFUNCTION("IF(IMPORTRANGE(""https://docs.google.com/spreadsheets/d/10OcXjkVvXdQ20Dikey2wLwZD9Qs97Ke_ckzbHR2FA6E/edit?usp=sharing"", ""P1!$B$11"")=1, IFERROR(INDEX(IMPORTRANGE(""https://docs.google.com/spreadsheets/d/10OcXjkVvXdQ20Dikey2wLwZD9Qs97Ke_ckzbHR2FA6E/"&"edit?usp=sharing"", ""P1!$E$6:$BL$6""), MATCH(BG3, IMPORTRANGE(""https://docs.google.com/spreadsheets/d/10OcXjkVvXdQ20Dikey2wLwZD9Qs97Ke_ckzbHR2FA6E/edit?usp=sharing"", ""P1!$E$4:$BL$4""), 0)), ""Unknown""), IF(IMPORTRANGE(""https://docs.google"&".com/spreadsheets/d/10OcXjkVvXdQ20Dikey2wLwZD9Qs97Ke_ckzbHR2FA6E/edit?usp=sharing"", ""P1!$B$11"")=2, 0, ""Unknown""))"),18.600594014169225) -> 18.600594 | BH9: =IFERROR(__xludf.DUMMYFUNCTION("IF(IMPORTRANGE(""https://docs.google.com/spreadsheets/d/10OcXjkVvXdQ20Dikey2wLwZD9Qs97Ke_ckzbHR2FA6E/edit?usp=sharing"", ""P1!$B$11"")=1, IFERROR(INDEX(IMPORTRANGE(""https://docs.google.com/spreadsheets/d/10OcXjkVvXdQ20Dikey2wLwZD9Qs97Ke_ckzbHR2FA6E/"&"edit?usp=sharing"", ""P1!$E$6:$BL$6""), MATCH(BH3, IMPORTRANGE(""https://docs.google.com/spreadsheets/d/10OcXjkVvXdQ20Dikey2wLwZD9Qs97Ke_ckzbHR2FA6E/edit?usp=sharing"", ""P1!$E$4:$BL$4""), 0)), ""Unknown""), IF(IMPORTRANGE(""https://docs.google"&".com/spreadsheets/d/10OcXjkVvXdQ20Dikey2wLwZD9Qs97Ke_ckzbHR2FA6E/edit?usp=sharing"", ""P1!$B$11"")=2, 0, ""Unknown""))"),18.503101102159476) -> 18.503101 | BI9: =IFERROR(__xludf.DUMMYFUNCTION("IF(IMPORTRANGE(""https://docs.google.com/spreadsheets/d/10OcXjkVvXdQ20Dikey2wLwZD9Qs97Ke_ckzbHR2FA6E/edit?usp=sharing"", ""P1!$B$11"")=1, IFERROR(INDEX(IMPORTRANGE(""https://docs.google.com/spreadsheets/d/10OcXjkVvXdQ20Dikey2wLwZD9Qs97Ke_ckzbHR2FA6E/"&"edit?usp=sharing"", ""P1!$E$6:$BL$6""), MATCH(BI3, IMPORTRANGE(""https://docs.google.com/spreadsheets/d/10OcXjkVvXdQ20Dikey2wLwZD9Qs97Ke_ckzbHR2FA6E/edit?usp=sharing"", ""P1!$E$4:$BL$4""), 0)), ""Unknown""), IF(IMPORTRANGE(""https://docs.google"&".com/spreadsheets/d/10OcXjkVvXdQ20Dikey2wLwZD9Qs97Ke_ckzbHR2FA6E/edit?usp=sharing"", ""P1!$B$11"")=2, 0, ""Unknown""))"),18.409239688490803) -> 18.40924 | BJ9: =IFERROR(__xludf.DUMMYFUNCTION("IF(IMPORTRANGE(""https://docs.google.com/spreadsheets/d/10OcXjkVvXdQ20Dikey2wLwZD9Qs97Ke_ckzbHR2FA6E/edit?usp=sharing"", ""P1!$B$11"")=1, IFERROR(INDEX(IMPORTRANGE(""https://docs.google.com/spreadsheets/d/10OcXjkVvXdQ20Dikey2wLwZD9Qs97Ke_ckzbHR2FA6E/"&"edit?usp=sharing"", ""P1!$E$6:$BL$6""), MATCH(BJ3, IMPORTRANGE(""https://docs.google.com/spreadsheets/d/10OcXjkVvXdQ20Dikey2wLwZD9Qs97Ke_ckzbHR2FA6E/edit?usp=sharing"", ""P1!$E$4:$BL$4""), 0)), ""Unknown""), IF(IMPORTRANGE(""https://docs.google"&".com/spreadsheets/d/10OcXjkVvXdQ20Dikey2wLwZD9Qs97Ke_ckzbHR2FA6E/edit?usp=sharing"", ""P1!$B$11"")=2, 0, ""Unknown""))"),18.312749738559678) -> 18.31275 | BK9: =IFERROR(__xludf.DUMMYFUNCTION("IF(IMPORTRANGE(""https://docs.google.com/spreadsheets/d/10OcXjkVvXdQ20Dikey2wLwZD9Qs97Ke_ckzbHR2FA6E/edit?usp=sharing"", ""P1!$B$11"")=1, IFERROR(INDEX(IMPORTRANGE(""https://docs.google.com/spreadsheets/d/10OcXjkVvXdQ20Dikey2wLwZD9Qs97Ke_ckzbHR2FA6E/"&"edit?usp=sharing"", ""P1!$E$6:$BL$6""), MATCH(BK3, IMPORTRANGE(""https://docs.google.com/spreadsheets/d/10OcXjkVvXdQ20Dikey2wLwZD9Qs97Ke_ckzbHR2FA6E/edit?usp=sharing"", ""P1!$E$4:$BL$4""), 0)), ""Unknown""), IF(IMPORTRANGE(""https://docs.google"&".com/spreadsheets/d/10OcXjkVvXdQ20Dikey2wLwZD9Qs97Ke_ckzbHR2FA6E/edit?usp=sharing"", ""P1!$B$11"")=2, 0, ""Unknown""))"),18.219853927790894) -> 18.219854 | BL9: =AVERAGE(D9:BK9) -> 21.301016
C10: Ocupación % (Mercado) | D10: =IFERROR(__xludf.DUMMYFUNCTION("IMPORTRANGE(""10OcXjkVvXdQ20Dikey2wLwZD9Qs97Ke_ckzbHR2FA6E"",""P1!E14:BL14"")"),0.5700161290322582) -> 0.57001613 | E10: =IFERROR(__xludf.DUMMYFUNCTION("""COMPUTED_VALUE"""),0.6813214285714286) -> 0.68132143 | F10: =IFERROR(__xludf.DUMMYFUNCTION("""COMPUTED_VALUE"""),0.6134516129032258) -> 0.61345161 | G10: =IFERROR(__xludf.DUMMYFUNCTION("""COMPUTED_VALUE"""),0.6785333333333331) -> 0.67853333 | H10: =IFERROR(__xludf.DUMMYFUNCTION("""COMPUTED_VALUE"""),0.6939193548387097) -> 0.69391935 | I10: =IFERROR(__xludf.DUMMYFUNCTION("""COMPUTED_VALUE"""),0.6986666666666665) -> 0.69866667 | J10: =IFERROR(__xludf.DUMMYFUNCTION("""COMPUTED_VALUE"""),0.6928548387096773) -> 0.69285484 | K10: =IFERROR(__xludf.DUMMYFUNCTION("""COMPUTED_VALUE"""),0.6455483870967743) -> 0.64554839 | L10: =IFERROR(__xludf.DUMMYFUNCTION("""COMPUTED_VALUE"""),0.6595166666666665) -> 0.65951667 | M10: =IFERROR(__xludf.DUMMYFUNCTION("""COMPUTED_VALUE"""),0.6066935483870967) -> 0.60669355 | N10: =IFERROR(__xludf.DUMMYFUNCTION("""COMPUTED_VALUE"""),0.66905) -> 0.66905 | O10: =IFERROR(__xludf.DUMMYFUNCTION("""COMPUTED_VALUE"""),0.6060806451612902) -> 0.60608065 | P10: =IFERROR(__xludf.DUMMYFUNCTION("""COMPUTED_VALUE"""),0.5700161290322582) -> 0.57001613 | Q10: =IFERROR(__xludf.DUMMYFUNCTION("""COMPUTED_VALUE"""),0.6813214285714286) -> 0.68132143 | R10: =IFERROR(__xludf.DUMMYFUNCTION("""COMPUTED_VALUE"""),0.6134516129032258) -> 0.61345161 | S10: =IFERROR(__xludf.DUMMYFUNCTION("""COMPUTED_VALUE"""),0.6785333333333331) -> 0.67853333 | T10: =IFERROR(__xludf.DUMMYFUNCTION("""COMPUTED_VALUE"""),0.6939193548387097) -> 0.69391935 | U10: =IFERROR(__xludf.DUMMYFUNCTION("""COMPUTED_VALUE"""),0.6986666666666665) -> 0.69866667 | V10: =IFERROR(__xludf.DUMMYFUNCTION("""COMPUTED_VALUE"""),0.6928548387096773) -> 0.69285484 | W10: =IFERROR(__xludf.DUMMYFUNCTION("""COMPUTED_VALUE"""),0.6455483870967743) -> 0.64554839 | X10: =IFERROR(__xludf.DUMMYFUNCTION("""COMPUTED_VALUE"""),0.6595166666666665) -> 0.65951667 | Y10: =IFERROR(__xludf.DUMMYFUNCTION("""COMPUTED_VALUE"""),0.6066935483870967) -> 0.60669355 | Z10: =IFERROR(__xludf.DUMMYFUNCTION("""COMPUTED_VALUE"""),0.66905) -> 0.66905 | AA10: =IFERROR(__xludf.DUMMYFUNCTION("""COMPUTED_VALUE"""),0.6060806451612902) -> 0.60608065 | AB10: =IFERROR(__xludf.DUMMYFUNCTION("""COMPUTED_VALUE"""),0.5700161290322582) -> 0.57001613 | AC10: =IFERROR(__xludf.DUMMYFUNCTION("""COMPUTED_VALUE"""),0.6813214285714286) -> 0.68132143 | AD10: =IFERROR(__xludf.DUMMYFUNCTION("""COMPUTED_VALUE"""),0.6134516129032258) -> 0.61345161 | AE10: =IFERROR(__xludf.DUMMYFUNCTION("""COMPUTED_VALUE"""),0.6785333333333331) -> 0.67853333 | AF10: =IFERROR(__xludf.DUMMYFUNCTION("""COMPUTED_VALUE"""),0.6939193548387097) -> 0.69391935 | AG10: =IFERROR(__xludf.DUMMYFUNCTION("""COMPUTED_VALUE"""),0.6986666666666665) -> 0.69866667 | AH10: =IFERROR(__xludf.DUMMYFUNCTION("""COMPUTED_VALUE"""),0.6928548387096773) -> 0.69285484 | AI10: =IFERROR(__xludf.DUMMYFUNCTION("""COMPUTED_VALUE"""),0.6455483870967743) -> 0.64554839 | AJ10: =IFERROR(__xludf.DUMMYFUNCTION("""COMPUTED_VALUE"""),0.6595166666666665) -> 0.65951667 | AK10: =IFERROR(__xludf.DUMMYFUNCTION("""COMPUTED_VALUE"""),0.6066935483870967) -> 0.60669355 | AL10: =IFERROR(__xludf.DUMMYFUNCTION("""COMPUTED_VALUE"""),0.66905) -> 0.66905 | AM10: =IFERROR(__xludf.DUMMYFUNCTION("""COMPUTED_VALUE"""),0.6060806451612902) -> 0.60608065 | AN10: =IFERROR(__xludf.DUMMYFUNCTION("""COMPUTED_VALUE"""),0.5700161290322582) -> 0.57001613 | AO10: =IFERROR(__xludf.DUMMYFUNCTION("""COMPUTED_VALUE"""),0.6813214285714286) -> 0.68132143 | AP10: =IFERROR(__xludf.DUMMYFUNCTION("""COMPUTED_VALUE"""),0.6134516129032258) -> 0.61345161 | AQ10: =IFERROR(__xludf.DUMMYFUNCTION("""COMPUTED_VALUE"""),0.6785333333333331) -> 0.67853333 | AR10: =IFERROR(__xludf.DUMMYFUNCTION("""COMPUTED_VALUE"""),0.6939193548387097) -> 0.69391935 | AS10: =IFERROR(__xludf.DUMMYFUNCTION("""COMPUTED_VALUE"""),0.6986666666666665) -> 0.69866667 | AT10: =IFERROR(__xludf.DUMMYFUNCTION("""COMPUTED_VALUE"""),0.6928548387096773) -> 0.69285484 | AU10: =IFERROR(__xludf.DUMMYFUNCTION("""COMPUTED_VALUE"""),0.6455483870967743) -> 0.64554839 | AV10: =IFERROR(__xludf.DUMMYFUNCTION("""COMPUTED_VALUE"""),0.6595166666666665) -> 0.65951667 | AW10: =IFERROR(__xludf.DUMMYFUNCTION("""COMPUTED_VALUE"""),0.6066935483870967) -> 0.60669355 | AX10: =IFERROR(__xludf.DUMMYFUNCTION("""COMPUTED_VALUE"""),0.66905) -> 0.66905 | AY10: =IFERROR(__xludf.DUMMYFUNCTION("""COMPUTED_VALUE"""),0.6060806451612902) -> 0.60608065 | AZ10: =IFERROR(__xludf.DUMMYFUNCTION("""COMPUTED_VALUE"""),0.5700161290322582) -> 0.57001613 | BA10: =IFERROR(__xludf.DUMMYFUNCTION("""COMPUTED_VALUE"""),0.6813214285714286) -> 0.68132143 | BB10: =IFERROR(__xludf.DUMMYFUNCTION("""COMPUTED_VALUE"""),0.6134516129032258) -> 0.61345161 | BC10: =IFERROR(__xludf.DUMMYFUNCTION("""COMPUTED_VALUE"""),0.6785333333333331) -> 0.67853333 | BD10: =IFERROR(__xludf.DUMMYFUNCTION("""COMPUTED_VALUE"""),0.6939193548387097) -> 0.69391935 | BE10: =IFERROR(__xludf.DUMMYFUNCTION("""COMPUTED_VALUE"""),0.6986666666666665) -> 0.69866667 | BF10: =IFERROR(__xludf.DUMMYFUNCTION("""COMPUTED_VALUE"""),0.6928548387096773) -> 0.69285484 | BG10: =IFERROR(__xludf.DUMMYFUNCTION("""COMPUTED_VALUE"""),0.6455483870967743) -> 0.64554839 | BH10: =IFERROR(__xludf.DUMMYFUNCTION("""COMPUTED_VALUE"""),0.6595166666666665) -> 0.65951667 | BI10: =IFERROR(__xludf.DUMMYFUNCTION("""COMPUTED_VALUE"""),0.6066935483870967) -> 0.60669355 | BJ10: =IFERROR(__xludf.DUMMYFUNCTION("""COMPUTED_VALUE"""),0.66905) -> 0.66905 | BK10: =IFERROR(__xludf.DUMMYFUNCTION("""COMPUTED_VALUE"""),0.6060806451612902) -> 0.60608065 | BL10: =AVERAGE(D10:BK10) -> 0.65130438
C11: ADR Implícito | D11: =IFERROR(__xludf.DUMMYFUNCTION("IMPORTRANGE(""10OcXjkVvXdQ20Dikey2wLwZD9Qs97Ke_ckzbHR2FA6E"",""P1!E15:BL15"")"),1339.7392982578176) -> 1339.7393 | E11: =IFERROR(__xludf.DUMMYFUNCTION("""COMPUTED_VALUE"""),1349.3163954323456) -> 1349.3164 | F11: =IFERROR(__xludf.DUMMYFUNCTION("""COMPUTED_VALUE"""),1209.9278503160565) -> 1209.9279 | G11: =IFERROR(__xludf.DUMMYFUNCTION("""COMPUTED_VALUE"""),1225.0233520795716) -> 1225.0234 | H11: =IFERROR(__xludf.DUMMYFUNCTION("""COMPUTED_VALUE"""),1194.6606858802666) -> 1194.6607 | I11: =IFERROR(__xludf.DUMMYFUNCTION("""COMPUTED_VALUE"""),1234.1579689239336) -> 1234.158 | J11: =IFERROR(__xludf.DUMMYFUNCTION("""COMPUTED_VALUE"""),1206.3797045308463) -> 1206.3797 | K11: =IFERROR(__xludf.DUMMYFUNCTION("""COMPUTED_VALUE"""),1256.1956713551972) -> 1256.1957 | L11: =IFERROR(__xludf.DUMMYFUNCTION("""COMPUTED_VALUE"""),1241.9936264922626) -> 1241.9936 | M11: =IFERROR(__xludf.DUMMYFUNCTION("""COMPUTED_VALUE"""),1272.2738405418927) -> 1272.2738 | N11: =IFERROR(__xludf.DUMMYFUNCTION("""COMPUTED_VALUE"""),1336.7862272085836) -> 1336.7862 | O11: =IFERROR(__xludf.DUMMYFUNCTION("""COMPUTED_VALUE"""),1356.2331073793514) -> 1356.2331 | P11: =IFERROR(__xludf.DUMMYFUNCTION("""COMPUTED_VALUE"""),1393.3288701881297) -> 1393.3289 | Q11: =IFERROR(__xludf.DUMMYFUNCTION("""COMPUTED_VALUE"""),1403.2890512496397) -> 1403.2891 | R11: =IFERROR(__xludf.DUMMYFUNCTION("""COMPUTED_VALUE"""),1258.3249643286988) -> 1258.325 | S11: =IFERROR(__xludf.DUMMYFUNCTION("""COMPUTED_VALUE"""),1274.0242861627546) -> 1274.0243 | T11: =IFERROR(__xludf.DUMMYFUNCTION("""COMPUTED_VALUE"""),1242.447113315477) -> 1242.4471 | U11: =IFERROR(__xludf.DUMMYFUNCTION("""COMPUTED_VALUE"""),1283.5242876808913) -> 1283.5243 | V11: =IFERROR(__xludf.DUMMYFUNCTION("""COMPUTED_VALUE"""),1254.6348927120798) -> 1254.6349 | W11: =IFERROR(__xludf.DUMMYFUNCTION("""COMPUTED_VALUE"""),1306.443498209405) -> 1306.4435 | X11: =IFERROR(__xludf.DUMMYFUNCTION("""COMPUTED_VALUE"""),1291.6733715519533) -> 1291.6734 | Y11: =IFERROR(__xludf.DUMMYFUNCTION("""COMPUTED_VALUE"""),1323.164794163568) -> 1323.1648 | Z11: =IFERROR(__xludf.DUMMYFUNCTION("""COMPUTED_VALUE"""),1390.257676296927) -> 1390.2577 | AA11: =IFERROR(__xludf.DUMMYFUNCTION("""COMPUTED_VALUE"""),1410.4824316745257) -> 1410.4824 | AB11: =IFERROR(__xludf.DUMMYFUNCTION("""COMPUTED_VALUE"""),1449.0620249956557) -> 1449.062 | AC11: =IFERROR(__xludf.DUMMYFUNCTION("""COMPUTED_VALUE"""),1459.420613299625) -> 1459.4206 | AD11: =IFERROR(__xludf.DUMMYFUNCTION("""COMPUTED_VALUE"""),1308.6579629018465) -> 1308.658 | AE11: =IFERROR(__xludf.DUMMYFUNCTION("""COMPUTED_VALUE"""),1324.9852576092646) -> 1324.9853 | AF11: =IFERROR(__xludf.DUMMYFUNCTION("""COMPUTED_VALUE"""),1292.144997848096) -> 1292.145 | AG11: =IFERROR(__xludf.DUMMYFUNCTION("""COMPUTED_VALUE"""),1334.865259188127) -> 1334.8653 | AH11: =IFERROR(__xludf.DUMMYFUNCTION("""COMPUTED_VALUE"""),1304.8202884205632) -> 1304.8203 | AI11: =IFERROR(__xludf.DUMMYFUNCTION("""COMPUTED_VALUE"""),1358.701238137781) -> 1358.7012 | AJ11: =IFERROR(__xludf.DUMMYFUNCTION("""COMPUTED_VALUE"""),1343.3403064140314) -> 1343.3403 | AK11: =IFERROR(__xludf.DUMMYFUNCTION("""COMPUTED_VALUE"""),1376.091385930111) -> 1376.0914 | AL11: =IFERROR(__xludf.DUMMYFUNCTION("""COMPUTED_VALUE"""),1445.8679833488045) -> 1445.868 | AM11: =IFERROR(__xludf.DUMMYFUNCTION("""COMPUTED_VALUE"""),1466.901728941507) -> 1466.9017 | AN11: =IFERROR(__xludf.DUMMYFUNCTION("""COMPUTED_VALUE"""),1507.0245059954816) -> 1507.0245 | AO11: =IFERROR(__xludf.DUMMYFUNCTION("""COMPUTED_VALUE"""),1517.7974378316105) -> 1517.7974 | AP11: =IFERROR(__xludf.DUMMYFUNCTION("""COMPUTED_VALUE"""),1361.0042814179205) -> 1361.0043 | AQ11: =IFERROR(__xludf.DUMMYFUNCTION("""COMPUTED_VALUE"""),1377.9846679136351) -> 1377.9847 | AR11: =IFERROR(__xludf.DUMMYFUNCTION("""COMPUTED_VALUE"""),1343.83079776202) -> 1343.8308 | AS11: =IFERROR(__xludf.DUMMYFUNCTION("""COMPUTED_VALUE"""),1388.259869555652) -> 1388.2599 | AT11: =IFERROR(__xludf.DUMMYFUNCTION("""COMPUTED_VALUE"""),1357.013099957386) -> 1357.0131 | AU11: =IFERROR(__xludf.DUMMYFUNCTION("""COMPUTED_VALUE"""),1413.0492876632927) -> 1413.0493 | AV11: =IFERROR(__xludf.DUMMYFUNCTION("""COMPUTED_VALUE"""),1397.0739186705923) -> 1397.0739 | AW11: =IFERROR(__xludf.DUMMYFUNCTION("""COMPUTED_VALUE"""),1431.1350413673154) -> 1431.135 | AX11: =IFERROR(__xludf.DUMMYFUNCTION("""COMPUTED_VALUE"""),1503.7027026827561) -> 1503.7027 | AY11: =IFERROR(__xludf.DUMMYFUNCTION("""COMPUTED_VALUE"""),1525.5777980991672) -> 1525.5778 | AZ11: =IFERROR(__xludf.DUMMYFUNCTION("""COMPUTED_VALUE"""),1567.305486235301) -> 1567.3055 | BA11: =IFERROR(__xludf.DUMMYFUNCTION("""COMPUTED_VALUE"""),1578.5093353448747) -> 1578.5093 | BB11: =IFERROR(__xludf.DUMMYFUNCTION("""COMPUTED_VALUE"""),1415.4444526746372) -> 1415.4445 | BC11: =IFERROR(__xludf.DUMMYFUNCTION("""COMPUTED_VALUE"""),1433.1040546301808) -> 1433.1041 | BD11: =IFERROR(__xludf.DUMMYFUNCTION("""COMPUTED_VALUE"""),1397.584029672501) -> 1397.584 | BE11: =IFERROR(__xludf.DUMMYFUNCTION("""COMPUTED_VALUE"""),1443.7902643378784) -> 1443.7903 | BF11: =IFERROR(__xludf.DUMMYFUNCTION("""COMPUTED_VALUE"""),1411.2936239556814) -> 1411.2936 | BG11: =IFERROR(__xludf.DUMMYFUNCTION("""COMPUTED_VALUE"""),1469.5712591698245) -> 1469.5713 | BH11: =IFERROR(__xludf.DUMMYFUNCTION("""COMPUTED_VALUE"""),1452.956875417416) -> 1452.9569 | BI11: =IFERROR(__xludf.DUMMYFUNCTION("""COMPUTED_VALUE"""),1488.3804430220086) -> 1488.3804 | BJ11: =IFERROR(__xludf.DUMMYFUNCTION("""COMPUTED_VALUE"""),1563.8508107900666) -> 1563.8508 | BK11: =IFERROR(__xludf.DUMMYFUNCTION("""COMPUTED_VALUE"""),1586.6009100231338) -> 1586.6009 | BL11: =AVERAGE(D11:BK11) -> 1374.1831
C12: RevPAR | D12: =IFERROR(__xludf.DUMMYFUNCTION("IMPORTRANGE(""10OcXjkVvXdQ20Dikey2wLwZD9Qs97Ke_ckzbHR2FA6E"",""P1!E13:BL13"")"),763.6730087053152) -> 763.67301 | E12: =IFERROR(__xludf.DUMMYFUNCTION("""COMPUTED_VALUE"""),919.3181741308165) -> 919.31817 | F12: =IFERROR(__xludf.DUMMYFUNCTION("""COMPUTED_VALUE"""),742.2321912729176) -> 742.23219 | G12: =IFERROR(__xludf.DUMMYFUNCTION("""COMPUTED_VALUE"""),831.219178497725) -> 831.21918 | H12: =IFERROR(__xludf.DUMMYFUNCTION("""COMPUTED_VALUE"""),828.9981723972049) -> 828.99817 | I12: =IFERROR(__xludf.DUMMYFUNCTION("""COMPUTED_VALUE"""),862.2650342881882) -> 862.26503 | J12: =IFERROR(__xludf.DUMMYFUNCTION("""COMPUTED_VALUE"""),835.8460156053477) -> 835.84602 | K12: =IFERROR(__xludf.DUMMYFUNCTION("""COMPUTED_VALUE"""),810.9350895212972) -> 810.93509 | L12: =IFERROR(__xludf.DUMMYFUNCTION("""COMPUTED_VALUE"""),819.1154965654218) -> 819.1155 | M12: =IFERROR(__xludf.DUMMYFUNCTION("""COMPUTED_VALUE"""),771.88033083844) -> 771.88033 | N12: =IFERROR(__xludf.DUMMYFUNCTION("""COMPUTED_VALUE"""),894.3768253139029) -> 894.37683 | O12: =IFERROR(__xludf.DUMMYFUNCTION("""COMPUTED_VALUE"""),821.9866367095788) -> 821.98664 | P12: =IFERROR(__xludf.DUMMYFUNCTION("""COMPUTED_VALUE"""),794.2199290535275) -> 794.21993 | Q12: =IFERROR(__xludf.DUMMYFUNCTION("""COMPUTED_VALUE"""),956.0909010960493) -> 956.0909 | R12: =IFERROR(__xludf.DUMMYFUNCTION("""COMPUTED_VALUE"""),771.9214789238343) -> 771.92148 | S12: =IFERROR(__xludf.DUMMYFUNCTION("""COMPUTED_VALUE"""),864.4679456376341) -> 864.46795 | T12: =IFERROR(__xludf.DUMMYFUNCTION("""COMPUTED_VALUE"""),862.1580992930931) -> 862.1581 | U12: =IFERROR(__xludf.DUMMYFUNCTION("""COMPUTED_VALUE"""),896.755635659716) -> 896.75564 | V12: =IFERROR(__xludf.DUMMYFUNCTION("""COMPUTED_VALUE"""),869.2798562295615) -> 869.27986 | W12: =IFERROR(__xludf.DUMMYFUNCTION("""COMPUTED_VALUE"""),843.3724931021491) -> 843.37249 | X12: =IFERROR(__xludf.DUMMYFUNCTION("""COMPUTED_VALUE"""),851.8801164280388) -> 851.88012 | Y12: =IFERROR(__xludf.DUMMYFUNCTION("""COMPUTED_VALUE"""),802.7555440719775) -> 802.75554 | Z12: =IFERROR(__xludf.DUMMYFUNCTION("""COMPUTED_VALUE"""),930.1518983264591) -> 930.1519 | AA12: =IFERROR(__xludf.DUMMYFUNCTION("""COMPUTED_VALUE"""),854.866102177962) -> 854.8661 | AB12: =IFERROR(__xludf.DUMMYFUNCTION("""COMPUTED_VALUE"""),825.988726215669) -> 825.98873 | AC12: =IFERROR(__xludf.DUMMYFUNCTION("""COMPUTED_VALUE"""),994.334537139891) -> 994.33454 | AD12: =IFERROR(__xludf.DUMMYFUNCTION("""COMPUTED_VALUE"""),802.7983380807876) -> 802.79834 | AE12: =IFERROR(__xludf.DUMMYFUNCTION("""COMPUTED_VALUE"""),899.0466634631395) -> 899.04666 | AF12: =IFERROR(__xludf.DUMMYFUNCTION("""COMPUTED_VALUE"""),896.6444232648166) -> 896.64442 | AG12: =IFERROR(__xludf.DUMMYFUNCTION("""COMPUTED_VALUE"""),932.6258610861047) -> 932.62586 | AH12: =IFERROR(__xludf.DUMMYFUNCTION("""COMPUTED_VALUE"""),904.0510504787441) -> 904.05105 | AI12: =IFERROR(__xludf.DUMMYFUNCTION("""COMPUTED_VALUE"""),877.1073928262348) -> 877.10739 | AJ12: =IFERROR(__xludf.DUMMYFUNCTION("""COMPUTED_VALUE"""),885.9553210851603) -> 885.95532 | AK12: =IFERROR(__xludf.DUMMYFUNCTION("""COMPUTED_VALUE"""),834.8657658348568) -> 834.86577 | AL12: =IFERROR(__xludf.DUMMYFUNCTION("""COMPUTED_VALUE"""),967.3579742595177) -> 967.35797 | AM12: =IFERROR(__xludf.DUMMYFUNCTION("""COMPUTED_VALUE"""),889.0607462650806) -> 889.06075 | AN12: =IFERROR(__xludf.DUMMYFUNCTION("""COMPUTED_VALUE"""),859.0282752642955) -> 859.02828 | AO12: =IFERROR(__xludf.DUMMYFUNCTION("""COMPUTED_VALUE"""),1034.107918625487) -> 1034.1079 | AP12: =IFERROR(__xludf.DUMMYFUNCTION("""COMPUTED_VALUE"""),834.9102716040192) -> 834.91027 | AQ12: =IFERROR(__xludf.DUMMYFUNCTION("""COMPUTED_VALUE"""),935.0085300016649) -> 935.00853 | AR12: =IFERROR(__xludf.DUMMYFUNCTION("""COMPUTED_VALUE"""),932.5102001954095) -> 932.5102 | AS12: =IFERROR(__xludf.DUMMYFUNCTION("""COMPUTED_VALUE"""),969.9308955295486) -> 969.9309 | AT12: =IFERROR(__xludf.DUMMYFUNCTION("""COMPUTED_VALUE"""),940.2130924978939) -> 940.21309 | AU12: =IFERROR(__xludf.DUMMYFUNCTION("""COMPUTED_VALUE"""),912.1916885392844) -> 912.19169 | AV12: =IFERROR(__xludf.DUMMYFUNCTION("""COMPUTED_VALUE"""),921.3935339285666) -> 921.39353 | AW12: =IFERROR(__xludf.DUMMYFUNCTION("""COMPUTED_VALUE"""),868.260396468251) -> 868.2604 | AX12: =IFERROR(__xludf.DUMMYFUNCTION("""COMPUTED_VALUE"""),1006.052293229898) -> 1006.0523 | AY12: =IFERROR(__xludf.DUMMYFUNCTION("""COMPUTED_VALUE"""),924.6231761156838) -> 924.62318 | AZ12: =IFERROR(__xludf.DUMMYFUNCTION("""COMPUTED_VALUE"""),893.3894062748675) -> 893.38941 | BA12: =IFERROR(__xludf.DUMMYFUNCTION("""COMPUTED_VALUE"""),1075.4722353705063) -> 1075.4722 | BB12: =IFERROR(__xludf.DUMMYFUNCTION("""COMPUTED_VALUE"""),868.3066824681799) -> 868.30668 | BC12: =IFERROR(__xludf.DUMMYFUNCTION("""COMPUTED_VALUE"""),972.4088712017317) -> 972.40887 | BD12: =IFERROR(__xludf.DUMMYFUNCTION("""COMPUTED_VALUE"""),969.810608203226) -> 969.81061 | BE12: =IFERROR(__xludf.DUMMYFUNCTION("""COMPUTED_VALUE"""),1008.7281313507309) -> 1008.7281 | BF12: =IFERROR(__xludf.DUMMYFUNCTION("""COMPUTED_VALUE"""),977.8216161978096) -> 977.82162 | BG12: =IFERROR(__xludf.DUMMYFUNCTION("""COMPUTED_VALUE"""),948.679356080856) -> 948.67936 | BH12: =IFERROR(__xludf.DUMMYFUNCTION("""COMPUTED_VALUE"""),958.2492752857094) -> 958.24928 | BI12: =IFERROR(__xludf.DUMMYFUNCTION("""COMPUTED_VALUE"""),902.9908123269813) -> 902.99081 | BJ12: =IFERROR(__xludf.DUMMYFUNCTION("""COMPUTED_VALUE"""),1046.294384959094) -> 1046.2944 | BK12: =IFERROR(__xludf.DUMMYFUNCTION("""COMPUTED_VALUE"""),961.6081031603111) -> 961.6081 | BL12: =AVERAGE(D12:BK12) -> 893.85988
B13: ({UO} | AT-AMP-02) - Analisis de Mercado [No. 2 - KIVA] | D13: =IFERROR(__xludf.DUMMYFUNCTION("IFERROR(IMPORTRANGE(""https://docs.google.com/spreadsheets/d/113Ah55vN7ZtqjRW56fWOsnIaTUko57qPvHiPNGZ2OQ0/edit?usp=sharing"", ""P1!E"" & FilaVentaEsc & "":BL"" & FilaVentaEsc), ""Revise Error"")"),415667.29837790644) -> 415667.3 | E13: =IFERROR(__xludf.DUMMYFUNCTION("""COMPUTED_VALUE"""),414575.82753013924) -> 414575.83 | F13: =IFERROR(__xludf.DUMMYFUNCTION("""COMPUTED_VALUE"""),503507.2533419138) -> 503507.25 | G13: =IFERROR(__xludf.DUMMYFUNCTION("""COMPUTED_VALUE"""),406436.05524811125) -> 406436.06 | H13: =IFERROR(__xludf.DUMMYFUNCTION("""COMPUTED_VALUE"""),415094.3446624822) -> 415094.34 | I13: =IFERROR(__xludf.DUMMYFUNCTION("""COMPUTED_VALUE"""),412473.37288263283) -> 412473.37 | J13: =IFERROR(__xludf.DUMMYFUNCTION("""COMPUTED_VALUE"""),469664.11898114585) -> 469664.12 | K13: =IFERROR(__xludf.DUMMYFUNCTION("""COMPUTED_VALUE"""),485076.76720863394) -> 485076.77 | L13: =IFERROR(__xludf.DUMMYFUNCTION("""COMPUTED_VALUE"""),349690.5258173814) -> 349690.53 | M13: =IFERROR(__xludf.DUMMYFUNCTION("""COMPUTED_VALUE"""),332155.65606695943) -> 332155.66 | N13: =IFERROR(__xludf.DUMMYFUNCTION("""COMPUTED_VALUE"""),457071.35044006625) -> 457071.35 | O13: =IFERROR(__xludf.DUMMYFUNCTION("""COMPUTED_VALUE"""),399419.8669335193) -> 399419.87 | P13: =IFERROR(__xludf.DUMMYFUNCTION("""COMPUTED_VALUE"""),406356.3508942413) -> 406356.35 | Q13: =IFERROR(__xludf.DUMMYFUNCTION("""COMPUTED_VALUE"""),405289.328993464) -> 405289.33 | R13: =IFERROR(__xludf.DUMMYFUNCTION("""COMPUTED_VALUE"""),492228.6908670549) -> 492228.69 | S13: =IFERROR(__xludf.DUMMYFUNCTION("""COMPUTED_VALUE"""),397331.88761055353) -> 397331.89 | T13: =IFERROR(__xludf.DUMMYFUNCTION("""COMPUTED_VALUE"""),405796.23134204256) -> 405796.23 | U13: =IFERROR(__xludf.DUMMYFUNCTION("""COMPUTED_VALUE"""),403233.9693300618) -> 403233.97 | V13: =IFERROR(__xludf.DUMMYFUNCTION("""COMPUTED_VALUE"""),459143.64271596813) -> 459143.64 | W13: =IFERROR(__xludf.DUMMYFUNCTION("""COMPUTED_VALUE"""),474211.0476231606) -> 474211.05 | X13: =IFERROR(__xludf.DUMMYFUNCTION("""COMPUTED_VALUE"""),341857.458039072) -> 341857.46 | Y13: =IFERROR(__xludf.DUMMYFUNCTION("""COMPUTED_VALUE"""),324715.3693710596) -> 324715.37 | Z13: =IFERROR(__xludf.DUMMYFUNCTION("""COMPUTED_VALUE"""),446832.95219020883) -> 446832.95 | AA13: =IFERROR(__xludf.DUMMYFUNCTION("""COMPUTED_VALUE"""),390472.86191420857) -> 390472.86 | AB13: =IFERROR(__xludf.DUMMYFUNCTION("""COMPUTED_VALUE"""),397253.96863421035) -> 397253.97 | AC13: =IFERROR(__xludf.DUMMYFUNCTION("""COMPUTED_VALUE"""),396210.8480240104) -> 396210.85 | AD13: =IFERROR(__xludf.DUMMYFUNCTION("""COMPUTED_VALUE"""),481202.768191633) -> 481202.77 | AE13: =IFERROR(__xludf.DUMMYFUNCTION("""COMPUTED_VALUE"""),388431.6533280771) -> 388431.65 | AF13: =IFERROR(__xludf.DUMMYFUNCTION("""COMPUTED_VALUE"""),396706.39575998083) -> 396706.4 | AG13: =IFERROR(__xludf.DUMMYFUNCTION("""COMPUTED_VALUE"""),394201.5284170685) -> 394201.53 | AH13: =IFERROR(__xludf.DUMMYFUNCTION("""COMPUTED_VALUE"""),448858.82511913055) -> 448858.83 | AI13: =IFERROR(__xludf.DUMMYFUNCTION("""COMPUTED_VALUE"""),463588.72015640175) -> 463588.72 | AJ13: =IFERROR(__xludf.DUMMYFUNCTION("""COMPUTED_VALUE"""),334199.8509789969) -> 334199.85 | AK13: =IFERROR(__xludf.DUMMYFUNCTION("""COMPUTED_VALUE"""),317441.7450971478) -> 317441.75 | AL13: =IFERROR(__xludf.DUMMYFUNCTION("""COMPUTED_VALUE"""),436823.8940611481) -> 436823.89 | AM13: =IFERROR(__xludf.DUMMYFUNCTION("""COMPUTED_VALUE"""),381726.2698073302) -> 381726.27 | AN13: =IFERROR(__xludf.DUMMYFUNCTION("""COMPUTED_VALUE"""),388355.47973680403) -> 388355.48 | AO13: =IFERROR(__xludf.DUMMYFUNCTION("""COMPUTED_VALUE"""),401169.1437792823) -> 401169.14 | AP13: =IFERROR(__xludf.DUMMYFUNCTION("""COMPUTED_VALUE"""),470344.085918076) -> 470344.09 | AQ13: =IFERROR(__xludf.DUMMYFUNCTION("""COMPUTED_VALUE"""),379666.4171588573) -> 379666.42 | AR13: =IFERROR(__xludf.DUMMYFUNCTION("""COMPUTED_VALUE"""),387754.4341500466) -> 387754.43 | AS13: =IFERROR(__xludf.DUMMYFUNCTION("""COMPUTED_VALUE"""),385306.0909179916) -> 385306.09 | AT13: =IFERROR(__xludf.DUMMYFUNCTION("""COMPUTED_VALUE"""),438730.00689564575) -> 438730.01 | AU13: =IFERROR(__xludf.DUMMYFUNCTION("""COMPUTED_VALUE"""),453127.5113884203) -> 453127.51 | AV13: =IFERROR(__xludf.DUMMYFUNCTION("""COMPUTED_VALUE"""),326658.39395187143) -> 326658.39 | AW13: =IFERROR(__xludf.DUMMYFUNCTION("""COMPUTED_VALUE"""),310278.4466329116) -> 310278.45 | AX13: =IFERROR(__xludf.DUMMYFUNCTION("""COMPUTED_VALUE"""),426966.6526056731) -> 426966.65 | AY13: =IFERROR(__xludf.DUMMYFUNCTION("""COMPUTED_VALUE"""),373112.34538024303) -> 373112.35 | AZ13: =IFERROR(__xludf.DUMMYFUNCTION("""COMPUTED_VALUE"""),379591.96247877914) -> 379591.96 | BA13: =IFERROR(__xludf.DUMMYFUNCTION("""COMPUTED_VALUE"""),378595.21925960085) -> 378595.22 | BB13: =IFERROR(__xludf.DUMMYFUNCTION("""COMPUTED_VALUE"""),459808.37839351106) -> 459808.38 | BC13: =IFERROR(__xludf.DUMMYFUNCTION("""COMPUTED_VALUE"""),371161.889414499) -> 371161.89 | BD13: =IFERROR(__xludf.DUMMYFUNCTION("""COMPUTED_VALUE"""),379068.7348250857) -> 379068.73 | BE13: =IFERROR(__xludf.DUMMYFUNCTION("""COMPUTED_VALUE"""),376675.23448142863) -> 376675.23 | BF13: =IFERROR(__xludf.DUMMYFUNCTION("""COMPUTED_VALUE"""),428902.4547411834) -> 428902.45 | BG13: =IFERROR(__xludf.DUMMYFUNCTION("""COMPUTED_VALUE"""),442977.45513331966) -> 442977.46 | BH13: =IFERROR(__xludf.DUMMYFUNCTION("""COMPUTED_VALUE"""),319341.2459273495) -> 319341.25 | BI13: =IFERROR(__xludf.DUMMYFUNCTION("""COMPUTED_VALUE"""),303328.2094283343) -> 303328.21 | BJ13: =IFERROR(__xludf.DUMMYFUNCTION("""COMPUTED_VALUE"""),417402.5995873061) -> 417402.6 | BK13: =IFERROR(__xludf.DUMMYFUNCTION("""COMPUTED_VALUE"""),364754.6288437257) -> 364754.63 | BL13: =SUM(D13:BK13) -> 24208026 | BM13: =AVERAGE(D13:BK13) -> 403467.1
C14: Property Count | D14: =IFERROR(__xludf.DUMMYFUNCTION("IF(IMPORTRANGE(""https://docs.google.com/spreadsheets/d/113Ah55vN7ZtqjRW56fWOsnIaTUko57qPvHiPNGZ2OQ0/edit?usp=sharing"", ""P1!$B$11"")=1, IFERROR(INDEX(IMPORTRANGE(""https://docs.google.com/spreadsheets/d/113Ah55vN7ZtqjRW56fWOsnIaTUko57qPvHiPNGZ2OQ0/"&"edit?usp=sharing"", ""P1!$E$6:$BL$6""), MATCH(D3, IMPORTRANGE(""https://docs.google.com/spreadsheets/d/113Ah55vN7ZtqjRW56fWOsnIaTUko57qPvHiPNGZ2OQ0/edit?usp=sharing"", ""P1!$E$4:$BL$4""), 0)), ""Unknown""), IF(IMPORTRANGE(""https://docs.google."&"com/spreadsheets/d/113Ah55vN7ZtqjRW56fWOsnIaTUko57qPvHiPNGZ2OQ0/edit?usp=sharing"", ""P1!$B$11"")=2, 0, ""Unknown""))"),15.2) -> 15.2 | E14: =IFERROR(__xludf.DUMMYFUNCTION("IF(IMPORTRANGE(""https://docs.google.com/spreadsheets/d/113Ah55vN7ZtqjRW56fWOsnIaTUko57qPvHiPNGZ2OQ0/edit?usp=sharing"", ""P1!$B$11"")=1, IFERROR(INDEX(IMPORTRANGE(""https://docs.google.com/spreadsheets/d/113Ah55vN7ZtqjRW56fWOsnIaTUko57qPvHiPNGZ2OQ0/"&"edit?usp=sharing"", ""P1!$E$6:$BL$6""), MATCH(E3, IMPORTRANGE(""https://docs.google.com/spreadsheets/d/113Ah55vN7ZtqjRW56fWOsnIaTUko57qPvHiPNGZ2OQ0/edit?usp=sharing"", ""P1!$E$4:$BL$4""), 0)), ""Unknown""), IF(IMPORTRANGE(""https://docs.google."&"com/spreadsheets/d/113Ah55vN7ZtqjRW56fWOsnIaTUko57qPvHiPNGZ2OQ0/edit?usp=sharing"", ""P1!$B$11"")=2, 0, ""Unknown""))"),15.120330917312678) -> 15.120331 | F14: =IFERROR(__xludf.DUMMYFUNCTION("IF(IMPORTRANGE(""https://docs.google.com/spreadsheets/d/113Ah55vN7ZtqjRW56fWOsnIaTUko57qPvHiPNGZ2OQ0/edit?usp=sharing"", ""P1!$B$11"")=1, IFERROR(INDEX(IMPORTRANGE(""https://docs.google.com/spreadsheets/d/113Ah55vN7ZtqjRW56fWOsnIaTUko57qPvHiPNGZ2OQ0/"&"edit?usp=sharing"", ""P1!$E$6:$BL$6""), MATCH(F3, IMPORTRANGE(""https://docs.google.com/spreadsheets/d/113Ah55vN7ZtqjRW56fWOsnIaTUko57qPvHiPNGZ2OQ0/edit?usp=sharing"", ""P1!$E$4:$BL$4""), 0)), ""Unknown""), IF(IMPORTRANGE(""https://docs.google."&"com/spreadsheets/d/113Ah55vN7ZtqjRW56fWOsnIaTUko57qPvHiPNGZ2OQ0/edit?usp=sharing"", ""P1!$B$11"")=2, 0, ""Unknown""))"),15.048730722530854) -> 15.048731 | G14: =IFERROR(__xludf.DUMMYFUNCTION("IF(IMPORTRANGE(""https://docs.google.com/spreadsheets/d/113Ah55vN7ZtqjRW56fWOsnIaTUko57qPvHiPNGZ2OQ0/edit?usp=sharing"", ""P1!$B$11"")=1, IFERROR(INDEX(IMPORTRANGE(""https://docs.google.com/spreadsheets/d/113Ah55vN7ZtqjRW56fWOsnIaTUko57qPvHiPNGZ2OQ0/"&"edit?usp=sharing"", ""P1!$E$6:$BL$6""), MATCH(G3, IMPORTRANGE(""https://docs.google.com/spreadsheets/d/113Ah55vN7ZtqjRW56fWOsnIaTUko57qPvHiPNGZ2OQ0/edit?usp=sharing"", ""P1!$E$4:$BL$4""), 0)), ""Unknown""), IF(IMPORTRANGE(""https://docs.google."&"com/spreadsheets/d/113Ah55vN7ZtqjRW56fWOsnIaTUko57qPvHiPNGZ2OQ0/edit?usp=sharing"", ""P1!$B$11"")=2, 0, ""Unknown""))"),14.969854500670818) -> 14.969855 | H14: =IFERROR(__xludf.DUMMYFUNCTION("IF(IMPORTRANGE(""https://docs.google.com/spreadsheets/d/113Ah55vN7ZtqjRW56fWOsnIaTUko57qPvHiPNGZ2OQ0/edit?usp=sharing"", ""P1!$B$11"")=1, IFERROR(INDEX(IMPORTRANGE(""https://docs.google.com/spreadsheets/d/113Ah55vN7ZtqjRW56fWOsnIaTUko57qPvHiPNGZ2OQ0/"&"edit?usp=sharing"", ""P1!$E$6:$BL$6""), MATCH(H3, IMPORTRANGE(""https://docs.google.com/spreadsheets/d/113Ah55vN7ZtqjRW56fWOsnIaTUko57qPvHiPNGZ2OQ0/edit?usp=sharing"", ""P1!$E$4:$BL$4""), 0)), ""Unknown""), IF(IMPORTRANGE(""https://docs.google."&"com/spreadsheets/d/113Ah55vN7ZtqjRW56fWOsnIaTUko57qPvHiPNGZ2OQ0/edit?usp=sharing"", ""P1!$B$11"")=2, 0, ""Unknown""))"),14.893916326951206) -> 14.893916 | I14: =IFERROR(__xludf.DUMMYFUNCTION("IF(IMPORTRANGE(""https://docs.google.com/spreadsheets/d/113Ah55vN7ZtqjRW56fWOsnIaTUko57qPvHiPNGZ2OQ0/edit?usp=sharing"", ""P1!$B$11"")=1, IFERROR(INDEX(IMPORTRANGE(""https://docs.google.com/spreadsheets/d/113Ah55vN7ZtqjRW56fWOsnIaTUko57qPvHiPNGZ2OQ0/"&"edit?usp=sharing"", ""P1!$E$6:$BL$6""), MATCH(I3, IMPORTRANGE(""https://docs.google.com/spreadsheets/d/113Ah55vN7ZtqjRW56fWOsnIaTUko57qPvHiPNGZ2OQ0/edit?usp=sharing"", ""P1!$E$4:$BL$4""), 0)), ""Unknown""), IF(IMPORTRANGE(""https://docs.google."&"com/spreadsheets/d/113Ah55vN7ZtqjRW56fWOsnIaTUko57qPvHiPNGZ2OQ0/edit?usp=sharing"", ""P1!$B$11"")=2, 0, ""Unknown""))"),14.8158515472545) -> 14.815852 | J14: =IFERROR(__xludf.DUMMYFUNCTION("IF(IMPORTRANGE(""https://docs.google.com/spreadsheets/d/113Ah55vN7ZtqjRW56fWOsnIaTUko57qPvHiPNGZ2OQ0/edit?usp=sharing"", ""P1!$B$11"")=1, IFERROR(INDEX(IMPORTRANGE(""https://docs.google.com/spreadsheets/d/113Ah55vN7ZtqjRW56fWOsnIaTUko57qPvHiPNGZ2OQ0/"&"edit?usp=sharing"", ""P1!$E$6:$BL$6""), MATCH(J3, IMPORTRANGE(""https://docs.google.com/spreadsheets/d/113Ah55vN7ZtqjRW56fWOsnIaTUko57qPvHiPNGZ2OQ0/edit?usp=sharing"", ""P1!$E$4:$BL$4""), 0)), ""Unknown""), IF(IMPORTRANGE(""https://docs.google."&"com/spreadsheets/d/113Ah55vN7ZtqjRW56fWOsnIaTUko57qPvHiPNGZ2OQ0/edit?usp=sharing"", ""P1!$B$11"")=2, 0, ""Unknown""))"),14.740694590415073) -> 14.740695 | K14: =IFERROR(__xludf.DUMMYFUNCTION("IF(IMPORTRANGE(""https://docs.google.com/spreadsheets/d/113Ah55vN7ZtqjRW56fWOsnIaTUko57qPvHiPNGZ2OQ0/edit?usp=sharing"", ""P1!$B$11"")=1, IFERROR(INDEX(IMPORTRANGE(""https://docs.google.com/spreadsheets/d/113Ah55vN7ZtqjRW56fWOsnIaTUko57qPvHiPNGZ2OQ0/"&"edit?usp=sharing"", ""P1!$E$6:$BL$6""), MATCH(K3, IMPORTRANGE(""https://docs.google.com/spreadsheets/d/113Ah55vN7ZtqjRW56fWOsnIaTUko57qPvHiPNGZ2OQ0/edit?usp=sharing"", ""P1!$E$4:$BL$4""), 0)), ""Unknown""), IF(IMPORTRANGE(""https://docs.google."&"com/spreadsheets/d/113Ah55vN7ZtqjRW56fWOsnIaTUko57qPvHiPNGZ2OQ0/edit?usp=sharing"", ""P1!$B$11"")=2, 0, ""Unknown""))"),14.663432905139262) -> 14.663433 | L14: =IFERROR(__xludf.DUMMYFUNCTION("IF(IMPORTRANGE(""https://docs.google.com/spreadsheets/d/113Ah55vN7ZtqjRW56fWOsnIaTUko57qPvHiPNGZ2OQ0/edit?usp=sharing"", ""P1!$B$11"")=1, IFERROR(INDEX(IMPORTRANGE(""https://docs.google.com/spreadsheets/d/113Ah55vN7ZtqjRW56fWOsnIaTUko57qPvHiPNGZ2OQ0/"&"edit?usp=sharing"", ""P1!$E$6:$BL$6""), MATCH(L3, IMPORTRANGE(""https://docs.google.com/spreadsheets/d/113Ah55vN7ZtqjRW56fWOsnIaTUko57qPvHiPNGZ2OQ0/edit?usp=sharing"", ""P1!$E$4:$BL$4""), 0)), ""Unknown""), IF(IMPORTRANGE(""https://docs.google."&"com/spreadsheets/d/113Ah55vN7ZtqjRW56fWOsnIaTUko57qPvHiPNGZ2OQ0/edit?usp=sharing"", ""P1!$B$11"")=2, 0, ""Unknown""))"),14.586576178257712) -> 14.586576 | M14: =IFERROR(__xludf.DUMMYFUNCTION("IF(IMPORTRANGE(""https://docs.google.com/spreadsheets/d/113Ah55vN7ZtqjRW56fWOsnIaTUko57qPvHiPNGZ2OQ0/edit?usp=sharing"", ""P1!$B$11"")=1, IFERROR(INDEX(IMPORTRANGE(""https://docs.google.com/spreadsheets/d/113Ah55vN7ZtqjRW56fWOsnIaTUko57qPvHiPNGZ2OQ0/"&"edit?usp=sharing"", ""P1!$E$6:$BL$6""), MATCH(M3, IMPORTRANGE(""https://docs.google.com/spreadsheets/d/113Ah55vN7ZtqjRW56fWOsnIaTUko57qPvHiPNGZ2OQ0/edit?usp=sharing"", ""P1!$E$4:$BL$4""), 0)), ""Unknown""), IF(IMPORTRANGE(""https://docs.google."&"com/spreadsheets/d/113Ah55vN7ZtqjRW56fWOsnIaTUko57qPvHiPNGZ2OQ0/edit?usp=sharing"", ""P1!$B$11"")=2, 0, ""Unknown""))"),14.512582275661714) -> 14.512582 | N14: =IFERROR(__xludf.DUMMYFUNCTION("IF(IMPORTRANGE(""https://docs.google.com/spreadsheets/d/113Ah55vN7ZtqjRW56fWOsnIaTUko57qPvHiPNGZ2OQ0/edit?usp=sharing"", ""P1!$B$11"")=1, IFERROR(INDEX(IMPORTRANGE(""https://docs.google.com/spreadsheets/d/113Ah55vN7ZtqjRW56fWOsnIaTUko57qPvHiPNGZ2OQ0/"&"edit?usp=sharing"", ""P1!$E$6:$BL$6""), MATCH(N3, IMPORTRANGE(""https://docs.google.com/spreadsheets/d/113Ah55vN7ZtqjRW56fWOsnIaTUko57qPvHiPNGZ2OQ0/edit?usp=sharing"", ""P1!$E$4:$BL$4""), 0)), ""Unknown""), IF(IMPORTRANGE(""https://docs.google."&"com/spreadsheets/d/113Ah55vN7ZtqjRW56fWOsnIaTUko57qPvHiPNGZ2OQ0/edit?usp=sharing"", ""P1!$B$11"")=2, 0, ""Unknown""))"),14.436516215311302) -> 14.436516 | O14: =IFERROR(__xludf.DUMMYFUNCTION("IF(IMPORTRANGE(""https://docs.google.com/spreadsheets/d/113Ah55vN7ZtqjRW56fWOsnIaTUko57qPvHiPNGZ2OQ0/edit?usp=sharing"", ""P1!$B$11"")=1, IFERROR(INDEX(IMPORTRANGE(""https://docs.google.com/spreadsheets/d/113Ah55vN7ZtqjRW56fWOsnIaTUko57qPvHiPNGZ2OQ0/"&"edit?usp=sharing"", ""P1!$E$6:$BL$6""), MATCH(O3, IMPORTRANGE(""https://docs.google.com/spreadsheets/d/113Ah55vN7ZtqjRW56fWOsnIaTUko57qPvHiPNGZ2OQ0/edit?usp=sharing"", ""P1!$E$4:$BL$4""), 0)), ""Unknown""), IF(IMPORTRANGE(""https://docs.google."&"com/spreadsheets/d/113Ah55vN7ZtqjRW56fWOsnIaTUko57qPvHiPNGZ2OQ0/edit?usp=sharing"", ""P1!$B$11"")=2, 0, ""Unknown""))"),14.363283527831594) -> 14.363284 | P14: =IFERROR(__xludf.DUMMYFUNCTION("IF(IMPORTRANGE(""https://docs.google.com/spreadsheets/d/113Ah55vN7ZtqjRW56fWOsnIaTUko57qPvHiPNGZ2OQ0/edit?usp=sharing"", ""P1!$B$11"")=1, IFERROR(INDEX(IMPORTRANGE(""https://docs.google.com/spreadsheets/d/113Ah55vN7ZtqjRW56fWOsnIaTUko57qPvHiPNGZ2OQ0/"&"edit?usp=sharing"", ""P1!$E$6:$BL$6""), MATCH(P3, IMPORTRANGE(""https://docs.google.com/spreadsheets/d/113Ah55vN7ZtqjRW56fWOsnIaTUko57qPvHiPNGZ2OQ0/edit?usp=sharing"", ""P1!$E$4:$BL$4""), 0)), ""Unknown""), IF(IMPORTRANGE(""https://docs.google."&"com/spreadsheets/d/113Ah55vN7ZtqjRW56fWOsnIaTUko57qPvHiPNGZ2OQ0/edit?usp=sharing"", ""P1!$B$11"")=2, 0, ""Unknown""))"),14.287999999999998) -> 14.288 | Q14: =IFERROR(__xludf.DUMMYFUNCTION("IF(IMPORTRANGE(""https://docs.google.com/spreadsheets/d/113Ah55vN7ZtqjRW56fWOsnIaTUko57qPvHiPNGZ2OQ0/edit?usp=sharing"", ""P1!$B$11"")=1, IFERROR(INDEX(IMPORTRANGE(""https://docs.google.com/spreadsheets/d/113Ah55vN7ZtqjRW56fWOsnIaTUko57qPvHiPNGZ2OQ0/"&"edit?usp=sharing"", ""P1!$E$6:$BL$6""), MATCH(Q3, IMPORTRANGE(""https://docs.google.com/spreadsheets/d/113Ah55vN7ZtqjRW56fWOsnIaTUko57qPvHiPNGZ2OQ0/edit?usp=sharing"", ""P1!$E$4:$BL$4""), 0)), ""Unknown""), IF(IMPORTRANGE(""https://docs.google."&"com/spreadsheets/d/113Ah55vN7ZtqjRW56fWOsnIaTUko57qPvHiPNGZ2OQ0/edit?usp=sharing"", ""P1!$B$11"")=2, 0, ""Unknown""))"),14.213111062273915) -> 14.213111 | R14: =IFERROR(__xludf.DUMMYFUNCTION("IF(IMPORTRANGE(""https://docs.google.com/spreadsheets/d/113Ah55vN7ZtqjRW56fWOsnIaTUko57qPvHiPNGZ2OQ0/edit?usp=sharing"", ""P1!$B$11"")=1, IFERROR(INDEX(IMPORTRANGE(""https://docs.google.com/spreadsheets/d/113Ah55vN7ZtqjRW56fWOsnIaTUko57qPvHiPNGZ2OQ0/"&"edit?usp=sharing"", ""P1!$E$6:$BL$6""), MATCH(R3, IMPORTRANGE(""https://docs.google.com/spreadsheets/d/113Ah55vN7ZtqjRW56fWOsnIaTUko57qPvHiPNGZ2OQ0/edit?usp=sharing"", ""P1!$E$4:$BL$4""), 0)), ""Unknown""), IF(IMPORTRANGE(""https://docs.google."&"com/spreadsheets/d/113Ah55vN7ZtqjRW56fWOsnIaTUko57qPvHiPNGZ2OQ0/edit?usp=sharing"", ""P1!$B$11"")=2, 0, ""Unknown""))"),14.145806879179002) -> 14.145807 | S14: =IFERROR(__xludf.DUMMYFUNCTION("IF(IMPORTRANGE(""https://docs.google.com/spreadsheets/d/113Ah55vN7ZtqjRW56fWOsnIaTUko57qPvHiPNGZ2OQ0/edit?usp=sharing"", ""P1!$B$11"")=1, IFERROR(INDEX(IMPORTRANGE(""https://docs.google.com/spreadsheets/d/113Ah55vN7ZtqjRW56fWOsnIaTUko57qPvHiPNGZ2OQ0/"&"edit?usp=sharing"", ""P1!$E$6:$BL$6""), MATCH(S3, IMPORTRANGE(""https://docs.google.com/spreadsheets/d/113Ah55vN7ZtqjRW56fWOsnIaTUko57qPvHiPNGZ2OQ0/edit?usp=sharing"", ""P1!$E$4:$BL$4""), 0)), ""Unknown""), IF(IMPORTRANGE(""https://docs.google."&"com/spreadsheets/d/113Ah55vN7ZtqjRW56fWOsnIaTUko57qPvHiPNGZ2OQ0/edit?usp=sharing"", ""P1!$B$11"")=2, 0, ""Unknown""))"),14.071663230630568) -> 14.071663 | T14: =IFERROR(__xludf.DUMMYFUNCTION("IF(IMPORTRANGE(""https://docs.google.com/spreadsheets/d/113Ah55vN7ZtqjRW56fWOsnIaTUko57qPvHiPNGZ2OQ0/edit?usp=sharing"", ""P1!$B$11"")=1, IFERROR(INDEX(IMPORTRANGE(""https://docs.google.com/spreadsheets/d/113Ah55vN7ZtqjRW56fWOsnIaTUko57qPvHiPNGZ2OQ0/"&"edit?usp=sharing"", ""P1!$E$6:$BL$6""), MATCH(T3, IMPORTRANGE(""https://docs.google.com/spreadsheets/d/113Ah55vN7ZtqjRW56fWOsnIaTUko57qPvHiPNGZ2OQ0/edit?usp=sharing"", ""P1!$E$4:$BL$4""), 0)), ""Unknown""), IF(IMPORTRANGE(""https://docs.google."&"com/spreadsheets/d/113Ah55vN7ZtqjRW56fWOsnIaTUko57qPvHiPNGZ2OQ0/edit?usp=sharing"", ""P1!$B$11"")=2, 0, ""Unknown""))"),14.000281347334132) -> 14.000281 | U14: =IFERROR(__xludf.DUMMYFUNCTION("IF(IMPORTRANGE(""https://docs.google.com/spreadsheets/d/113Ah55vN7ZtqjRW56fWOsnIaTUko57qPvHiPNGZ2OQ0/edit?usp=sharing"", ""P1!$B$11"")=1, IFERROR(INDEX(IMPORTRANGE(""https://docs.google.com/spreadsheets/d/113Ah55vN7ZtqjRW56fWOsnIaTUko57qPvHiPNGZ2OQ0/"&"edit?usp=sharing"", ""P1!$E$6:$BL$6""), MATCH(U3, IMPORTRANGE(""https://docs.google.com/spreadsheets/d/113Ah55vN7ZtqjRW56fWOsnIaTUko57qPvHiPNGZ2OQ0/edit?usp=sharing"", ""P1!$E$4:$BL$4""), 0)), ""Unknown""), IF(IMPORTRANGE(""https://docs.google."&"com/spreadsheets/d/113Ah55vN7ZtqjRW56fWOsnIaTUko57qPvHiPNGZ2OQ0/edit?usp=sharing"", ""P1!$B$11"")=2, 0, ""Unknown""))"),13.926900454419227) -> 13.9269 | V14: =IFERROR(__xludf.DUMMYFUNCTION("IF(IMPORTRANGE(""https://docs.google.com/spreadsheets/d/113Ah55vN7ZtqjRW56fWOsnIaTUko57qPvHiPNGZ2OQ0/edit?usp=sharing"", ""P1!$B$11"")=1, IFERROR(INDEX(IMPORTRANGE(""https://docs.google.com/spreadsheets/d/113Ah55vN7ZtqjRW56fWOsnIaTUko57qPvHiPNGZ2OQ0/"&"edit?usp=sharing"", ""P1!$E$6:$BL$6""), MATCH(V3, IMPORTRANGE(""https://docs.google.com/spreadsheets/d/113Ah55vN7ZtqjRW56fWOsnIaTUko57qPvHiPNGZ2OQ0/edit?usp=sharing"", ""P1!$E$4:$BL$4""), 0)), ""Unknown""), IF(IMPORTRANGE(""https://docs.google."&"com/spreadsheets/d/113Ah55vN7ZtqjRW56fWOsnIaTUko57qPvHiPNGZ2OQ0/edit?usp=sharing"", ""P1!$B$11"")=2, 0, ""Unknown""))"),13.856252914990167) -> 13.856253 | W14: =IFERROR(__xludf.DUMMYFUNCTION("IF(IMPORTRANGE(""https://docs.google.com/spreadsheets/d/113Ah55vN7ZtqjRW56fWOsnIaTUko57qPvHiPNGZ2OQ0/edit?usp=sharing"", ""P1!$B$11"")=1, IFERROR(INDEX(IMPORTRANGE(""https://docs.google.com/spreadsheets/d/113Ah55vN7ZtqjRW56fWOsnIaTUko57qPvHiPNGZ2OQ0/"&"edit?usp=sharing"", ""P1!$E$6:$BL$6""), MATCH(W3, IMPORTRANGE(""https://docs.google.com/spreadsheets/d/113Ah55vN7ZtqjRW56fWOsnIaTUko57qPvHiPNGZ2OQ0/edit?usp=sharing"", ""P1!$E$4:$BL$4""), 0)), ""Unknown""), IF(IMPORTRANGE(""https://docs.google."&"com/spreadsheets/d/113Ah55vN7ZtqjRW56fWOsnIaTUko57qPvHiPNGZ2OQ0/edit?usp=sharing"", ""P1!$B$11"")=2, 0, ""Unknown""))"),13.783626930830906) -> 13.783627 | X14: =IFERROR(__xludf.DUMMYFUNCTION("IF(IMPORTRANGE(""https://docs.google.com/spreadsheets/d/113Ah55vN7ZtqjRW56fWOsnIaTUko57qPvHiPNGZ2OQ0/edit?usp=sharing"", ""P1!$B$11"")=1, IFERROR(INDEX(IMPORTRANGE(""https://docs.google.com/spreadsheets/d/113Ah55vN7ZtqjRW56fWOsnIaTUko57qPvHiPNGZ2OQ0/"&"edit?usp=sharing"", ""P1!$E$6:$BL$6""), MATCH(X3, IMPORTRANGE(""https://docs.google.com/spreadsheets/d/113Ah55vN7ZtqjRW56fWOsnIaTUko57qPvHiPNGZ2OQ0/edit?usp=sharing"", ""P1!$E$4:$BL$4""), 0)), ""Unknown""), IF(IMPORTRANGE(""https://docs.google."&"com/spreadsheets/d/113Ah55vN7ZtqjRW56fWOsnIaTUko57qPvHiPNGZ2OQ0/edit?usp=sharing"", ""P1!$B$11"")=2, 0, ""Unknown""))"),13.711381607562249) -> 13.711382 | Y14: =IFERROR(__xludf.DUMMYFUNCTION("IF(IMPORTRANGE(""https://docs.google.com/spreadsheets/d/113Ah55vN7ZtqjRW56fWOsnIaTUko57qPvHiPNGZ2OQ0/edit?usp=sharing"", ""P1!$B$11"")=1, IFERROR(INDEX(IMPORTRANGE(""https://docs.google.com/spreadsheets/d/113Ah55vN7ZtqjRW56fWOsnIaTUko57qPvHiPNGZ2OQ0/"&"edit?usp=sharing"", ""P1!$E$6:$BL$6""), MATCH(Y3, IMPORTRANGE(""https://docs.google.com/spreadsheets/d/113Ah55vN7ZtqjRW56fWOsnIaTUko57qPvHiPNGZ2OQ0/edit?usp=sharing"", ""P1!$E$4:$BL$4""), 0)), ""Unknown""), IF(IMPORTRANGE(""https://docs.google."&"com/spreadsheets/d/113Ah55vN7ZtqjRW56fWOsnIaTUko57qPvHiPNGZ2OQ0/edit?usp=sharing"", ""P1!$B$11"")=2, 0, ""Unknown""))"),13.641827339122012) -> 13.641827 | Z14: =IFERROR(__xludf.DUMMYFUNCTION("IF(IMPORTRANGE(""https://docs.google.com/spreadsheets/d/113Ah55vN7ZtqjRW56fWOsnIaTUko57qPvHiPNGZ2OQ0/edit?usp=sharing"", ""P1!$B$11"")=1, IFERROR(INDEX(IMPORTRANGE(""https://docs.google.com/spreadsheets/d/113Ah55vN7ZtqjRW56fWOsnIaTUko57qPvHiPNGZ2OQ0/"&"edit?usp=sharing"", ""P1!$E$6:$BL$6""), MATCH(Z3, IMPORTRANGE(""https://docs.google.com/spreadsheets/d/113Ah55vN7ZtqjRW56fWOsnIaTUko57qPvHiPNGZ2OQ0/edit?usp=sharing"", ""P1!$E$4:$BL$4""), 0)), ""Unknown""), IF(IMPORTRANGE(""https://docs.google."&"com/spreadsheets/d/113Ah55vN7ZtqjRW56fWOsnIaTUko57qPvHiPNGZ2OQ0/edit?usp=sharing"", ""P1!$B$11"")=2, 0, ""Unknown""))"),13.570325242392624) -> 13.570325 | AA14: =IFERROR(__xludf.DUMMYFUNCTION("IF(IMPORTRANGE(""https://docs.google.com/spreadsheets/d/113Ah55vN7ZtqjRW56fWOsnIaTUko57qPvHiPNGZ2OQ0/edit?usp=sharing"", ""P1!$B$11"")=1, IFERROR(INDEX(IMPORTRANGE(""https://docs.google.com/spreadsheets/d/113Ah55vN7ZtqjRW56fWOsnIaTUko57qPvHiPNGZ2OQ0/"&"edit?usp=sharing"", ""P1!$E$6:$BL$6""), MATCH(AA3, IMPORTRANGE(""https://docs.google.com/spreadsheets/d/113Ah55vN7ZtqjRW56fWOsnIaTUko57qPvHiPNGZ2OQ0/edit?usp=sharing"", ""P1!$E$4:$BL$4""), 0)), ""Unknown""), IF(IMPORTRANGE(""https://docs.google"&".com/spreadsheets/d/113Ah55vN7ZtqjRW56fWOsnIaTUko57qPvHiPNGZ2OQ0/edit?usp=sharing"", ""P1!$B$11"")=2, 0, ""Unknown""))"),13.501486516161698) -> 13.501487 | AB14: =IFERROR(__xludf.DUMMYFUNCTION("IF(IMPORTRANGE(""https://docs.google.com/spreadsheets/d/113Ah55vN7ZtqjRW56fWOsnIaTUko57qPvHiPNGZ2OQ0/edit?usp=sharing"", ""P1!$B$11"")=1, IFERROR(INDEX(IMPORTRANGE(""https://docs.google.com/spreadsheets/d/113Ah55vN7ZtqjRW56fWOsnIaTUko57qPvHiPNGZ2OQ0/"&"edit?usp=sharing"", ""P1!$E$6:$BL$6""), MATCH(AB3, IMPORTRANGE(""https://docs.google.com/spreadsheets/d/113Ah55vN7ZtqjRW56fWOsnIaTUko57qPvHiPNGZ2OQ0/edit?usp=sharing"", ""P1!$E$4:$BL$4""), 0)), ""Unknown""), IF(IMPORTRANGE(""https://docs.google"&".com/spreadsheets/d/113Ah55vN7ZtqjRW56fWOsnIaTUko57qPvHiPNGZ2OQ0/edit?usp=sharing"", ""P1!$B$11"")=2, 0, ""Unknown""))"),13.430719999999999) -> 13.43072 | AC14: =IFERROR(__xludf.DUMMYFUNCTION("IF(IMPORTRANGE(""https://docs.google.com/spreadsheets/d/113Ah55vN7ZtqjRW56fWOsnIaTUko57qPvHiPNGZ2OQ0/edit?usp=sharing"", ""P1!$B$11"")=1, IFERROR(INDEX(IMPORTRANGE(""https://docs.google.com/spreadsheets/d/113Ah55vN7ZtqjRW56fWOsnIaTUko57qPvHiPNGZ2OQ0/"&"edit?usp=sharing"", ""P1!$E$6:$BL$6""), MATCH(AC3, IMPORTRANGE(""https://docs.google.com/spreadsheets/d/113Ah55vN7ZtqjRW56fWOsnIaTUko57qPvHiPNGZ2OQ0/edit?usp=sharing"", ""P1!$E$4:$BL$4""), 0)), ""Unknown""), IF(IMPORTRANGE(""https://docs.google"&".com/spreadsheets/d/113Ah55vN7ZtqjRW56fWOsnIaTUko57qPvHiPNGZ2OQ0/edit?usp=sharing"", ""P1!$B$11"")=2, 0, ""Unknown""))"),13.360324398537479) -> 13.360324 | AD14: =IFERROR(__xludf.DUMMYFUNCTION("IF(IMPORTRANGE(""https://docs.google.com/spreadsheets/d/113Ah55vN7ZtqjRW56fWOsnIaTUko57qPvHiPNGZ2OQ0/edit?usp=sharing"", ""P1!$B$11"")=1, IFERROR(INDEX(IMPORTRANGE(""https://docs.google.com/spreadsheets/d/113Ah55vN7ZtqjRW56fWOsnIaTUko57qPvHiPNGZ2OQ0/"&"edit?usp=sharing"", ""P1!$E$6:$BL$6""), MATCH(AD3, IMPORTRANGE(""https://docs.google.com/spreadsheets/d/113Ah55vN7ZtqjRW56fWOsnIaTUko57qPvHiPNGZ2OQ0/edit?usp=sharing"", ""P1!$E$4:$BL$4""), 0)), ""Unknown""), IF(IMPORTRANGE(""https://docs.google"&".com/spreadsheets/d/113Ah55vN7ZtqjRW56fWOsnIaTUko57qPvHiPNGZ2OQ0/edit?usp=sharing"", ""P1!$B$11"")=2, 0, ""Unknown""))"),13.297058466428263) -> 13.297058 | AE14: =IFERROR(__xludf.DUMMYFUNCTION("IF(IMPORTRANGE(""https://docs.google.com/spreadsheets/d/113Ah55vN7ZtqjRW56fWOsnIaTUko57qPvHiPNGZ2OQ0/edit?usp=sharing"", ""P1!$B$11"")=1, IFERROR(INDEX(IMPORTRANGE(""https://docs.google.com/spreadsheets/d/113Ah55vN7ZtqjRW56fWOsnIaTUko57qPvHiPNGZ2OQ0/"&"edit?usp=sharing"", ""P1!$E$6:$BL$6""), MATCH(AE3, IMPORTRANGE(""https://docs.google.com/spreadsheets/d/113Ah55vN7ZtqjRW56fWOsnIaTUko57qPvHiPNGZ2OQ0/edit?usp=sharing"", ""P1!$E$4:$BL$4""), 0)), ""Unknown""), IF(IMPORTRANGE(""https://docs.google"&".com/spreadsheets/d/113Ah55vN7ZtqjRW56fWOsnIaTUko57qPvHiPNGZ2OQ0/edit?usp=sharing"", ""P1!$B$11"")=2, 0, ""Unknown""))"),13.227363436792734) -> 13.227363 | AF14: =IFERROR(__xludf.DUMMYFUNCTION("IF(IMPORTRANGE(""https://docs.google.com/spreadsheets/d/113Ah55vN7ZtqjRW56fWOsnIaTUko57qPvHiPNGZ2OQ0/edit?usp=sharing"", ""P1!$B$11"")=1, IFERROR(INDEX(IMPORTRANGE(""https://docs.google.com/spreadsheets/d/113Ah55vN7ZtqjRW56fWOsnIaTUko57qPvHiPNGZ2OQ0/"&"edit?usp=sharing"", ""P1!$E$6:$BL$6""), MATCH(AF3, IMPORTRANGE(""https://docs.google.com/spreadsheets/d/113Ah55vN7ZtqjRW56fWOsnIaTUko57qPvHiPNGZ2OQ0/edit?usp=sharing"", ""P1!$E$4:$BL$4""), 0)), ""Unknown""), IF(IMPORTRANGE(""https://docs.google"&".com/spreadsheets/d/113Ah55vN7ZtqjRW56fWOsnIaTUko57qPvHiPNGZ2OQ0/edit?usp=sharing"", ""P1!$B$11"")=2, 0, ""Unknown""))"),13.160264466494082) -> 13.160264 | AG14: =IFERROR(__xludf.DUMMYFUNCTION("IF(IMPORTRANGE(""https://docs.google.com/spreadsheets/d/113Ah55vN7ZtqjRW56fWOsnIaTUko57qPvHiPNGZ2OQ0/edit?usp=sharing"", ""P1!$B$11"")=1, IFERROR(INDEX(IMPORTRANGE(""https://docs.google.com/spreadsheets/d/113Ah55vN7ZtqjRW56fWOsnIaTUko57qPvHiPNGZ2OQ0/"&"edit?usp=sharing"", ""P1!$E$6:$BL$6""), MATCH(AG3, IMPORTRANGE(""https://docs.google.com/spreadsheets/d/113Ah55vN7ZtqjRW56fWOsnIaTUko57qPvHiPNGZ2OQ0/edit?usp=sharing"", ""P1!$E$4:$BL$4""), 0)), ""Unknown""), IF(IMPORTRANGE(""https://docs.google"&".com/spreadsheets/d/113Ah55vN7ZtqjRW56fWOsnIaTUko57qPvHiPNGZ2OQ0/edit?usp=sharing"", ""P1!$B$11"")=2, 0, ""Unknown""))"),13.091286427154074) -> 13.091286 | AH14: =IFERROR(__xludf.DUMMYFUNCTION("IF(IMPORTRANGE(""https://docs.google.com/spreadsheets/d/113Ah55vN7ZtqjRW56fWOsnIaTUko57qPvHiPNGZ2OQ0/edit?usp=sharing"", ""P1!$B$11"")=1, IFERROR(INDEX(IMPORTRANGE(""https://docs.google.com/spreadsheets/d/113Ah55vN7ZtqjRW56fWOsnIaTUko57qPvHiPNGZ2OQ0/"&"edit?usp=sharing"", ""P1!$E$6:$BL$6""), MATCH(AH3, IMPORTRANGE(""https://docs.google.com/spreadsheets/d/113Ah55vN7ZtqjRW56fWOsnIaTUko57qPvHiPNGZ2OQ0/edit?usp=sharing"", ""P1!$E$4:$BL$4""), 0)), ""Unknown""), IF(IMPORTRANGE(""https://docs.google"&".com/spreadsheets/d/113Ah55vN7ZtqjRW56fWOsnIaTUko57qPvHiPNGZ2OQ0/edit?usp=sharing"", ""P1!$B$11"")=2, 0, ""Unknown""))"),13.024877740090757) -> 13.024878 | AI14: =IFERROR(__xludf.DUMMYFUNCTION("IF(IMPORTRANGE(""https://docs.google.com/spreadsheets/d/113Ah55vN7ZtqjRW56fWOsnIaTUko57qPvHiPNGZ2OQ0/edit?usp=sharing"", ""P1!$B$11"")=1, IFERROR(INDEX(IMPORTRANGE(""https://docs.google.com/spreadsheets/d/113Ah55vN7ZtqjRW56fWOsnIaTUko57qPvHiPNGZ2OQ0/"&"edit?usp=sharing"", ""P1!$E$6:$BL$6""), MATCH(AI3, IMPORTRANGE(""https://docs.google.com/spreadsheets/d/113Ah55vN7ZtqjRW56fWOsnIaTUko57qPvHiPNGZ2OQ0/edit?usp=sharing"", ""P1!$E$4:$BL$4""), 0)), ""Unknown""), IF(IMPORTRANGE(""https://docs.google"&".com/spreadsheets/d/113Ah55vN7ZtqjRW56fWOsnIaTUko57qPvHiPNGZ2OQ0/edit?usp=sharing"", ""P1!$B$11"")=2, 0, ""Unknown""))"),12.95660931498105) -> 12.956609 | AJ14: =IFERROR(__xludf.DUMMYFUNCTION("IF(IMPORTRANGE(""https://docs.google.com/spreadsheets/d/113Ah55vN7ZtqjRW56fWOsnIaTUko57qPvHiPNGZ2OQ0/edit?usp=sharing"", ""P1!$B$11"")=1, IFERROR(INDEX(IMPORTRANGE(""https://docs.google.com/spreadsheets/d/113Ah55vN7ZtqjRW56fWOsnIaTUko57qPvHiPNGZ2OQ0/"&"edit?usp=sharing"", ""P1!$E$6:$BL$6""), MATCH(AJ3, IMPORTRANGE(""https://docs.google.com/spreadsheets/d/113Ah55vN7ZtqjRW56fWOsnIaTUko57qPvHiPNGZ2OQ0/edit?usp=sharing"", ""P1!$E$4:$BL$4""), 0)), ""Unknown""), IF(IMPORTRANGE(""https://docs.google"&".com/spreadsheets/d/113Ah55vN7ZtqjRW56fWOsnIaTUko57qPvHiPNGZ2OQ0/edit?usp=sharing"", ""P1!$B$11"")=2, 0, ""Unknown""))"),12.888698711108514) -> 12.888699 | AK14: =IFERROR(__xludf.DUMMYFUNCTION("IF(IMPORTRANGE(""https://docs.google.com/spreadsheets/d/113Ah55vN7ZtqjRW56fWOsnIaTUko57qPvHiPNGZ2OQ0/edit?usp=sharing"", ""P1!$B$11"")=1, IFERROR(INDEX(IMPORTRANGE(""https://docs.google.com/spreadsheets/d/113Ah55vN7ZtqjRW56fWOsnIaTUko57qPvHiPNGZ2OQ0/"&"edit?usp=sharing"", ""P1!$E$6:$BL$6""), MATCH(AK3, IMPORTRANGE(""https://docs.google.com/spreadsheets/d/113Ah55vN7ZtqjRW56fWOsnIaTUko57qPvHiPNGZ2OQ0/edit?usp=sharing"", ""P1!$E$4:$BL$4""), 0)), ""Unknown""), IF(IMPORTRANGE(""https://docs.google"&".com/spreadsheets/d/113Ah55vN7ZtqjRW56fWOsnIaTUko57qPvHiPNGZ2OQ0/edit?usp=sharing"", ""P1!$B$11"")=2, 0, ""Unknown""))"),12.823317698774689) -> 12.823318 | AL14: =IFERROR(__xludf.DUMMYFUNCTION("IF(IMPORTRANGE(""https://docs.google.com/spreadsheets/d/113Ah55vN7ZtqjRW56fWOsnIaTUko57qPvHiPNGZ2OQ0/edit?usp=sharing"", ""P1!$B$11"")=1, IFERROR(INDEX(IMPORTRANGE(""https://docs.google.com/spreadsheets/d/113Ah55vN7ZtqjRW56fWOsnIaTUko57qPvHiPNGZ2OQ0/"&"edit?usp=sharing"", ""P1!$E$6:$BL$6""), MATCH(AL3, IMPORTRANGE(""https://docs.google.com/spreadsheets/d/113Ah55vN7ZtqjRW56fWOsnIaTUko57qPvHiPNGZ2OQ0/edit?usp=sharing"", ""P1!$E$4:$BL$4""), 0)), ""Unknown""), IF(IMPORTRANGE(""https://docs.google"&".com/spreadsheets/d/113Ah55vN7ZtqjRW56fWOsnIaTUko57qPvHiPNGZ2OQ0/edit?usp=sharing"", ""P1!$B$11"")=2, 0, ""Unknown""))"),12.756105727849066) -> 12.756106 | AM14: =IFERROR(__xludf.DUMMYFUNCTION("IF(IMPORTRANGE(""https://docs.google.com/spreadsheets/d/113Ah55vN7ZtqjRW56fWOsnIaTUko57qPvHiPNGZ2OQ0/edit?usp=sharing"", ""P1!$B$11"")=1, IFERROR(INDEX(IMPORTRANGE(""https://docs.google.com/spreadsheets/d/113Ah55vN7ZtqjRW56fWOsnIaTUko57qPvHiPNGZ2OQ0/"&"edit?usp=sharing"", ""P1!$E$6:$BL$6""), MATCH(AM3, IMPORTRANGE(""https://docs.google.com/spreadsheets/d/113Ah55vN7ZtqjRW56fWOsnIaTUko57qPvHiPNGZ2OQ0/edit?usp=sharing"", ""P1!$E$4:$BL$4""), 0)), ""Unknown""), IF(IMPORTRANGE(""https://docs.google"&".com/spreadsheets/d/113Ah55vN7ZtqjRW56fWOsnIaTUko57qPvHiPNGZ2OQ0/edit?usp=sharing"", ""P1!$B$11"")=2, 0, ""Unknown""))"),12.691397325191994) -> 12.691397 | AN14: =IFERROR(__xludf.DUMMYFUNCTION("IF(IMPORTRANGE(""https://docs.google.com/spreadsheets/d/113Ah55vN7ZtqjRW56fWOsnIaTUko57qPvHiPNGZ2OQ0/edit?usp=sharing"", ""P1!$B$11"")=1, IFERROR(INDEX(IMPORTRANGE(""https://docs.google.com/spreadsheets/d/113Ah55vN7ZtqjRW56fWOsnIaTUko57qPvHiPNGZ2OQ0/"&"edit?usp=sharing"", ""P1!$E$6:$BL$6""), MATCH(AN3, IMPORTRANGE(""https://docs.google.com/spreadsheets/d/113Ah55vN7ZtqjRW56fWOsnIaTUko57qPvHiPNGZ2OQ0/edit?usp=sharing"", ""P1!$E$4:$BL$4""), 0)), ""Unknown""), IF(IMPORTRANGE(""https://docs.google"&".com/spreadsheets/d/113Ah55vN7ZtqjRW56fWOsnIaTUko57qPvHiPNGZ2OQ0/edit?usp=sharing"", ""P1!$B$11"")=2, 0, ""Unknown""))"),12.624876799999997) -> 12.624877 | AO14: =IFERROR(__xludf.DUMMYFUNCTION("IF(IMPORTRANGE(""https://docs.google.com/spreadsheets/d/113Ah55vN7ZtqjRW56fWOsnIaTUko57qPvHiPNGZ2OQ0/edit?usp=sharing"", ""P1!$B$11"")=1, IFERROR(INDEX(IMPORTRANGE(""https://docs.google.com/spreadsheets/d/113Ah55vN7ZtqjRW56fWOsnIaTUko57qPvHiPNGZ2OQ0/"&"edit?usp=sharing"", ""P1!$E$6:$BL$6""), MATCH(AO3, IMPORTRANGE(""https://docs.google.com/spreadsheets/d/113Ah55vN7ZtqjRW56fWOsnIaTUko57qPvHiPNGZ2OQ0/edit?usp=sharing"", ""P1!$E$4:$BL$4""), 0)), ""Unknown""), IF(IMPORTRANGE(""https://docs.google"&".com/spreadsheets/d/113Ah55vN7ZtqjRW56fWOsnIaTUko57qPvHiPNGZ2OQ0/edit?usp=sharing"", ""P1!$B$11"")=2, 0, ""Unknown""))"),12.55870493462523) -> 12.558705 | AP14: =IFERROR(__xludf.DUMMYFUNCTION("IF(IMPORTRANGE(""https://docs.google.com/spreadsheets/d/113Ah55vN7ZtqjRW56fWOsnIaTUko57qPvHiPNGZ2OQ0/edit?usp=sharing"", ""P1!$B$11"")=1, IFERROR(INDEX(IMPORTRANGE(""https://docs.google.com/spreadsheets/d/113Ah55vN7ZtqjRW56fWOsnIaTUko57qPvHiPNGZ2OQ0/"&"edit?usp=sharing"", ""P1!$E$6:$BL$6""), MATCH(AP3, IMPORTRANGE(""https://docs.google.com/spreadsheets/d/113Ah55vN7ZtqjRW56fWOsnIaTUko57qPvHiPNGZ2OQ0/edit?usp=sharing"", ""P1!$E$4:$BL$4""), 0)), ""Unknown""), IF(IMPORTRANGE(""https://docs.google"&".com/spreadsheets/d/113Ah55vN7ZtqjRW56fWOsnIaTUko57qPvHiPNGZ2OQ0/edit?usp=sharing"", ""P1!$B$11"")=2, 0, ""Unknown""))"),12.497116247047202) -> 12.497116 | AQ14: =IFERROR(__xludf.DUMMYFUNCTION("IF(IMPORTRANGE(""https://docs.google.com/spreadsheets/d/113Ah55vN7ZtqjRW56fWOsnIaTUko57qPvHiPNGZ2OQ0/edit?usp=sharing"", ""P1!$B$11"")=1, IFERROR(INDEX(IMPORTRANGE(""https://docs.google.com/spreadsheets/d/113Ah55vN7ZtqjRW56fWOsnIaTUko57qPvHiPNGZ2OQ0/"&"edit?usp=sharing"", ""P1!$E$6:$BL$6""), MATCH(AQ3, IMPORTRANGE(""https://docs.google.com/spreadsheets/d/113Ah55vN7ZtqjRW56fWOsnIaTUko57qPvHiPNGZ2OQ0/edit?usp=sharing"", ""P1!$E$4:$BL$4""), 0)), ""Unknown""), IF(IMPORTRANGE(""https://docs.google"&".com/spreadsheets/d/113Ah55vN7ZtqjRW56fWOsnIaTUko57qPvHiPNGZ2OQ0/edit?usp=sharing"", ""P1!$B$11"")=2, 0, ""Unknown""))"),12.43161402417621) -> 12.431614 | AR14: =IFERROR(__xludf.DUMMYFUNCTION("IF(IMPORTRANGE(""https://docs.google.com/spreadsheets/d/113Ah55vN7ZtqjRW56fWOsnIaTUko57qPvHiPNGZ2OQ0/edit?usp=sharing"", ""P1!$B$11"")=1, IFERROR(INDEX(IMPORTRANGE(""https://docs.google.com/spreadsheets/d/113Ah55vN7ZtqjRW56fWOsnIaTUko57qPvHiPNGZ2OQ0/"&"edit?usp=sharing"", ""P1!$E$6:$BL$6""), MATCH(AR3, IMPORTRANGE(""https://docs.google.com/spreadsheets/d/113Ah55vN7ZtqjRW56fWOsnIaTUko57qPvHiPNGZ2OQ0/edit?usp=sharing"", ""P1!$E$4:$BL$4""), 0)), ""Unknown""), IF(IMPORTRANGE(""https://docs.google"&".com/spreadsheets/d/113Ah55vN7ZtqjRW56fWOsnIaTUko57qPvHiPNGZ2OQ0/edit?usp=sharing"", ""P1!$B$11"")=2, 0, ""Unknown""))"),12.368551683433969) -> 12.368552 | AS14: =IFERROR(__xludf.DUMMYFUNCTION("IF(IMPORTRANGE(""https://docs.google.com/spreadsheets/d/113Ah55vN7ZtqjRW56fWOsnIaTUko57qPvHiPNGZ2OQ0/edit?usp=sharing"", ""P1!$B$11"")=1, IFERROR(INDEX(IMPORTRANGE(""https://docs.google.com/spreadsheets/d/113Ah55vN7ZtqjRW56fWOsnIaTUko57qPvHiPNGZ2OQ0/"&"edit?usp=sharing"", ""P1!$E$6:$BL$6""), MATCH(AS3, IMPORTRANGE(""https://docs.google.com/spreadsheets/d/113Ah55vN7ZtqjRW56fWOsnIaTUko57qPvHiPNGZ2OQ0/edit?usp=sharing"", ""P1!$E$4:$BL$4""), 0)), ""Unknown""), IF(IMPORTRANGE(""https://docs.google"&".com/spreadsheets/d/113Ah55vN7ZtqjRW56fWOsnIaTUko57qPvHiPNGZ2OQ0/edit?usp=sharing"", ""P1!$B$11"")=2, 0, ""Unknown""))"),12.303723317197791) -> 12.303723 | AT14: =IFERROR(__xludf.DUMMYFUNCTION("IF(IMPORTRANGE(""https://docs.google.com/spreadsheets/d/113Ah55vN7ZtqjRW56fWOsnIaTUko57qPvHiPNGZ2OQ0/edit?usp=sharing"", ""P1!$B$11"")=1, IFERROR(INDEX(IMPORTRANGE(""https://docs.google.com/spreadsheets/d/113Ah55vN7ZtqjRW56fWOsnIaTUko57qPvHiPNGZ2OQ0/"&"edit?usp=sharing"", ""P1!$E$6:$BL$6""), MATCH(AT3, IMPORTRANGE(""https://docs.google.com/spreadsheets/d/113Ah55vN7ZtqjRW56fWOsnIaTUko57qPvHiPNGZ2OQ0/edit?usp=sharing"", ""P1!$E$4:$BL$4""), 0)), ""Unknown""), IF(IMPORTRANGE(""https://docs.google"&".com/spreadsheets/d/113Ah55vN7ZtqjRW56fWOsnIaTUko57qPvHiPNGZ2OQ0/edit?usp=sharing"", ""P1!$B$11"")=2, 0, ""Unknown""))"),12.241309732709206) -> 12.24131 | AU14: =IFERROR(__xludf.DUMMYFUNCTION("IF(IMPORTRANGE(""https://docs.google.com/spreadsheets/d/113Ah55vN7ZtqjRW56fWOsnIaTUko57qPvHiPNGZ2OQ0/edit?usp=sharing"", ""P1!$B$11"")=1, IFERROR(INDEX(IMPORTRANGE(""https://docs.google.com/spreadsheets/d/113Ah55vN7ZtqjRW56fWOsnIaTUko57qPvHiPNGZ2OQ0/"&"edit?usp=sharing"", ""P1!$E$6:$BL$6""), MATCH(AU3, IMPORTRANGE(""https://docs.google.com/spreadsheets/d/113Ah55vN7ZtqjRW56fWOsnIaTUko57qPvHiPNGZ2OQ0/edit?usp=sharing"", ""P1!$E$4:$BL$4""), 0)), ""Unknown""), IF(IMPORTRANGE(""https://docs.google"&".com/spreadsheets/d/113Ah55vN7ZtqjRW56fWOsnIaTUko57qPvHiPNGZ2OQ0/edit?usp=sharing"", ""P1!$B$11"")=2, 0, ""Unknown""))"),12.177148290781817) -> 12.177148 | AV14: =IFERROR(__xludf.DUMMYFUNCTION("IF(IMPORTRANGE(""https://docs.google.com/spreadsheets/d/113Ah55vN7ZtqjRW56fWOsnIaTUko57qPvHiPNGZ2OQ0/edit?usp=sharing"", ""P1!$B$11"")=1, IFERROR(INDEX(IMPORTRANGE(""https://docs.google.com/spreadsheets/d/113Ah55vN7ZtqjRW56fWOsnIaTUko57qPvHiPNGZ2OQ0/"&"edit?usp=sharing"", ""P1!$E$6:$BL$6""), MATCH(AV3, IMPORTRANGE(""https://docs.google.com/spreadsheets/d/113Ah55vN7ZtqjRW56fWOsnIaTUko57qPvHiPNGZ2OQ0/edit?usp=sharing"", ""P1!$E$4:$BL$4""), 0)), ""Unknown""), IF(IMPORTRANGE(""https://docs.google"&".com/spreadsheets/d/113Ah55vN7ZtqjRW56fWOsnIaTUko57qPvHiPNGZ2OQ0/edit?usp=sharing"", ""P1!$B$11"")=2, 0, ""Unknown""))"),12.11332314380326) -> 12.113323 | AW14: =IFERROR(__xludf.DUMMYFUNCTION("IF(IMPORTRANGE(""https://docs.google.com/spreadsheets/d/113Ah55vN7ZtqjRW56fWOsnIaTUko57qPvHiPNGZ2OQ0/edit?usp=sharing"", ""P1!$B$11"")=1, IFERROR(INDEX(IMPORTRANGE(""https://docs.google.com/spreadsheets/d/113Ah55vN7ZtqjRW56fWOsnIaTUko57qPvHiPNGZ2OQ0/"&"edit?usp=sharing"", ""P1!$E$6:$BL$6""), MATCH(AW3, IMPORTRANGE(""https://docs.google.com/spreadsheets/d/113Ah55vN7ZtqjRW56fWOsnIaTUko57qPvHiPNGZ2OQ0/edit?usp=sharing"", ""P1!$E$4:$BL$4""), 0)), ""Unknown""), IF(IMPORTRANGE(""https://docs.google"&".com/spreadsheets/d/113Ah55vN7ZtqjRW56fWOsnIaTUko57qPvHiPNGZ2OQ0/edit?usp=sharing"", ""P1!$B$11"")=2, 0, ""Unknown""))"),12.051875409813947) -> 12.051875 | AX14: =IFERROR(__xludf.DUMMYFUNCTION("IF(IMPORTRANGE(""https://docs.google.com/spreadsheets/d/113Ah55vN7ZtqjRW56fWOsnIaTUko57qPvHiPNGZ2OQ0/edit?usp=sharing"", ""P1!$B$11"")=1, IFERROR(INDEX(IMPORTRANGE(""https://docs.google.com/spreadsheets/d/113Ah55vN7ZtqjRW56fWOsnIaTUko57qPvHiPNGZ2OQ0/"&"edit?usp=sharing"", ""P1!$E$6:$BL$6""), MATCH(AX3, IMPORTRANGE(""https://docs.google.com/spreadsheets/d/113Ah55vN7ZtqjRW56fWOsnIaTUko57qPvHiPNGZ2OQ0/edit?usp=sharing"", ""P1!$E$4:$BL$4""), 0)), ""Unknown""), IF(IMPORTRANGE(""https://docs.google"&".com/spreadsheets/d/113Ah55vN7ZtqjRW56fWOsnIaTUko57qPvHiPNGZ2OQ0/edit?usp=sharing"", ""P1!$B$11"")=2, 0, ""Unknown""))"),11.988706866487515) -> 11.988707 | AY14: =IFERROR(__xludf.DUMMYFUNCTION("IF(IMPORTRANGE(""https://docs.google.com/spreadsheets/d/113Ah55vN7ZtqjRW56fWOsnIaTUko57qPvHiPNGZ2OQ0/edit?usp=sharing"", ""P1!$B$11"")=1, IFERROR(INDEX(IMPORTRANGE(""https://docs.google.com/spreadsheets/d/113Ah55vN7ZtqjRW56fWOsnIaTUko57qPvHiPNGZ2OQ0/"&"edit?usp=sharing"", ""P1!$E$6:$BL$6""), MATCH(AY3, IMPORTRANGE(""https://docs.google.com/spreadsheets/d/113Ah55vN7ZtqjRW56fWOsnIaTUko57qPvHiPNGZ2OQ0/edit?usp=sharing"", ""P1!$E$4:$BL$4""), 0)), ""Unknown""), IF(IMPORTRANGE(""https://docs.google"&".com/spreadsheets/d/113Ah55vN7ZtqjRW56fWOsnIaTUko57qPvHiPNGZ2OQ0/edit?usp=sharing"", ""P1!$B$11"")=2, 0, ""Unknown""))"),11.927891278422843) -> 11.927891 | AZ14: =IFERROR(__xludf.DUMMYFUNCTION("IF(IMPORTRANGE(""https://docs.google.com/spreadsheets/d/113Ah55vN7ZtqjRW56fWOsnIaTUko57qPvHiPNGZ2OQ0/edit?usp=sharing"", ""P1!$B$11"")=1, IFERROR(INDEX(IMPORTRANGE(""https://docs.google.com/spreadsheets/d/113Ah55vN7ZtqjRW56fWOsnIaTUko57qPvHiPNGZ2OQ0/"&"edit?usp=sharing"", ""P1!$E$6:$BL$6""), MATCH(AZ3, IMPORTRANGE(""https://docs.google.com/spreadsheets/d/113Ah55vN7ZtqjRW56fWOsnIaTUko57qPvHiPNGZ2OQ0/edit?usp=sharing"", ""P1!$E$4:$BL$4""), 0)), ""Unknown""), IF(IMPORTRANGE(""https://docs.google"&".com/spreadsheets/d/113Ah55vN7ZtqjRW56fWOsnIaTUko57qPvHiPNGZ2OQ0/edit?usp=sharing"", ""P1!$B$11"")=2, 0, ""Unknown""))"),11.865372583913235) -> 11.865373 | BA14: =IFERROR(__xludf.DUMMYFUNCTION("IF(IMPORTRANGE(""https://docs.google.com/spreadsheets/d/113Ah55vN7ZtqjRW56fWOsnIaTUko57qPvHiPNGZ2OQ0/edit?usp=sharing"", ""P1!$B$11"")=1, IFERROR(INDEX(IMPORTRANGE(""https://docs.google.com/spreadsheets/d/113Ah55vN7ZtqjRW56fWOsnIaTUko57qPvHiPNGZ2OQ0/"&"edit?usp=sharing"", ""P1!$E$6:$BL$6""), MATCH(BA3, IMPORTRANGE(""https://docs.google.com/spreadsheets/d/113Ah55vN7ZtqjRW56fWOsnIaTUko57qPvHiPNGZ2OQ0/edit?usp=sharing"", ""P1!$E$4:$BL$4""), 0)), ""Unknown""), IF(IMPORTRANGE(""https://docs.google"&".com/spreadsheets/d/113Ah55vN7ZtqjRW56fWOsnIaTUko57qPvHiPNGZ2OQ0/edit?usp=sharing"", ""P1!$B$11"")=2, 0, ""Unknown""))"),11.803181574077469) -> 11.803182 | BB14: =IFERROR(__xludf.DUMMYFUNCTION("IF(IMPORTRANGE(""https://docs.google.com/spreadsheets/d/113Ah55vN7ZtqjRW56fWOsnIaTUko57qPvHiPNGZ2OQ0/edit?usp=sharing"", ""P1!$B$11"")=1, IFERROR(INDEX(IMPORTRANGE(""https://docs.google.com/spreadsheets/d/113Ah55vN7ZtqjRW56fWOsnIaTUko57qPvHiPNGZ2OQ0/"&"edit?usp=sharing"", ""P1!$E$6:$BL$6""), MATCH(BB3, IMPORTRANGE(""https://docs.google.com/spreadsheets/d/113Ah55vN7ZtqjRW56fWOsnIaTUko57qPvHiPNGZ2OQ0/edit?usp=sharing"", ""P1!$E$4:$BL$4""), 0)), ""Unknown""), IF(IMPORTRANGE(""https://docs.google"&".com/spreadsheets/d/113Ah55vN7ZtqjRW56fWOsnIaTUko57qPvHiPNGZ2OQ0/edit?usp=sharing"", ""P1!$B$11"")=2, 0, ""Unknown""))"),11.74728927222437) -> 11.747289 | BC14: =IFERROR(__xludf.DUMMYFUNCTION("IF(IMPORTRANGE(""https://docs.google.com/spreadsheets/d/113Ah55vN7ZtqjRW56fWOsnIaTUko57qPvHiPNGZ2OQ0/edit?usp=sharing"", ""P1!$B$11"")=1, IFERROR(INDEX(IMPORTRANGE(""https://docs.google.com/spreadsheets/d/113Ah55vN7ZtqjRW56fWOsnIaTUko57qPvHiPNGZ2OQ0/"&"edit?usp=sharing"", ""P1!$E$6:$BL$6""), MATCH(BC3, IMPORTRANGE(""https://docs.google.com/spreadsheets/d/113Ah55vN7ZtqjRW56fWOsnIaTUko57qPvHiPNGZ2OQ0/edit?usp=sharing"", ""P1!$E$4:$BL$4""), 0)), ""Unknown""), IF(IMPORTRANGE(""https://docs.google"&".com/spreadsheets/d/113Ah55vN7ZtqjRW56fWOsnIaTUko57qPvHiPNGZ2OQ0/edit?usp=sharing"", ""P1!$B$11"")=2, 0, ""Unknown""))"),11.685717182725638) -> 11.685717 | BD14: =IFERROR(__xludf.DUMMYFUNCTION("IF(IMPORTRANGE(""https://docs.google.com/spreadsheets/d/113Ah55vN7ZtqjRW56fWOsnIaTUko57qPvHiPNGZ2OQ0/edit?usp=sharing"", ""P1!$B$11"")=1, IFERROR(INDEX(IMPORTRANGE(""https://docs.google.com/spreadsheets/d/113Ah55vN7ZtqjRW56fWOsnIaTUko57qPvHiPNGZ2OQ0/"&"edit?usp=sharing"", ""P1!$E$6:$BL$6""), MATCH(BD3, IMPORTRANGE(""https://docs.google.com/spreadsheets/d/113Ah55vN7ZtqjRW56fWOsnIaTUko57qPvHiPNGZ2OQ0/edit?usp=sharing"", ""P1!$E$4:$BL$4""), 0)), ""Unknown""), IF(IMPORTRANGE(""https://docs.google"&".com/spreadsheets/d/113Ah55vN7ZtqjRW56fWOsnIaTUko57qPvHiPNGZ2OQ0/edit?usp=sharing"", ""P1!$B$11"")=2, 0, ""Unknown""))"),11.626438582427932) -> 11.626439 | BE14: =IFERROR(__xludf.DUMMYFUNCTION("IF(IMPORTRANGE(""https://docs.google.com/spreadsheets/d/113Ah55vN7ZtqjRW56fWOsnIaTUko57qPvHiPNGZ2OQ0/edit?usp=sharing"", ""P1!$B$11"")=1, IFERROR(INDEX(IMPORTRANGE(""https://docs.google.com/spreadsheets/d/113Ah55vN7ZtqjRW56fWOsnIaTUko57qPvHiPNGZ2OQ0/"&"edit?usp=sharing"", ""P1!$E$6:$BL$6""), MATCH(BE3, IMPORTRANGE(""https://docs.google.com/spreadsheets/d/113Ah55vN7ZtqjRW56fWOsnIaTUko57qPvHiPNGZ2OQ0/edit?usp=sharing"", ""P1!$E$4:$BL$4""), 0)), ""Unknown""), IF(IMPORTRANGE(""https://docs.google"&".com/spreadsheets/d/113Ah55vN7ZtqjRW56fWOsnIaTUko57qPvHiPNGZ2OQ0/edit?usp=sharing"", ""P1!$B$11"")=2, 0, ""Unknown""))"),11.565499918165923) -> 11.5655 | BF14: =IFERROR(__xludf.DUMMYFUNCTION("IF(IMPORTRANGE(""https://docs.google.com/spreadsheets/d/113Ah55vN7ZtqjRW56fWOsnIaTUko57qPvHiPNGZ2OQ0/edit?usp=sharing"", ""P1!$B$11"")=1, IFERROR(INDEX(IMPORTRANGE(""https://docs.google.com/spreadsheets/d/113Ah55vN7ZtqjRW56fWOsnIaTUko57qPvHiPNGZ2OQ0/"&"edit?usp=sharing"", ""P1!$E$6:$BL$6""), MATCH(BF3, IMPORTRANGE(""https://docs.google.com/spreadsheets/d/113Ah55vN7ZtqjRW56fWOsnIaTUko57qPvHiPNGZ2OQ0/edit?usp=sharing"", ""P1!$E$4:$BL$4""), 0)), ""Unknown""), IF(IMPORTRANGE(""https://docs.google"&".com/spreadsheets/d/113Ah55vN7ZtqjRW56fWOsnIaTUko57qPvHiPNGZ2OQ0/edit?usp=sharing"", ""P1!$B$11"")=2, 0, ""Unknown""))"),11.506831148746654) -> 11.506831 | BG14: =IFERROR(__xludf.DUMMYFUNCTION("IF(IMPORTRANGE(""https://docs.google.com/spreadsheets/d/113Ah55vN7ZtqjRW56fWOsnIaTUko57qPvHiPNGZ2OQ0/edit?usp=sharing"", ""P1!$B$11"")=1, IFERROR(INDEX(IMPORTRANGE(""https://docs.google.com/spreadsheets/d/113Ah55vN7ZtqjRW56fWOsnIaTUko57qPvHiPNGZ2OQ0/"&"edit?usp=sharing"", ""P1!$E$6:$BL$6""), MATCH(BG3, IMPORTRANGE(""https://docs.google.com/spreadsheets/d/113Ah55vN7ZtqjRW56fWOsnIaTUko57qPvHiPNGZ2OQ0/edit?usp=sharing"", ""P1!$E$4:$BL$4""), 0)), ""Unknown""), IF(IMPORTRANGE(""https://docs.google"&".com/spreadsheets/d/113Ah55vN7ZtqjRW56fWOsnIaTUko57qPvHiPNGZ2OQ0/edit?usp=sharing"", ""P1!$B$11"")=2, 0, ""Unknown""))"),11.446519393334906) -> 11.446519 | BH14: =IFERROR(__xludf.DUMMYFUNCTION("IF(IMPORTRANGE(""https://docs.google.com/spreadsheets/d/113Ah55vN7ZtqjRW56fWOsnIaTUko57qPvHiPNGZ2OQ0/edit?usp=sharing"", ""P1!$B$11"")=1, IFERROR(INDEX(IMPORTRANGE(""https://docs.google.com/spreadsheets/d/113Ah55vN7ZtqjRW56fWOsnIaTUko57qPvHiPNGZ2OQ0/"&"edit?usp=sharing"", ""P1!$E$6:$BL$6""), MATCH(BH3, IMPORTRANGE(""https://docs.google.com/spreadsheets/d/113Ah55vN7ZtqjRW56fWOsnIaTUko57qPvHiPNGZ2OQ0/edit?usp=sharing"", ""P1!$E$4:$BL$4""), 0)), ""Unknown""), IF(IMPORTRANGE(""https://docs.google"&".com/spreadsheets/d/113Ah55vN7ZtqjRW56fWOsnIaTUko57qPvHiPNGZ2OQ0/edit?usp=sharing"", ""P1!$B$11"")=2, 0, ""Unknown""))"),11.386523755175062) -> 11.386524 | BI14: =IFERROR(__xludf.DUMMYFUNCTION("IF(IMPORTRANGE(""https://docs.google.com/spreadsheets/d/113Ah55vN7ZtqjRW56fWOsnIaTUko57qPvHiPNGZ2OQ0/edit?usp=sharing"", ""P1!$B$11"")=1, IFERROR(INDEX(IMPORTRANGE(""https://docs.google.com/spreadsheets/d/113Ah55vN7ZtqjRW56fWOsnIaTUko57qPvHiPNGZ2OQ0/"&"edit?usp=sharing"", ""P1!$E$6:$BL$6""), MATCH(BI3, IMPORTRANGE(""https://docs.google.com/spreadsheets/d/113Ah55vN7ZtqjRW56fWOsnIaTUko57qPvHiPNGZ2OQ0/edit?usp=sharing"", ""P1!$E$4:$BL$4""), 0)), ""Unknown""), IF(IMPORTRANGE(""https://docs.google"&".com/spreadsheets/d/113Ah55vN7ZtqjRW56fWOsnIaTUko57qPvHiPNGZ2OQ0/edit?usp=sharing"", ""P1!$B$11"")=2, 0, ""Unknown""))"),11.328762885225109) -> 11.328763 | BJ14: =IFERROR(__xludf.DUMMYFUNCTION("IF(IMPORTRANGE(""https://docs.google.com/spreadsheets/d/113Ah55vN7ZtqjRW56fWOsnIaTUko57qPvHiPNGZ2OQ0/edit?usp=sharing"", ""P1!$B$11"")=1, IFERROR(INDEX(IMPORTRANGE(""https://docs.google.com/spreadsheets/d/113Ah55vN7ZtqjRW56fWOsnIaTUko57qPvHiPNGZ2OQ0/"&"edit?usp=sharing"", ""P1!$E$6:$BL$6""), MATCH(BJ3, IMPORTRANGE(""https://docs.google.com/spreadsheets/d/113Ah55vN7ZtqjRW56fWOsnIaTUko57qPvHiPNGZ2OQ0/edit?usp=sharing"", ""P1!$E$4:$BL$4""), 0)), ""Unknown""), IF(IMPORTRANGE(""https://docs.google"&".com/spreadsheets/d/113Ah55vN7ZtqjRW56fWOsnIaTUko57qPvHiPNGZ2OQ0/edit?usp=sharing"", ""P1!$B$11"")=2, 0, ""Unknown""))"),11.269384454498264) -> 11.269384 | BK14: =IFERROR(__xludf.DUMMYFUNCTION("IF(IMPORTRANGE(""https://docs.google.com/spreadsheets/d/113Ah55vN7ZtqjRW56fWOsnIaTUko57qPvHiPNGZ2OQ0/edit?usp=sharing"", ""P1!$B$11"")=1, IFERROR(INDEX(IMPORTRANGE(""https://docs.google.com/spreadsheets/d/113Ah55vN7ZtqjRW56fWOsnIaTUko57qPvHiPNGZ2OQ0/"&"edit?usp=sharing"", ""P1!$E$6:$BL$6""), MATCH(BK3, IMPORTRANGE(""https://docs.google.com/spreadsheets/d/113Ah55vN7ZtqjRW56fWOsnIaTUko57qPvHiPNGZ2OQ0/edit?usp=sharing"", ""P1!$E$4:$BL$4""), 0)), ""Unknown""), IF(IMPORTRANGE(""https://docs.google"&".com/spreadsheets/d/113Ah55vN7ZtqjRW56fWOsnIaTUko57qPvHiPNGZ2OQ0/edit?usp=sharing"", ""P1!$B$11"")=2, 0, ""Unknown""))"),11.212217801717474) -> 11.212218 | BL14: =AVERAGE(D14:BK14) -> 13.108317
C15: Ocupación % (Mercado) | D15: =IFERROR(__xludf.DUMMYFUNCTION("IMPORTRANGE(""113Ah55vN7ZtqjRW56fWOsnIaTUko57qPvHiPNGZ2OQ0"",""P1!E14:BL14"")"),0.5980322580645161) -> 0.59803226 | E15: =IFERROR(__xludf.DUMMYFUNCTION("""COMPUTED_VALUE"""),0.6460000000000001) -> 0.646 | F15: =IFERROR(__xludf.DUMMYFUNCTION("""COMPUTED_VALUE"""),0.7239354838709676) -> 0.72393548 | G15: =IFERROR(__xludf.DUMMYFUNCTION("""COMPUTED_VALUE"""),0.6091166666666668) -> 0.60911667 | H15: =IFERROR(__xludf.DUMMYFUNCTION("""COMPUTED_VALUE"""),0.5887580645161289) -> 0.58875806 | I15: =IFERROR(__xludf.DUMMYFUNCTION("""COMPUTED_VALUE"""),0.6110333333333332) -> 0.61103333 | J15: =IFERROR(__xludf.DUMMYFUNCTION("""COMPUTED_VALUE"""),0.6885967741935484) -> 0.68859677 | K15: =IFERROR(__xludf.DUMMYFUNCTION("""COMPUTED_VALUE"""),0.6928709677419355) -> 0.69287097 | L15: =IFERROR(__xludf.DUMMYFUNCTION("""COMPUTED_VALUE"""),0.5429833333333334) -> 0.54298333 | M15: =IFERROR(__xludf.DUMMYFUNCTION("""COMPUTED_VALUE"""),0.5027419354838709) -> 0.50274194 | N15: =IFERROR(__xludf.DUMMYFUNCTION("""COMPUTED_VALUE"""),0.6626333333333334) -> 0.66263333 | O15: =IFERROR(__xludf.DUMMYFUNCTION("""COMPUTED_VALUE"""),0.5708548387096776) -> 0.57085484 | P15: =IFERROR(__xludf.DUMMYFUNCTION("""COMPUTED_VALUE"""),0.5980322580645161) -> 0.59803226 | Q15: =IFERROR(__xludf.DUMMYFUNCTION("""COMPUTED_VALUE"""),0.6460000000000001) -> 0.646 | R15: =IFERROR(__xludf.DUMMYFUNCTION("""COMPUTED_VALUE"""),0.7239354838709676) -> 0.72393548 | S15: =IFERROR(__xludf.DUMMYFUNCTION("""COMPUTED_VALUE"""),0.6091166666666668) -> 0.60911667 | T15: =IFERROR(__xludf.DUMMYFUNCTION("""COMPUTED_VALUE"""),0.5887580645161289) -> 0.58875806 | U15: =IFERROR(__xludf.DUMMYFUNCTION("""COMPUTED_VALUE"""),0.6110333333333332) -> 0.61103333 | V15: =IFERROR(__xludf.DUMMYFUNCTION("""COMPUTED_VALUE"""),0.6885967741935484) -> 0.68859677 | W15: =IFERROR(__xludf.DUMMYFUNCTION("""COMPUTED_VALUE"""),0.6928709677419355) -> 0.69287097 | X15: =IFERROR(__xludf.DUMMYFUNCTION("""COMPUTED_VALUE"""),0.5429833333333334) -> 0.54298333 | Y15: =IFERROR(__xludf.DUMMYFUNCTION("""COMPUTED_VALUE"""),0.5027419354838709) -> 0.50274194 | Z15: =IFERROR(__xludf.DUMMYFUNCTION("""COMPUTED_VALUE"""),0.6626333333333334) -> 0.66263333 | AA15: =IFERROR(__xludf.DUMMYFUNCTION("""COMPUTED_VALUE"""),0.5708548387096776) -> 0.57085484 | AB15: =IFERROR(__xludf.DUMMYFUNCTION("""COMPUTED_VALUE"""),0.5980322580645161) -> 0.59803226 | AC15: =IFERROR(__xludf.DUMMYFUNCTION("""COMPUTED_VALUE"""),0.6460000000000001) -> 0.646 | AD15: =IFERROR(__xludf.DUMMYFUNCTION("""COMPUTED_VALUE"""),0.7239354838709676) -> 0.72393548 | AE15: =IFERROR(__xludf.DUMMYFUNCTION("""COMPUTED_VALUE"""),0.6091166666666668) -> 0.60911667 | AF15: =IFERROR(__xludf.DUMMYFUNCTION("""COMPUTED_VALUE"""),0.5887580645161289) -> 0.58875806 | AG15: =IFERROR(__xludf.DUMMYFUNCTION("""COMPUTED_VALUE"""),0.6110333333333332) -> 0.61103333 | AH15: =IFERROR(__xludf.DUMMYFUNCTION("""COMPUTED_VALUE"""),0.6885967741935484) -> 0.68859677 | AI15: =IFERROR(__xludf.DUMMYFUNCTION("""COMPUTED_VALUE"""),0.6928709677419355) -> 0.69287097 | AJ15: =IFERROR(__xludf.DUMMYFUNCTION("""COMPUTED_VALUE"""),0.5429833333333334) -> 0.54298333 | AK15: =IFERROR(__xludf.DUMMYFUNCTION("""COMPUTED_VALUE"""),0.5027419354838709) -> 0.50274194 | AL15: =IFERROR(__xludf.DUMMYFUNCTION("""COMPUTED_VALUE"""),0.6626333333333334) -> 0.66263333 | AM15: =IFERROR(__xludf.DUMMYFUNCTION("""COMPUTED_VALUE"""),0.5708548387096776) -> 0.57085484 | AN15: =IFERROR(__xludf.DUMMYFUNCTION("""COMPUTED_VALUE"""),0.5980322580645161) -> 0.59803226 | AO15: =IFERROR(__xludf.DUMMYFUNCTION("""COMPUTED_VALUE"""),0.6460000000000001) -> 0.646 | AP15: =IFERROR(__xludf.DUMMYFUNCTION("""COMPUTED_VALUE"""),0.7239354838709676) -> 0.72393548 | AQ15: =IFERROR(__xludf.DUMMYFUNCTION("""COMPUTED_VALUE"""),0.6091166666666668) -> 0.60911667 | AR15: =IFERROR(__xludf.DUMMYFUNCTION("""COMPUTED_VALUE"""),0.5887580645161289) -> 0.58875806 | AS15: =IFERROR(__xludf.DUMMYFUNCTION("""COMPUTED_VALUE"""),0.6110333333333332) -> 0.61103333 | AT15: =IFERROR(__xludf.DUMMYFUNCTION("""COMPUTED_VALUE"""),0.6885967741935484) -> 0.68859677 | AU15: =IFERROR(__xludf.DUMMYFUNCTION("""COMPUTED_VALUE"""),0.6928709677419355) -> 0.69287097 | AV15: =IFERROR(__xludf.DUMMYFUNCTION("""COMPUTED_VALUE"""),0.5429833333333334) -> 0.54298333 | AW15: =IFERROR(__xludf.DUMMYFUNCTION("""COMPUTED_VALUE"""),0.5027419354838709) -> 0.50274194 | AX15: =IFERROR(__xludf.DUMMYFUNCTION("""COMPUTED_VALUE"""),0.6626333333333334) -> 0.66263333 | AY15: =IFERROR(__xludf.DUMMYFUNCTION("""COMPUTED_VALUE"""),0.5708548387096776) -> 0.57085484 | AZ15: =IFERROR(__xludf.DUMMYFUNCTION("""COMPUTED_VALUE"""),0.5980322580645161) -> 0.59803226 | BA15: =IFERROR(__xludf.DUMMYFUNCTION("""COMPUTED_VALUE"""),0.6460000000000001) -> 0.646 | BB15: =IFERROR(__xludf.DUMMYFUNCTION("""COMPUTED_VALUE"""),0.7239354838709676) -> 0.72393548 | BC15: =IFERROR(__xludf.DUMMYFUNCTION("""COMPUTED_VALUE"""),0.6091166666666668) -> 0.60911667 | BD15: =IFERROR(__xludf.DUMMYFUNCTION("""COMPUTED_VALUE"""),0.5887580645161289) -> 0.58875806 | BE15: =IFERROR(__xludf.DUMMYFUNCTION("""COMPUTED_VALUE"""),0.6110333333333332) -> 0.61103333 | BF15: =IFERROR(__xludf.DUMMYFUNCTION("""COMPUTED_VALUE"""),0.6885967741935484) -> 0.68859677 | BG15: =IFERROR(__xludf.DUMMYFUNCTION("""COMPUTED_VALUE"""),0.6928709677419355) -> 0.69287097 | BH15: =IFERROR(__xludf.DUMMYFUNCTION("""COMPUTED_VALUE"""),0.5429833333333334) -> 0.54298333 | BI15: =IFERROR(__xludf.DUMMYFUNCTION("""COMPUTED_VALUE"""),0.5027419354838709) -> 0.50274194 | BJ15: =IFERROR(__xludf.DUMMYFUNCTION("""COMPUTED_VALUE"""),0.6626333333333334) -> 0.66263333 | BK15: =IFERROR(__xludf.DUMMYFUNCTION("""COMPUTED_VALUE"""),0.5708548387096776) -> 0.57085484 | BL15: =AVERAGE(D15:BK15) -> 0.61979642
C16: ADR Implícito | D16: =IFERROR(__xludf.DUMMYFUNCTION("IMPORTRANGE(""113Ah55vN7ZtqjRW56fWOsnIaTUko57qPvHiPNGZ2OQ0"",""P1!E15:BL15"")"),1475.0813306014436) -> 1475.0813 | E16: =IFERROR(__xludf.DUMMYFUNCTION("""COMPUTED_VALUE"""),1515.835699392831) -> 1515.8357 | F16: =IFERROR(__xludf.DUMMYFUNCTION("""COMPUTED_VALUE"""),1490.885538247655) -> 1490.8855 | G16: =IFERROR(__xludf.DUMMYFUNCTION("""COMPUTED_VALUE"""),1485.77453554034) -> 1485.7745 | H16: =IFERROR(__xludf.DUMMYFUNCTION("""COMPUTED_VALUE"""),1527.001079424367) -> 1527.0011 | I16: =IFERROR(__xludf.DUMMYFUNCTION("""COMPUTED_VALUE"""),1518.7389908715422) -> 1518.739 | J16: =IFERROR(__xludf.DUMMYFUNCTION("""COMPUTED_VALUE"""),1492.597660742661) -> 1492.5977 | K16: =IFERROR(__xludf.DUMMYFUNCTION("""COMPUTED_VALUE"""),1540.1419854116796) -> 1540.142 | L16: =IFERROR(__xludf.DUMMYFUNCTION("""COMPUTED_VALUE"""),1471.7117174403318) -> 1471.7117 | M16: =IFERROR(__xludf.DUMMYFUNCTION("""COMPUTED_VALUE"""),1468.5547781845821) -> 1468.5548 | N16: =IFERROR(__xludf.DUMMYFUNCTION("""COMPUTED_VALUE"""),1592.6746350650806) -> 1592.6746 | O16: =IFERROR(__xludf.DUMMYFUNCTION("""COMPUTED_VALUE"""),1571.406512852541) -> 1571.4065 | P16: =IFERROR(__xludf.DUMMYFUNCTION("""COMPUTED_VALUE"""),1534.0845838255013) -> 1534.0846 | Q16: =IFERROR(__xludf.DUMMYFUNCTION("""COMPUTED_VALUE"""),1576.469127368544) -> 1576.4691 | R16: =IFERROR(__xludf.DUMMYFUNCTION("""COMPUTED_VALUE"""),1550.5209597775613) -> 1550.521 | S16: =IFERROR(__xludf.DUMMYFUNCTION("""COMPUTED_VALUE"""),1545.2055169619537) -> 1545.2055 | T16: =IFERROR(__xludf.DUMMYFUNCTION("""COMPUTED_VALUE"""),1588.0811226013413) -> 1588.0811 | U16: =IFERROR(__xludf.DUMMYFUNCTION("""COMPUTED_VALUE"""),1579.4885505064042) -> 1579.4886 | V16: =IFERROR(__xludf.DUMMYFUNCTION("""COMPUTED_VALUE"""),1552.3015671723674) -> 1552.3016 | W16: =IFERROR(__xludf.DUMMYFUNCTION("""COMPUTED_VALUE"""),1601.7476648281468) -> 1601.7477 | X16: =IFERROR(__xludf.DUMMYFUNCTION("""COMPUTED_VALUE"""),1530.580186137945) -> 1530.5802 | Y16: =IFERROR(__xludf.DUMMYFUNCTION("""COMPUTED_VALUE"""),1527.2969693119658) -> 1527.297 | Z16: =IFERROR(__xludf.DUMMYFUNCTION("""COMPUTED_VALUE"""),1656.381620467684) -> 1656.3816 | AA16: =IFERROR(__xludf.DUMMYFUNCTION("""COMPUTED_VALUE"""),1634.2627733666432) -> 1634.2628 | AB16: =IFERROR(__xludf.DUMMYFUNCTION("""COMPUTED_VALUE"""),1595.4479671785216) -> 1595.448 | AC16: =IFERROR(__xludf.DUMMYFUNCTION("""COMPUTED_VALUE"""),1639.5278924632858) -> 1639.5279 | AD16: =IFERROR(__xludf.DUMMYFUNCTION("""COMPUTED_VALUE"""),1612.541798168664) -> 1612.5418 | AE16: =IFERROR(__xludf.DUMMYFUNCTION("""COMPUTED_VALUE"""),1607.0137376404316) -> 1607.0137 | AF16: =IFERROR(__xludf.DUMMYFUNCTION("""COMPUTED_VALUE"""),1651.6043675053957) -> 1651.6044 | AG16: =IFERROR(__xludf.DUMMYFUNCTION("""COMPUTED_VALUE"""),1642.6680925266603) -> 1642.6681 | AH16: =IFERROR(__xludf.DUMMYFUNCTION("""COMPUTED_VALUE"""),1614.3936298592625) -> 1614.3936 | AI16: =IFERROR(__xludf.DUMMYFUNCTION("""COMPUTED_VALUE"""),1665.8175714212728) -> 1665.8176 | AJ16: =IFERROR(__xludf.DUMMYFUNCTION("""COMPUTED_VALUE"""),1591.803393583463) -> 1591.8034 | AK16: =IFERROR(__xludf.DUMMYFUNCTION("""COMPUTED_VALUE"""),1588.3888480844444) -> 1588.3888 | AL16: =IFERROR(__xludf.DUMMYFUNCTION("""COMPUTED_VALUE"""),1722.6368852863914) -> 1722.6369 | AM16: =IFERROR(__xludf.DUMMYFUNCTION("""COMPUTED_VALUE"""),1699.6332843013088) -> 1699.6333 | AN16: =IFERROR(__xludf.DUMMYFUNCTION("""COMPUTED_VALUE"""),1659.2658858656625) -> 1659.2659 | AO16: =IFERROR(__xludf.DUMMYFUNCTION("""COMPUTED_VALUE"""),1705.1090081618172) -> 1705.109 | AP16: =IFERROR(__xludf.DUMMYFUNCTION("""COMPUTED_VALUE"""),1677.04347009541) -> 1677.0435 | AQ16: =IFERROR(__xludf.DUMMYFUNCTION("""COMPUTED_VALUE"""),1671.294287146049) -> 1671.2943 | AR16: =IFERROR(__xludf.DUMMYFUNCTION("""COMPUTED_VALUE"""),1717.668542205611) -> 1717.6685 | AS16: =IFERROR(__xludf.DUMMYFUNCTION("""COMPUTED_VALUE"""),1708.3748162277268) -> 1708.3748 | AT16: =IFERROR(__xludf.DUMMYFUNCTION("""COMPUTED_VALUE"""),1678.969375053633) -> 1678.9694 | AU16: =IFERROR(__xludf.DUMMYFUNCTION("""COMPUTED_VALUE"""),1732.4502742781237) -> 1732.4503 | AV16: =IFERROR(__xludf.DUMMYFUNCTION("""COMPUTED_VALUE"""),1655.4755293268015) -> 1655.4755 | AW16: =IFERROR(__xludf.DUMMYFUNCTION("""COMPUTED_VALUE"""),1651.9244020078224) -> 1651.9244 | AX16: =IFERROR(__xludf.DUMMYFUNCTION("""COMPUTED_VALUE"""),1791.5423606978468) -> 1791.5424 | AY16: =IFERROR(__xludf.DUMMYFUNCTION("""COMPUTED_VALUE"""),1767.6186156733609) -> 1767.6186 | AZ16: =IFERROR(__xludf.DUMMYFUNCTION("""COMPUTED_VALUE"""),1725.6365213002894) -> 1725.6365 | BA16: =IFERROR(__xludf.DUMMYFUNCTION("""COMPUTED_VALUE"""),1773.31336848829) -> 1773.3134 | BB16: =IFERROR(__xludf.DUMMYFUNCTION("""COMPUTED_VALUE"""),1744.1252088992264) -> 1744.1252 | BC16: =IFERROR(__xludf.DUMMYFUNCTION("""COMPUTED_VALUE"""),1738.1460586318913) -> 1738.1461 | BD16: =IFERROR(__xludf.DUMMYFUNCTION("""COMPUTED_VALUE"""),1786.3752838938358) -> 1786.3753 | BE16: =IFERROR(__xludf.DUMMYFUNCTION("""COMPUTED_VALUE"""),1776.7098088768362) -> 1776.7098 | BF16: =IFERROR(__xludf.DUMMYFUNCTION("""COMPUTED_VALUE"""),1746.1281500557784) -> 1746.1282 | BG16: =IFERROR(__xludf.DUMMYFUNCTION("""COMPUTED_VALUE"""),1801.7482852492485) -> 1801.7483 | BH16: =IFERROR(__xludf.DUMMYFUNCTION("""COMPUTED_VALUE"""),1721.6945504998737) -> 1721.6945 | BI16: =IFERROR(__xludf.DUMMYFUNCTION("""COMPUTED_VALUE"""),1718.0013780881352) -> 1718.0014 | BJ16: =IFERROR(__xludf.DUMMYFUNCTION("""COMPUTED_VALUE"""),1863.204055125761) -> 1863.2041 | BK16: =IFERROR(__xludf.DUMMYFUNCTION("""COMPUTED_VALUE"""),1838.323360300296) -> 1838.3234 | BL16: =AVERAGE(D16:BK16) -> 1638.4741
C17: RevPAR | D17: =IFERROR(__xludf.DUMMYFUNCTION("IMPORTRANGE(""113Ah55vN7ZtqjRW56fWOsnIaTUko57qPvHiPNGZ2OQ0"",""P1!E13:BL13"")"),882.1462189683923) -> 882.14622 | E17: =IFERROR(__xludf.DUMMYFUNCTION("""COMPUTED_VALUE"""),979.229861807769) -> 979.22986 | F17: =IFERROR(__xludf.DUMMYFUNCTION("""COMPUTED_VALUE"""),1079.304943527544) -> 1079.3049 | G17: =IFERROR(__xludf.DUMMYFUNCTION("""COMPUTED_VALUE"""),905.0100325065468) -> 905.01003 | H17: =IFERROR(__xludf.DUMMYFUNCTION("""COMPUTED_VALUE"""),899.0342000359299) -> 899.0342 | I17: =IFERROR(__xludf.DUMMYFUNCTION("""COMPUTED_VALUE"""),928.0001480555412) -> 928.00015 | J17: =IFERROR(__xludf.DUMMYFUNCTION("""COMPUTED_VALUE"""),1027.7979343562326) -> 1027.7979 | K17: =IFERROR(__xludf.DUMMYFUNCTION("""COMPUTED_VALUE"""),1067.1196678921763) -> 1067.1197 | L17: =IFERROR(__xludf.DUMMYFUNCTION("""COMPUTED_VALUE"""),799.1149340414762) -> 799.11493 | M17: =IFERROR(__xludf.DUMMYFUNCTION("""COMPUTED_VALUE"""),738.3040715486036) -> 738.30407 | N17: =IFERROR(__xludf.DUMMYFUNCTION("""COMPUTED_VALUE"""),1055.3593023486246) -> 1055.3593 | O17: =IFERROR(__xludf.DUMMYFUNCTION("""COMPUTED_VALUE"""),897.0450114417741) -> 897.04501 | P17: =IFERROR(__xludf.DUMMYFUNCTION("""COMPUTED_VALUE"""),917.432067727128) -> 917.43207 | Q17: =IFERROR(__xludf.DUMMYFUNCTION("""COMPUTED_VALUE"""),1018.3990562800795) -> 1018.3991 | R17: =IFERROR(__xludf.DUMMYFUNCTION("""COMPUTED_VALUE"""),1122.477141268646) -> 1122.4771 | S17: =IFERROR(__xludf.DUMMYFUNCTION("""COMPUTED_VALUE"""),941.2104338068089) -> 941.21043 | T17: =IFERROR(__xludf.DUMMYFUNCTION("""COMPUTED_VALUE"""),934.995568037367) -> 934.99557 | U17: =IFERROR(__xludf.DUMMYFUNCTION("""COMPUTED_VALUE"""),965.1201539777629) -> 965.12015 | V17: =IFERROR(__xludf.DUMMYFUNCTION("""COMPUTED_VALUE"""),1068.909851730482) -> 1068.9099 | W17: =IFERROR(__xludf.DUMMYFUNCTION("""COMPUTED_VALUE"""),1109.8044546078634) -> 1109.8045 | X17: =IFERROR(__xludf.DUMMYFUNCTION("""COMPUTED_VALUE"""),831.0795314031352) -> 831.07953 | Y17: =IFERROR(__xludf.DUMMYFUNCTION("""COMPUTED_VALUE"""),767.8362344105478) -> 767.83623 | Z17: =IFERROR(__xludf.DUMMYFUNCTION("""COMPUTED_VALUE"""),1097.5736744425697) -> 1097.5737 | AA17: =IFERROR(__xludf.DUMMYFUNCTION("""COMPUTED_VALUE"""),932.9268118994454) -> 932.92681 | AB17: =IFERROR(__xludf.DUMMYFUNCTION("""COMPUTED_VALUE"""),954.1293504362133) -> 954.12935 | AC17: =IFERROR(__xludf.DUMMYFUNCTION("""COMPUTED_VALUE"""),1059.1350185312829) -> 1059.135 | AD17: =IFERROR(__xludf.DUMMYFUNCTION("""COMPUTED_VALUE"""),1167.376226919392) -> 1167.3762 | AE17: =IFERROR(__xludf.DUMMYFUNCTION("""COMPUTED_VALUE"""),978.858851159081) -> 978.85885 | AF17: =IFERROR(__xludf.DUMMYFUNCTION("""COMPUTED_VALUE"""),972.3953907588619) -> 972.39539 | AG17: =IFERROR(__xludf.DUMMYFUNCTION("""COMPUTED_VALUE"""),1003.7249601368735) -> 1003.725 | AH17: =IFERROR(__xludf.DUMMYFUNCTION("""COMPUTED_VALUE"""),1111.6662457997015) -> 1111.6662 | AI17: =IFERROR(__xludf.DUMMYFUNCTION("""COMPUTED_VALUE"""),1154.196632792178) -> 1154.1966 | AJ17: =IFERROR(__xludf.DUMMYFUNCTION("""COMPUTED_VALUE"""),864.3227126592608) -> 864.32271 | AK17: =IFERROR(__xludf.DUMMYFUNCTION("""COMPUTED_VALUE"""),798.5496837869698) -> 798.54968 | AL17: =IFERROR(__xludf.DUMMYFUNCTION("""COMPUTED_VALUE"""),1141.4766214202725) -> 1141.4766 | AM17: =IFERROR(__xludf.DUMMYFUNCTION("""COMPUTED_VALUE"""),970.2438843754231) -> 970.24388 | AN17: =IFERROR(__xludf.DUMMYFUNCTION("""COMPUTED_VALUE"""),992.2945244536618) -> 992.29452 | AO17: =IFERROR(__xludf.DUMMYFUNCTION("""COMPUTED_VALUE"""),1101.5004192725341) -> 1101.5004 | AP17: =IFERROR(__xludf.DUMMYFUNCTION("""COMPUTED_VALUE"""),1214.0712759961673) -> 1214.0713 | AQ17: =IFERROR(__xludf.DUMMYFUNCTION("""COMPUTED_VALUE"""),1018.0132052054445) -> 1018.0132 | AR17: =IFERROR(__xludf.DUMMYFUNCTION("""COMPUTED_VALUE"""),1011.2912063892162) -> 1011.2912 | AS17: =IFERROR(__xludf.DUMMYFUNCTION("""COMPUTED_VALUE"""),1043.8739585423484) -> 1043.874 | AT17: =IFERROR(__xludf.DUMMYFUNCTION("""COMPUTED_VALUE"""),1156.1328956316895) -> 1156.1329 | AU17: =IFERROR(__xludf.DUMMYFUNCTION("""COMPUTED_VALUE"""),1200.3644981038651) -> 1200.3645 | AV17: =IFERROR(__xludf.DUMMYFUNCTION("""COMPUTED_VALUE"""),898.8956211656312) -> 898.89562 | AW17: =IFERROR(__xludf.DUMMYFUNCTION("""COMPUTED_VALUE"""),830.4916711384487) -> 830.49167 | AX17: =IFERROR(__xludf.DUMMYFUNCTION("""COMPUTED_VALUE"""),1187.1356862770833) -> 1187.1357 | AY17: =IFERROR(__xludf.DUMMYFUNCTION("""COMPUTED_VALUE"""),1009.05363975044) -> 1009.0536 | AZ17: =IFERROR(__xludf.DUMMYFUNCTION("""COMPUTED_VALUE"""),1031.9863054318084) -> 1031.9863 | BA17: =IFERROR(__xludf.DUMMYFUNCTION("""COMPUTED_VALUE"""),1145.5604360434356) -> 1145.5604 | BB17: =IFERROR(__xludf.DUMMYFUNCTION("""COMPUTED_VALUE"""),1262.634127036014) -> 1262.6341 | BC17: =IFERROR(__xludf.DUMMYFUNCTION("""COMPUTED_VALUE"""),1058.7337334136623) -> 1058.7337 | BD17: =IFERROR(__xludf.DUMMYFUNCTION("""COMPUTED_VALUE"""),1051.742854644785) -> 1051.7429 | BE17: =IFERROR(__xludf.DUMMYFUNCTION("""COMPUTED_VALUE"""),1085.6289168840426) -> 1085.6289 | BF17: =IFERROR(__xludf.DUMMYFUNCTION("""COMPUTED_VALUE"""),1202.3782114569572) -> 1202.3782 | BG17: =IFERROR(__xludf.DUMMYFUNCTION("""COMPUTED_VALUE"""),1248.3790780280196) -> 1248.3791 | BH17: =IFERROR(__xludf.DUMMYFUNCTION("""COMPUTED_VALUE"""),934.8514460122565) -> 934.85145 | BI17: =IFERROR(__xludf.DUMMYFUNCTION("""COMPUTED_VALUE"""),863.7113379839866) -> 863.71134 | BJ17: =IFERROR(__xludf.DUMMYFUNCTION("""COMPUTED_VALUE"""),1234.6211137281668) -> 1234.6211 | BK17: =IFERROR(__xludf.DUMMYFUNCTION("""COMPUTED_VALUE"""),1049.415785340458) -> 1049.4158 | BL17: =AVERAGE(D17:BK17) -> 1016.2345
B18: Reparto a Propietarios (Pass-through) | D18: =((D8+D13)*PctReparto)-((D9*CuotaSeg1)+(D14*CuotaSeg2)) -> 662588.45 | E18: =((E8+E13)*PctReparto)-((E9*CuotaSeg1)+(E14*CuotaSeg2)) -> 698022.29 | F18: =((F8+F13)*PctReparto)-((F9*CuotaSeg1)+(F14*CuotaSeg2)) -> 712786.52 | G18: =((G8+G13)*PctReparto)-((G9*CuotaSeg1)+(G14*CuotaSeg2)) -> 673390.49 | H18: =((H8+H13)*PctReparto)-((H9*CuotaSeg1)+(H14*CuotaSeg2)) -> 691853.06 | I18: =((I8+I13)*PctReparto)-((I9*CuotaSeg1)+(I14*CuotaSeg2)) -> 690944.55 | J18: =((J8+J13)*PctReparto)-((J9*CuotaSeg1)+(J14*CuotaSeg2)) -> 732679.36 | K18: =((K8+K13)*PctReparto)-((K9*CuotaSeg1)+(K14*CuotaSeg2)) -> 728444.13 | ... BK18: =((BK8+BK13)*PctReparto)-((BK9*CuotaSeg1)+(BK14*CuotaSeg2)) -> 616207.77 | BL18: =SUM(D18:BK18) -> 39527097 | BM18: =AVERAGE(D18:BK18) -> 658784.95
A19: Ingreso Del Mar (Neto de Reparto) | D19: =IFERROR(D$7-D18,"") -> 337823.27 | E19: =IFERROR(E$7-E18,"") -> 349021.51 | F19: =IFERROR(F$7-F18,"") -> 353391.98 | G19: =IFERROR(G$7-G18,"") -> 339653.03 | H19: =IFERROR(H$7-H18,"") -> 345222.9 | I19: =IFERROR(I$7-I18,"") -> 344319.37 | J19: =IFERROR(J$7-J18,"") -> 357652.66 | K19: =IFERROR(K$7-K18,"") -> 355646.41 | ... BK19: =IFERROR(BK$7-BK18,"") -> 291677.99 | BL19: =SUM(D19:BK19) -> 19227626 | BM19: =AVERAGE(D19:BK19) -> 320460.43
A20: % Take Rate Del Mar | D20: =IFERROR(D19/D$7,"") -> 0.33768424 | E20: =IFERROR(E19/E$7,"") -> 0.33333994 | F20: =IFERROR(F19/F$7,"") -> 0.33145667 | G20: =IFERROR(G19/G$7,"") -> 0.3352798 | H20: =IFERROR(H19/H$7,"") -> 0.33288102 | I20: =IFERROR(I19/I$7,"") -> 0.33259091 | J20: =IFERROR(J19/J$7,"") -> 0.32802179 | K20: =IFERROR(K19/K$7,"") -> 0.32805969 | ... BK20: =IFERROR(BK19/BK$7,"") -> 0.32127169 | BL20: =AVERAGE(D20:BK20) -> 0.32736199
A21: Costos Directos Del Mar (COGS) | D21: =IFERROR(SUM(D24),"Revise Error") -> 83334.296 | E21: =IFERROR(SUM(E24),"Revise Error") -> 87218.749 | F21: =IFERROR(SUM(F24),"Revise Error") -> 88812.668 | G21: =IFERROR(SUM(G24),"Revise Error") -> 84386.526 | H21: =IFERROR(SUM(H24),"Revise Error") -> 86388.427 | I21: =IFERROR(SUM(I24),"Revise Error") -> 86237.485 | J21: =IFERROR(SUM(J24),"Revise Error") -> 90824.657 | K21: =IFERROR(SUM(K24),"Revise Error") -> 90304.742 | ... BK21: =IFERROR(SUM(BK24),"Revise Error") -> 75626.884 | BL21: =SUM(D21:BK21) -> 4894268.4 | BM21: =AVERAGE(D21:BK21) -> 81571.14
A22: UT. Bruta | D22: =IFERROR(D19-D21,"Revise Error") -> 254488.97 | E22: =IFERROR(E19-E21,"Revise Error") -> 261802.77 | F22: =IFERROR(F19-F21,"Revise Error") -> 264579.31 | G22: =IFERROR(G19-G21,"Revise Error") -> 255266.51 | H22: =IFERROR(H19-H21,"Revise Error") -> 258834.47 | I22: =IFERROR(I19-I21,"Revise Error") -> 258081.89 | J22: =IFERROR(J19-J21,"Revise Error") -> 266828 | K22: =IFERROR(K19-K21,"Revise Error") -> 265341.66 | ... BK22: =IFERROR(BK19-BK21,"Revise Error") -> 216051.11 | BL22: =SUM(D22:BK22) -> 14333357 | BM22: =AVERAGE(D22:BK22) -> 238889.29
A23: % UT. Bruta | D23: =IFERROR(D22/D19,"Revise Error") -> 0.75331985 | E23: =IFERROR(E22/E19,"Revise Error") -> 0.75010495 | F23: =IFERROR(F22/F19,"Revise Error") -> 0.7486851 | G23: =IFERROR(G22/G19,"Revise Error") -> 0.7515508 | H23: =IFERROR(H22/H19,"Revise Error") -> 0.74976044 | I23: =IFERROR(I22/I19,"Revise Error") -> 0.74954216 | J23: =IFERROR(J22/J19,"Revise Error") -> 0.74605345 | K23: =IFERROR(K22/K19,"Revise Error") -> 0.74608279 | ... BK23: =IFERROR(BK22/BK19,"Revise Error") -> 0.74071789 | BL23: =AVERAGE(D23:BK23) -> 0.74545031
B24: Convenio Limpieza & Mantenimiento | D24: =IFERROR(D$7*PctConvenio,"Revise Error") -> 83334.296 | E24: =IFERROR(E$7*PctConvenio,"Revise Error") -> 87218.749 | F24: =IFERROR(F$7*PctConvenio,"Revise Error") -> 88812.668 | G24: =IFERROR(G$7*PctConvenio,"Revise Error") -> 84386.526 | H24: =IFERROR(H$7*PctConvenio,"Revise Error") -> 86388.427 | I24: =IFERROR(I$7*PctConvenio,"Revise Error") -> 86237.485 | J24: =IFERROR(J$7*PctConvenio,"Revise Error") -> 90824.657 | K24: =IFERROR(K$7*PctConvenio,"Revise Error") -> 90304.742 | ... BK24: =IFERROR(BK$7*PctConvenio,"Revise Error") -> 75626.884 | BL24: =SUM(D24:BK24) -> 4894268.4 | BM24: =AVERAGE(D24:BK24) -> 81571.14
A25: Gastos Operativos | D25: =IFERROR(D28+D34+D37+D43+D50,"Revise Error") -> 107990 | E25: =IFERROR(E28+E34+E37+E43+E50,"Revise Error") -> 107990 | F25: =IFERROR(F28+F34+F37+F43+F50,"Revise Error") -> 107990 | G25: =IFERROR(G28+G34+G37+G43+G50,"Revise Error") -> 107990 | H25: =IFERROR(H28+H34+H37+H43+H50,"Revise Error") -> 107990 | I25: =IFERROR(I28+I34+I37+I43+I50,"Revise Error") -> 107990 | J25: =IFERROR(J28+J34+J37+J43+J50,"Revise Error") -> 107990 | K25: =IFERROR(K28+K34+K37+K43+K50,"Revise Error") -> 107990 | ... BK25: =IFERROR(BK28+BK34+BK37+BK43+BK50,"Revise Error") -> 128558.69 | BL25: =SUM(D25:BK25) -> 7082887.5 | BM25: =AVERAGE(D25:BK25) -> 118048.13
A26: UT. Operativa | D26: =IFERROR(D22-D25,"Revise Error") -> 146498.97 | E26: =IFERROR(E22-E25,"Revise Error") -> 153812.77 | F26: =IFERROR(F22-F25,"Revise Error") -> 156589.31 | G26: =IFERROR(G22-G25,"Revise Error") -> 147276.51 | H26: =IFERROR(H22-H25,"Revise Error") -> 150844.47 | I26: =IFERROR(I22-I25,"Revise Error") -> 150091.89 | J26: =IFERROR(J22-J25,"Revise Error") -> 158838 | K26: =IFERROR(K22-K25,"Revise Error") -> 157351.66 | ... BK26: =IFERROR(BK22-BK25,"Revise Error") -> 87492.419 | BL26: =SUM(D26:BK26) -> 7250469.7 | BM26: =AVERAGE(D26:BK26) -> 120841.16
A27: % UT. Operativa | D27: =IFERROR(D26/D19,"Revise Error") -> 0.43365566 | E27: =IFERROR(E26/E19,"Revise Error") -> 0.44069709 | F27: =IFERROR(F26/F19,"Revise Error") -> 0.44310374 | G27: =IFERROR(G26/G19,"Revise Error") -> 0.43360869 | H27: =IFERROR(H26/H19,"Revise Error") -> 0.43694804 | I27: =IFERROR(I26/I19,"Revise Error") -> 0.43590892 | J27: =IFERROR(J26/J19,"Revise Error") -> 0.44411246 | K27: =IFERROR(K26/K19,"Revise Error") -> 0.4424385 | ... BK27: =IFERROR(BK26/BK19,"Revise Error") -> 0.29996236 | BL27: =AVERAGE(D27:BK27) -> 0.37452797
B28: A&G Administración General | D28: =(SUM(D30:D33)) * D$5 -> 25850 | E28: =(SUM(E30:E33)) * E$5 -> 25850 | F28: =(SUM(F30:F33)) * F$5 -> 25850 | G28: =(SUM(G30:G33)) * G$5 -> 25850 | H28: =(SUM(H30:H33)) * H$5 -> 25850 | I28: =(SUM(I30:I33)) * I$5 -> 25850 | J28: =(SUM(J30:J33)) * J$5 -> 25850 | K28: =(SUM(K30:K33)) * K$5 -> 25850 | ... BK28: =(SUM(BK30:BK33)) * BK$5 -> 30826.606 | BL28: =SUM(D28:BK28) -> 1697014.2 | BM28: =AVERAGE(D28:BK28) -> 28283.569
B29: % s/ Ingreso Del Mar | D29: =IFERROR(D28/D$19,"") -> 0.0765193 | E29: =IFERROR(E28/E$19,"") -> 0.074064202 | F29: =IFERROR(F28/F$19,"") -> 0.073148237 | G29: =IFERROR(G28/G$19,"") -> 0.076107078 | H29: =IFERROR(H28/H$19,"") -> 0.074879159 | I29: =IFERROR(I28/I$19,"") -> 0.075075648 | J29: =IFERROR(J28/J$19,"") -> 0.072276829 | K29: =IFERROR(K28/K$19,"") -> 0.072684553 | ... BK29: =IFERROR(BK28/BK$19,"") -> 0.10568712 | BL29: =AVERAGE(D29:BK29) -> 0.088873012
C30: Administrador | D30: =10350*(1+InflacionAnual)^(YEAR(D$3)-AnioBase)*IF((D$9+D$14)<=40,Tramo1,IF((D$9+D$14)<=80,Tramo2,Tramo3)) -> 10350 | E30: =10350*(1+InflacionAnual)^(YEAR(E$3)-AnioBase)*IF((E$9+E$14)<=40,Tramo1,IF((E$9+E$14)<=80,Tramo2,Tramo3)) -> 10350 | F30: =10350*(1+InflacionAnual)^(YEAR(F$3)-AnioBase)*IF((F$9+F$14)<=40,Tramo1,IF((F$9+F$14)<=80,Tramo2,Tramo3)) -> 10350 | G30: =10350*(1+InflacionAnual)^(YEAR(G$3)-AnioBase)*IF((G$9+G$14)<=40,Tramo1,IF((G$9+G$14)<=80,Tramo2,Tramo3)) -> 10350 | H30: =10350*(1+InflacionAnual)^(YEAR(H$3)-AnioBase)*IF((H$9+H$14)<=40,Tramo1,IF((H$9+H$14)<=80,Tramo2,Tramo3)) -> 10350 | I30: =10350*(1+InflacionAnual)^(YEAR(I$3)-AnioBase)*IF((I$9+I$14)<=40,Tramo1,IF((I$9+I$14)<=80,Tramo2,Tramo3)) -> 10350 | J30: =10350*(1+InflacionAnual)^(YEAR(J$3)-AnioBase)*IF((J$9+J$14)<=40,Tramo1,IF((J$9+J$14)<=80,Tramo2,Tramo3)) -> 10350 | K30: =10350*(1+InflacionAnual)^(YEAR(K$3)-AnioBase)*IF((K$9+K$14)<=40,Tramo1,IF((K$9+K$14)<=80,Tramo2,Tramo3)) -> 10350 | ... BK30: =10350*(1+InflacionAnual)^(YEAR(BK$3)-AnioBase)*IF((BK$9+BK$14)<=40,Tramo1,IF((BK$9+BK$14)<=80,Tramo2,Tramo3)) -> 12342.568 | BL30: =SUM(D30:BK30) -> 679462.15 | BM30: =AVERAGE(D30:BK30) -> 11324.369
C31: Customer Success Manager | D31: =15500*(1+InflacionAnual)^(YEAR(D$3)-AnioBase)*IF((D$9+D$14)<=40,Tramo1,IF((D$9+D$14)<=80,Tramo2,Tramo3)) -> 15500 | E31: =15500*(1+InflacionAnual)^(YEAR(E$3)-AnioBase)*IF((E$9+E$14)<=40,Tramo1,IF((E$9+E$14)<=80,Tramo2,Tramo3)) -> 15500 | F31: =15500*(1+InflacionAnual)^(YEAR(F$3)-AnioBase)*IF((F$9+F$14)<=40,Tramo1,IF((F$9+F$14)<=80,Tramo2,Tramo3)) -> 15500 | G31: =15500*(1+InflacionAnual)^(YEAR(G$3)-AnioBase)*IF((G$9+G$14)<=40,Tramo1,IF((G$9+G$14)<=80,Tramo2,Tramo3)) -> 15500 | H31: =15500*(1+InflacionAnual)^(YEAR(H$3)-AnioBase)*IF((H$9+H$14)<=40,Tramo1,IF((H$9+H$14)<=80,Tramo2,Tramo3)) -> 15500 | I31: =15500*(1+InflacionAnual)^(YEAR(I$3)-AnioBase)*IF((I$9+I$14)<=40,Tramo1,IF((I$9+I$14)<=80,Tramo2,Tramo3)) -> 15500 | J31: =15500*(1+InflacionAnual)^(YEAR(J$3)-AnioBase)*IF((J$9+J$14)<=40,Tramo1,IF((J$9+J$14)<=80,Tramo2,Tramo3)) -> 15500 | K31: =15500*(1+InflacionAnual)^(YEAR(K$3)-AnioBase)*IF((K$9+K$14)<=40,Tramo1,IF((K$9+K$14)<=80,Tramo2,Tramo3)) -> 15500 | ... BK31: =15500*(1+InflacionAnual)^(YEAR(BK$3)-AnioBase)*IF((BK$9+BK$14)<=40,Tramo1,IF((BK$9+BK$14)<=80,Tramo2,Tramo3)) -> 18484.038 | BL31: =SUM(D31:BK31) -> 1017552 | BM31: =AVERAGE(D31:BK31) -> 16959.2
C32: Gastos Administrativos (Varios)
C33: Uniformes
B34: Operación de Huéspedes | D34: =(SUM(D36)) * D$5 -> 34500 | E34: =(SUM(E36)) * E$5 -> 34500 | F34: =(SUM(F36)) * F$5 -> 34500 | G34: =(SUM(G36)) * G$5 -> 34500 | H34: =(SUM(H36)) * H$5 -> 34500 | I34: =(SUM(I36)) * I$5 -> 34500 | J34: =(SUM(J36)) * J$5 -> 34500 | K34: =(SUM(K36)) * K$5 -> 34500 | ... BK34: =(SUM(BK36)) * BK$5 -> 41141.892 | BL34: =SUM(D34:BK34) -> 2264873.8 | BM34: =AVERAGE(D34:BK34) -> 37747.897
B35: % s/ Ingreso Del Mar | D35: =IFERROR(D34/D$19,"") -> 0.1021244 | E35: =IFERROR(E34/E$19,"") -> 0.098847775 | F35: =IFERROR(F34/F$19,"") -> 0.097625306 | G35: =IFERROR(G34/G$19,"") -> 0.10157424 | H35: =IFERROR(H34/H$19,"") -> 0.099935434 | I35: =IFERROR(I34/I$19,"") -> 0.10019767 | J35: =IFERROR(J34/J$19,"") -> 0.096462305 | K35: =IFERROR(K34/K$19,"") -> 0.097006463 | ... BK35: =IFERROR(BK34/BK$19,"") -> 0.14105244 | BL35: =AVERAGE(D35:BK35) -> 0.11861195
C36: Concierge | D36: =34500*(1+InflacionAnual)^(YEAR(D$3)-AnioBase)*IF((D$9+D$14)<=40,Tramo1,IF((D$9+D$14)<=80,Tramo2,Tramo3)) -> 34500 | E36: =34500*(1+InflacionAnual)^(YEAR(E$3)-AnioBase)*IF((E$9+E$14)<=40,Tramo1,IF((E$9+E$14)<=80,Tramo2,Tramo3)) -> 34500 | F36: =34500*(1+InflacionAnual)^(YEAR(F$3)-AnioBase)*IF((F$9+F$14)<=40,Tramo1,IF((F$9+F$14)<=80,Tramo2,Tramo3)) -> 34500 | G36: =34500*(1+InflacionAnual)^(YEAR(G$3)-AnioBase)*IF((G$9+G$14)<=40,Tramo1,IF((G$9+G$14)<=80,Tramo2,Tramo3)) -> 34500 | H36: =34500*(1+InflacionAnual)^(YEAR(H$3)-AnioBase)*IF((H$9+H$14)<=40,Tramo1,IF((H$9+H$14)<=80,Tramo2,Tramo3)) -> 34500 | I36: =34500*(1+InflacionAnual)^(YEAR(I$3)-AnioBase)*IF((I$9+I$14)<=40,Tramo1,IF((I$9+I$14)<=80,Tramo2,Tramo3)) -> 34500 | J36: =34500*(1+InflacionAnual)^(YEAR(J$3)-AnioBase)*IF((J$9+J$14)<=40,Tramo1,IF((J$9+J$14)<=80,Tramo2,Tramo3)) -> 34500 | K36: =34500*(1+InflacionAnual)^(YEAR(K$3)-AnioBase)*IF((K$9+K$14)<=40,Tramo1,IF((K$9+K$14)<=80,Tramo2,Tramo3)) -> 34500 | ... BK36: =34500*(1+InflacionAnual)^(YEAR(BK$3)-AnioBase)*IF((BK$9+BK$14)<=40,Tramo1,IF((BK$9+BK$14)<=80,Tramo2,Tramo3)) -> 41141.892 | BL36: =SUM(D36:BK36) -> 2264873.8 | BM36: =AVERAGE(D36:BK36) -> 37747.897
B37: Ventas & Marketing | D37: =(SUM(D40:D42)) * D$5 -> 29670 | E37: =(SUM(E40:E42)) * E$5 -> 29670 | F37: =(SUM(F40:F42)) * F$5 -> 29670 | G37: =(SUM(G40:G42)) * G$5 -> 29670 | H37: =(SUM(H40:H42)) * H$5 -> 29670 | I37: =(SUM(I40:I42)) * I$5 -> 29670 | J37: =(SUM(J40:J42)) * J$5 -> 29670 | K37: =(SUM(K40:K42)) * K$5 -> 29670 | ... BK37: =(SUM(BK40:BK42)) * BK$5 -> 35382.027 | BL37: =SUM(D37:BK37) -> 1947791.5 | BM37: =AVERAGE(D37:BK37) -> 32463.192
B38: CAC de Reposición de Llaves | D38: =CACporLlave*(ChurnBruto/12)*TasaReposicion*(D$10+D$15) -> 28.914316 | E38: =CACporLlave*(ChurnBruto/12)*TasaReposicion*(E$10+E$15) -> 32.857022 | F38: =CACporLlave*(ChurnBruto/12)*TasaReposicion*(F$10+F$15) -> 33.106191 | G38: =CACporLlave*(ChurnBruto/12)*TasaReposicion*(G$10+G$15) -> 31.87498 | H38: =CACporLlave*(ChurnBruto/12)*TasaReposicion*(H$10+H$15) -> 31.751887 | I38: =CACporLlave*(ChurnBruto/12)*TasaReposicion*(I$10+I$15) -> 32.420814 | J38: =CACporLlave*(ChurnBruto/12)*TasaReposicion*(J$10+J$15) -> 34.196981 | K38: =CACporLlave*(ChurnBruto/12)*TasaReposicion*(K$10+K$15) -> 33.131744 | ... BK38: =CACporLlave*(ChurnBruto/12)*TasaReposicion*(BK$10+BK$15) -> 29.134311
B39: % s/ Ingreso Del Mar | D39: =IFERROR(D37/D$19,"") -> 0.087826987 | E39: =IFERROR(E37/E$19,"") -> 0.085009086 | F39: =IFERROR(F37/F$19,"") -> 0.083957764 | G39: =IFERROR(G37/G$19,"") -> 0.087353849 | H39: =IFERROR(H37/H$19,"") -> 0.085944473 | I39: =IFERROR(I37/I$19,"") -> 0.086169999 | J39: =IFERROR(J37/J$19,"") -> 0.082957583 | K39: =IFERROR(K37/K$19,"") -> 0.083425558 | ... BK39: =IFERROR(BK37/BK$19,"") -> 0.1213051 | BL39: =AVERAGE(D39:BK39) -> 0.10200628
C40: Honorarios | D40: =8000*(1+InflacionAnual)^(YEAR(D$3)-AnioBase) -> 8000 | E40: =8000*(1+InflacionAnual)^(YEAR(E$3)-AnioBase) -> 8000 | F40: =8000*(1+InflacionAnual)^(YEAR(F$3)-AnioBase) -> 8000 | G40: =8000*(1+InflacionAnual)^(YEAR(G$3)-AnioBase) -> 8000 | H40: =8000*(1+InflacionAnual)^(YEAR(H$3)-AnioBase) -> 8000 | I40: =8000*(1+InflacionAnual)^(YEAR(I$3)-AnioBase) -> 8000 | J40: =8000*(1+InflacionAnual)^(YEAR(J$3)-AnioBase) -> 8000 | K40: =8000*(1+InflacionAnual)^(YEAR(K$3)-AnioBase) -> 8000 | ... BK40: =8000*(1+InflacionAnual)^(YEAR(BK$3)-AnioBase) -> 9540.1488 | BL40: =SUM(D40:BK40) -> 525188.13 | BM40: =AVERAGE(D40:BK40) -> 8753.1356
C41: Revenue Manager | D41: =6670*(1+InflacionAnual)^(YEAR(D$3)-AnioBase)*IF((D$9+D$14)<=40,Tramo1,IF((D$9+D$14)<=80,Tramo2,Tramo3)) -> 6670 | E41: =6670*(1+InflacionAnual)^(YEAR(E$3)-AnioBase)*IF((E$9+E$14)<=40,Tramo1,IF((E$9+E$14)<=80,Tramo2,Tramo3)) -> 6670 | F41: =6670*(1+InflacionAnual)^(YEAR(F$3)-AnioBase)*IF((F$9+F$14)<=40,Tramo1,IF((F$9+F$14)<=80,Tramo2,Tramo3)) -> 6670 | G41: =6670*(1+InflacionAnual)^(YEAR(G$3)-AnioBase)*IF((G$9+G$14)<=40,Tramo1,IF((G$9+G$14)<=80,Tramo2,Tramo3)) -> 6670 | H41: =6670*(1+InflacionAnual)^(YEAR(H$3)-AnioBase)*IF((H$9+H$14)<=40,Tramo1,IF((H$9+H$14)<=80,Tramo2,Tramo3)) -> 6670 | I41: =6670*(1+InflacionAnual)^(YEAR(I$3)-AnioBase)*IF((I$9+I$14)<=40,Tramo1,IF((I$9+I$14)<=80,Tramo2,Tramo3)) -> 6670 | J41: =6670*(1+InflacionAnual)^(YEAR(J$3)-AnioBase)*IF((J$9+J$14)<=40,Tramo1,IF((J$9+J$14)<=80,Tramo2,Tramo3)) -> 6670 | K41: =6670*(1+InflacionAnual)^(YEAR(K$3)-AnioBase)*IF((K$9+K$14)<=40,Tramo1,IF((K$9+K$14)<=80,Tramo2,Tramo3)) -> 6670 | ... BK41: =6670*(1+InflacionAnual)^(YEAR(BK$3)-AnioBase)*IF((BK$9+BK$14)<=40,Tramo1,IF((BK$9+BK$14)<=80,Tramo2,Tramo3)) -> 7954.0991 | BL41: =SUM(D41:BK41) -> 437875.61 | BM41: =AVERAGE(D41:BK41) -> 7297.9268
C42: Campañas | D42: =15000*(1+InflacionAnual)^(YEAR(D$3)-AnioBase) -> 15000 | E42: =15000*(1+InflacionAnual)^(YEAR(E$3)-AnioBase) -> 15000 | F42: =15000*(1+InflacionAnual)^(YEAR(F$3)-AnioBase) -> 15000 | G42: =15000*(1+InflacionAnual)^(YEAR(G$3)-AnioBase) -> 15000 | H42: =15000*(1+InflacionAnual)^(YEAR(H$3)-AnioBase) -> 15000 | I42: =15000*(1+InflacionAnual)^(YEAR(I$3)-AnioBase) -> 15000 | J42: =15000*(1+InflacionAnual)^(YEAR(J$3)-AnioBase) -> 15000 | K42: =15000*(1+InflacionAnual)^(YEAR(K$3)-AnioBase) -> 15000 | ... BK42: =15000*(1+InflacionAnual)^(YEAR(BK$3)-AnioBase) -> 17887.779 | BL42: =SUM(D42:BK42) -> 984727.75 | BM42: =AVERAGE(D42:BK42) -> 16412.129
B43: IT / Sistemas | D43: =(SUM(D45:D49)) * D$5 -> 17970 | E43: =(SUM(E45:E49)) * E$5 -> 17970 | F43: =(SUM(F45:F49)) * F$5 -> 17970 | G43: =(SUM(G45:G49)) * G$5 -> 17970 | H43: =(SUM(H45:H49)) * H$5 -> 17970 | I43: =(SUM(I45:I49)) * I$5 -> 17970 | J43: =(SUM(J45:J49)) * J$5 -> 17970 | K43: =(SUM(K45:K49)) * K$5 -> 17970 | ... BK43: =(SUM(BK45:BK49)) * BK$5 -> 21208.163 | BL43: =SUM(D43:BK43) -> 1173208.1 | BM43: =AVERAGE(D43:BK43) -> 19553.468
B44: % s/ Ingreso Del Mar | D44: =IFERROR(D43/D$19,"") -> 0.053193494 | E44: =IFERROR(E43/E$19,"") -> 0.051486797 | F44: =IFERROR(F43/F$19,"") -> 0.050850051 | G44: =IFERROR(G43/G$19,"") -> 0.052906932 | H44: =IFERROR(H43/H$19,"") -> 0.052053326 | I44: =IFERROR(I43/I$19,"") -> 0.052189919 | J44: =IFERROR(J43/J$19,"") -> 0.050244279 | K44: =IFERROR(K43/K$19,"") -> 0.050527714 | ... BK44: =IFERROR(BK43/BK$19,"") -> 0.072710878 | BL44: =AVERAGE(D44:BK44) -> 0.0614311
C45: Guesty (PMS) | D45: =7540*(1+InflacionAnual)^(YEAR(D$3)-AnioBase) -> 7540 | E45: =7540*(1+InflacionAnual)^(YEAR(E$3)-AnioBase) -> 7540 | F45: =7540*(1+InflacionAnual)^(YEAR(F$3)-AnioBase) -> 7540 | G45: =7540*(1+InflacionAnual)^(YEAR(G$3)-AnioBase) -> 7540 | H45: =7540*(1+InflacionAnual)^(YEAR(H$3)-AnioBase) -> 7540 | I45: =7540*(1+InflacionAnual)^(YEAR(I$3)-AnioBase) -> 7540 | J45: =7540*(1+InflacionAnual)^(YEAR(J$3)-AnioBase) -> 7540 | K45: =7540*(1+InflacionAnual)^(YEAR(K$3)-AnioBase) -> 7540 | ... BK45: =7540*(1+InflacionAnual)^(YEAR(BK$3)-AnioBase) -> 8991.5902 | BL45: =SUM(D45:BK45) -> 494989.82 | BM45: =AVERAGE(D45:BK45) -> 8249.8303
C46: Pricelabs (RMS) | D46: =3480*(1+InflacionAnual)^(YEAR(D$3)-AnioBase) -> 3480 | E46: =3480*(1+InflacionAnual)^(YEAR(E$3)-AnioBase) -> 3480 | F46: =3480*(1+InflacionAnual)^(YEAR(F$3)-AnioBase) -> 3480 | G46: =3480*(1+InflacionAnual)^(YEAR(G$3)-AnioBase) -> 3480 | H46: =3480*(1+InflacionAnual)^(YEAR(H$3)-AnioBase) -> 3480 | I46: =3480*(1+InflacionAnual)^(YEAR(I$3)-AnioBase) -> 3480 | J46: =3480*(1+InflacionAnual)^(YEAR(J$3)-AnioBase) -> 3480 | K46: =3480*(1+InflacionAnual)^(YEAR(K$3)-AnioBase) -> 3480 | ... BK46: =3480*(1+InflacionAnual)^(YEAR(BK$3)-AnioBase) -> 4149.9647 | BL46: =SUM(D46:BK46) -> 228456.84 | BM46: =AVERAGE(D46:BK46) -> 3807.614
C47: Sentinel (RMS) | D47: =5800*(1+InflacionAnual)^(YEAR(D$3)-AnioBase) -> 5800 | E47: =5800*(1+InflacionAnual)^(YEAR(E$3)-AnioBase) -> 5800 | F47: =5800*(1+InflacionAnual)^(YEAR(F$3)-AnioBase) -> 5800 | G47: =5800*(1+InflacionAnual)^(YEAR(G$3)-AnioBase) -> 5800 | H47: =5800*(1+InflacionAnual)^(YEAR(H$3)-AnioBase) -> 5800 | I47: =5800*(1+InflacionAnual)^(YEAR(I$3)-AnioBase) -> 5800 | J47: =5800*(1+InflacionAnual)^(YEAR(J$3)-AnioBase) -> 5800 | K47: =5800*(1+InflacionAnual)^(YEAR(K$3)-AnioBase) -> 5800 | ... BK47: =5800*(1+InflacionAnual)^(YEAR(BK$3)-AnioBase) -> 6916.6079 | BL47: =SUM(D47:BK47) -> 380761.4 | BM47: =AVERAGE(D47:BK47) -> 6346.0233
C48: Webpage Hosting | D48: 150 | E48: 150 | F48: 150 | G48: 150 | H48: 150 | I48: 150 | J48: 150 | K48: 150 | L48: 150 | M48: 150 | N48: 150 | O48: 150 | P48: 150 | Q48: 150 | R48: 150 | S48: 150 | T48: 150 | U48: 150 | V48: 150 | W48: 150 | X48: 150 | Y48: 150 | Z48: 150 | AA48: 150 | AB48: 150 | AC48: 150 | AD48: 150 | AE48: 150 | AF48: 150 | AG48: 150 | AH48: 150 | AI48: 150 | AJ48: 150 | AK48: 150 | AL48: 150 | AM48: 150 | AN48: 150 | AO48: 150 | AP48: 150 | AQ48: 150 | AR48: 150 | AS48: 150 | AT48: 150 | AU48: 150 | AV48: 150 | AW48: 150 | AX48: 150 | AY48: 150 | AZ48: 150 | BA48: 150 | BB48: 150 | BC48: 150 | BD48: 150 | BE48: 150 | BF48: 150 | BG48: 150 | BH48: 150 | BI48: 150 | BJ48: 150 | BK48: 150 | BL48: =SUM(D48:BK48) -> 9000 | BM48: =AVERAGE(D48:BK48) -> 150
C49: Telefono | D49: 1000 | E49: 1000 | F49: 1000 | G49: 1000 | H49: 1000 | I49: 1000 | J49: 1000 | K49: 1000 | L49: 1000 | M49: 1000 | N49: 1000 | O49: 1000 | P49: 1000 | Q49: 1000 | R49: 1000 | S49: 1000 | T49: 1000 | U49: 1000 | V49: 1000 | W49: 1000 | X49: 1000 | Y49: 1000 | Z49: 1000 | AA49: 1000 | AB49: 1000 | AC49: 1000 | AD49: 1000 | AE49: 1000 | AF49: 1000 | AG49: 1000 | AH49: 1000 | AI49: 1000 | AJ49: 1000 | AK49: 1000 | AL49: 1000 | AM49: 1000 | AN49: 1000 | AO49: 1000 | AP49: 1000 | AQ49: 1000 | AR49: 1000 | AS49: 1000 | AT49: 1000 | AU49: 1000 | AV49: 1000 | AW49: 1000 | AX49: 1000 | AY49: 1000 | AZ49: 1000 | BA49: 1000 | BB49: 1000 | BC49: 1000 | BD49: 1000 | BE49: 1000 | BF49: 1000 | BG49: 1000 | BH49: 1000 | BI49: 1000 | BJ49: 1000 | BK49: 1000 | BL49: =SUM(D49:BK49) -> 60000 | BM49: =AVERAGE(D49:BK49) -> 1000
B50: Utilities / Servicios | D50: =(SUM(D52:D53)) * D$5 -> 0 | E50: =(SUM(E52:E53)) * E$5 -> 0 | F50: =(SUM(F52:F53)) * F$5 -> 0 | G50: =(SUM(G52:G53)) * G$5 -> 0 | H50: =(SUM(H52:H53)) * H$5 -> 0 | I50: =(SUM(I52:I53)) * I$5 -> 0 | J50: =(SUM(J52:J53)) * J$5 -> 0 | K50: =(SUM(K52:K53)) * K$5 -> 0 | ... BK50: =(SUM(BK52:BK53)) * BK$5 -> 0 | BL50: =SUM(D50:BK50) -> 0 | BM50: =AVERAGE(D50:BK50) -> 0
B51: % s/ Ingreso Del Mar | D51: =IFERROR(D50/D$19,"") -> 0 | E51: =IFERROR(E50/E$19,"") -> 0 | F51: =IFERROR(F50/F$19,"") -> 0 | G51: =IFERROR(G50/G$19,"") -> 0 | H51: =IFERROR(H50/H$19,"") -> 0 | I51: =IFERROR(I50/I$19,"") -> 0 | J51: =IFERROR(J50/J$19,"") -> 0 | K51: =IFERROR(K50/K$19,"") -> 0 | ... BK51: =IFERROR(BK50/BK$19,"") -> 0 | BL51: =AVERAGE(D51:BK51) -> 0
C52: Gas LP | BL52: =SUM(D52:BK52) -> 0 | BM52: =AVERAGE(D52:BK52) -> #DIV/0!
D54: 0 | E54: 0 | F54: 0 | G54: 0 | H54: 0 | I54: 0 | J54: 0 | K54: 0 | L54: 0 | M54: 0 | N54: 0 | O54: 0 | P54: 0 | Q54: 0 | R54: 0 | S54: 0 | T54: 0 | U54: 0 | V54: 0 | W54: 0 | X54: 0 | Y54: 0 | Z54: 0 | AA54: 0 | AB54: 0 | AC54: 0 | AD54: 0 | AE54: 0 | AF54: 0 | AG54: 0 | AH54: 0 | AI54: 0 | AJ54: 0 | AK54: 0 | AL54: 0 | AM54: 0 | AN54: 0 | AO54: 0 | AP54: 0 | AQ54: 0 | AR54: 0 | AS54: 0 | AT54: 0 | AU54: 0 | AV54: 0 | AW54: 0 | AX54: 0 | AY54: 0 | AZ54: 0 | BA54: 0 | BB54: 0 | BC54: 0 | BD54: 0 | BE54: 0 | BF54: 0 | BG54: 0 | BH54: 0 | BI54: 0 | BJ54: 0 | BK54: 0 | BL54: =SUM(D54:BK54) -> 0 | BM54: =AVERAGE(D54:BK54) -> 0
A55: EBITDA | D55: =IFERROR(((D19-D21)-D25),"Revise Error") -> 146498.97 | E55: =IFERROR(((E19-E21)-E25),"Revise Error") -> 153812.77 | F55: =IFERROR(((F19-F21)-F25),"Revise Error") -> 156589.31 | G55: =IFERROR(((G19-G21)-G25),"Revise Error") -> 147276.51 | H55: =IFERROR(((H19-H21)-H25),"Revise Error") -> 150844.47 | I55: =IFERROR(((I19-I21)-I25),"Revise Error") -> 150091.89 | J55: =IFERROR(((J19-J21)-J25),"Revise Error") -> 158838 | K55: =IFERROR(((K19-K21)-K25),"Revise Error") -> 157351.66 | ... BK55: =IFERROR(((BK19-BK21)-BK25),"Revise Error") -> 87492.419 | BL55: =SUM(D55:BK55) -> 7250469.7 | BM55: =AVERAGE(D55:BK55) -> 120841.16
A56: % EBITDA | D56: =IFERROR(D55/D19,"Revise Error") -> 0.43365566 | E56: =IFERROR(E55/E19,"Revise Error") -> 0.44069709 | F56: =IFERROR(F55/F19,"Revise Error") -> 0.44310374 | G56: =IFERROR(G55/G19,"Revise Error") -> 0.43360869 | H56: =IFERROR(H55/H19,"Revise Error") -> 0.43694804 | I56: =IFERROR(I55/I19,"Revise Error") -> 0.43590892 | J56: =IFERROR(J55/J19,"Revise Error") -> 0.44411246 | K56: =IFERROR(K55/K19,"Revise Error") -> 0.4424385 | ... BK56: =IFERROR(BK55/BK19,"Revise Error") -> 0.29996236 | BL56: =AVERAGE(D56:BK56) -> 0.37452797
C59: Check: Venta = suma segmentos | D59: =IF(ABS(D$7-(D8+D13))<1,"OK","ERROR") -> OK | E59: =IF(ABS(E$7-(E8+E13))<1,"OK","ERROR") -> OK | F59: =IF(ABS(F$7-(F8+F13))<1,"OK","ERROR") -> OK | G59: =IF(ABS(G$7-(G8+G13))<1,"OK","ERROR") -> OK | H59: =IF(ABS(H$7-(H8+H13))<1,"OK","ERROR") -> OK | I59: =IF(ABS(I$7-(I8+I13))<1,"OK","ERROR") -> OK | J59: =IF(ABS(J$7-(J8+J13))<1,"OK","ERROR") -> OK | K59: =IF(ABS(K$7-(K8+K13))<1,"OK","ERROR") -> OK | ... BK59: =IF(ABS(BK$7-(BK8+BK13))<1,"OK","ERROR") -> OK
C60: Check: Ingreso DM + Reparto = Venta | D60: =IF(ABS(D$7-(D18+D19))<1,"OK","ERROR") -> OK | E60: =IF(ABS(E$7-(E18+E19))<1,"OK","ERROR") -> OK | F60: =IF(ABS(F$7-(F18+F19))<1,"OK","ERROR") -> OK | G60: =IF(ABS(G$7-(G18+G19))<1,"OK","ERROR") -> OK | H60: =IF(ABS(H$7-(H18+H19))<1,"OK","ERROR") -> OK | I60: =IF(ABS(I$7-(I18+I19))<1,"OK","ERROR") -> OK | J60: =IF(ABS(J$7-(J18+J19))<1,"OK","ERROR") -> OK | K60: =IF(ABS(K$7-(K18+K19))<1,"OK","ERROR") -> OK | ... BK60: =IF(ABS(BK$7-(BK18+BK19))<1,"OK","ERROR") -> OK
C61: Check: Gastos Op = suma bloques | D61: =IF(ABS(D25-(D28+D34+D37+D43+D50))<1,"OK","ERROR") -> OK | E61: =IF(ABS(E25-(E28+E34+E37+E43+E50))<1,"OK","ERROR") -> OK | F61: =IF(ABS(F25-(F28+F34+F37+F43+F50))<1,"OK","ERROR") -> OK | G61: =IF(ABS(G25-(G28+G34+G37+G43+G50))<1,"OK","ERROR") -> OK | H61: =IF(ABS(H25-(H28+H34+H37+H43+H50))<1,"OK","ERROR") -> OK | I61: =IF(ABS(I25-(I28+I34+I37+I43+I50))<1,"OK","ERROR") -> OK | J61: =IF(ABS(J25-(J28+J34+J37+J43+J50))<1,"OK","ERROR") -> OK | K61: =IF(ABS(K25-(K28+K34+K37+K43+K50))<1,"OK","ERROR") -> OK | ... BK61: =IF(ABS(BK25-(BK28+BK34+BK37+BK43+BK50))<1,"OK","ERROR") -> OK
C62: Check: sin errores en columna | D62: =IF(SUMPRODUCT(--ISERROR(D$7:D$56))=0,"OK","ERROR") -> OK | E62: =IF(SUMPRODUCT(--ISERROR(E$7:E$56))=0,"OK","ERROR") -> OK | F62: =IF(SUMPRODUCT(--ISERROR(F$7:F$56))=0,"OK","ERROR") -> OK | G62: =IF(SUMPRODUCT(--ISERROR(G$7:G$56))=0,"OK","ERROR") -> OK | H62: =IF(SUMPRODUCT(--ISERROR(H$7:H$56))=0,"OK","ERROR") -> OK | I62: =IF(SUMPRODUCT(--ISERROR(I$7:I$56))=0,"OK","ERROR") -> OK | J62: =IF(SUMPRODUCT(--ISERROR(J$7:J$56))=0,"OK","ERROR") -> OK | K62: =IF(SUMPRODUCT(--ISERROR(K$7:K$56))=0,"OK","ERROR") -> OK | ... BK62: =IF(SUMPRODUCT(--ISERROR(BK$7:BK$56))=0,"OK","ERROR") -> OK

Sheet Flujo de Efectivo
D3: ='Profit & Loss'!D3 -> 45658 | E3: ='Profit & Loss'!E3 -> 45689 | F3: ='Profit & Loss'!F3 -> 45717 | G3: ='Profit & Loss'!G3 -> 45748 | H3: ='Profit & Loss'!H3 -> 45778 | I3: ='Profit & Loss'!I3 -> 45809 | J3: ='Profit & Loss'!J3 -> 45839 | K3: ='Profit & Loss'!K3 -> 45870 | ... BK3: ='Profit & Loss'!BK3 -> 47453
A4: BLOQUE 0: PANEL DE CONTROL (TIMING Y SUPUESTOS)
A5: Plazo de cobranza Airbnb (días) | B5: 4
A6: Plazo de cobranza Booking.com (días) | B6: 0
A7: Plazo de cobranza VRBO (días) | B7: 3
A8: Plazo de cobranza Directo (días) | B8: -30
A9: Comisión Booking.com | B9: 0.17 | C9: Pago a 45 días
A10: Pago a Propietarios | B10: Corte día 5, Pago día 3 del mes siguiente
A11: ISR | B11: 0.3 | C11: Pago día 17 del mes siguiente
A12: Plazo de pago a Proveedores (días) | B12: 30
A13: Línea de Crédito Revolvente - Límite | B13: 500000
A14: Línea de Crédito - Tasa Anual | B14: 0.15
A15: Saldo Mínimo de Caja Deseado | B15: 200000
A17: CALENDARIO DE DESEMBOLSO DE INVERSIÓN INICIAL
A18: Mes | B18: t0 | C18: M1 (Ene-25) | D18: M2 (Feb-25) | E18: M3 (Mar-25)
A19: % Desembolso | B19: 0 | C19: 0.5 | D19: 0.3 | E19: 0.2
A20: Inversión Total | B20: ='Paso 5 Resumen Desglose de Inve'!D25+'Paso 5 Resumen Desglose de Inve'!D35+'Paso 5 Resumen Desglose de Inve'!D50+'Paso 5 Resumen Desglose de Inve'!D59+'Paso 5 Resumen Desglose de Inve'!D68 -> 3173369.8
A21: Monto Desembolsado | B21: =$B$20*B19 -> 0 | C21: =$B$20*C19 -> 1586684.9 | D21: =$B$20*D19 -> 952010.95 | E21: =$B$20*E19 -> 634673.97
A23: Mix de Canales
A24: Airbnb | B24: 0.5
A25: Booking.com | B25: 0.2
A26: VRBO | B26: 0.1
A27: Directo | B27: 0.2
A29: BLOQUE 1: ENTRADAS DE EFECTIVO
A30: Venta Total Devengada | D30: {=IFERROR(1*INDEX('Profit & Loss'!$1:$996, MATCH("Venta Total (Despues de Comisiones OTAs + Pasarelas de Pago, IVA e Impuestos)", 'Profit & Loss'!$A:$A, 0), COLUMN()), 0)} -> 1000411.7 | E30: {=IFERROR(1*INDEX('Profit & Loss'!$1:$996, MATCH("Venta Total (Despues de Comisiones OTAs + Pasarelas de Pago, IVA e Impuestos)", 'Profit & Loss'!$A:$A, 0), COLUMN()), 0)} -> 1047043.8 | F30: {=IFERROR(1*INDEX('Profit & Loss'!$1:$996, MATCH("Venta Total (Despues de Comisiones OTAs + Pasarelas de Pago, IVA e Impuestos)", 'Profit & Loss'!$A:$A, 0), COLUMN()), 0)} -> 1066178.5 | G30: {=IFERROR(1*INDEX('Profit & Loss'!$1:$996, MATCH("Venta Total (Despues de Comisiones OTAs + Pasarelas de Pago, IVA e Impuestos)", 'Profit & Loss'!$A:$A, 0), COLUMN()), 0)} -> 1013043.5 | H30: {=IFERROR(1*INDEX('Profit & Loss'!$1:$996, MATCH("Venta Total (Despues de Comisiones OTAs + Pasarelas de Pago, IVA e Impuestos)", 'Profit & Loss'!$A:$A, 0), COLUMN()), 0)} -> 1037076 | I30: {=IFERROR(1*INDEX('Profit & Loss'!$1:$996, MATCH("Venta Total (Despues de Comisiones OTAs + Pasarelas de Pago, IVA e Impuestos)", 'Profit & Loss'!$A:$A, 0), COLUMN()), 0)} -> 1035263.9 | J30: {=IFERROR(1*INDEX('Profit & Loss'!$1:$996, MATCH("Venta Total (Despues de Comisiones OTAs + Pasarelas de Pago, IVA e Impuestos)", 'Profit & Loss'!$A:$A, 0), COLUMN()), 0)} -> 1090332 | K30: {=IFERROR(1*INDEX('Profit & Loss'!$1:$996, MATCH("Venta Total (Despues de Comisiones OTAs + Pasarelas de Pago, IVA e Impuestos)", 'Profit & Loss'!$A:$A, 0), COLUMN()), 0)} -> 1084090.5 | ... BK30: {=IFERROR(1*INDEX('Profit & Loss'!$1:$996, MATCH("Venta Total (Despues de Comisiones OTAs + Pasarelas de Pago, IVA e Impuestos)", 'Profit & Loss'!$A:$A, 0), COLUMN()), 0)} -> 907885.76
A31: Cobranza Airbnb | D31: =D30 * $B$24 * (MAX(0, 30 - $B$5)/30) + N(C30) * $B$24 * ($B$5/30) -> 433511.75 | E31: =E30 * $B$24 * (MAX(0, 30 - $B$5)/30) + N(D30) * $B$24 * ($B$5/30) -> 520413.09 | F31: =F30 * $B$24 * (MAX(0, 30 - $B$5)/30) + N(E30) * $B$24 * ($B$5/30) -> 531813.6 | G31: =G30 * $B$24 * (MAX(0, 30 - $B$5)/30) + N(F30) * $B$24 * ($B$5/30) -> 510064.09 | H31: =H30 * $B$24 * (MAX(0, 30 - $B$5)/30) + N(G30) * $B$24 * ($B$5/30) -> 516935.81 | I31: =I30 * $B$24 * (MAX(0, 30 - $B$5)/30) + N(H30) * $B$24 * ($B$5/30) -> 517752.76 | J31: =J30 * $B$24 * (MAX(0, 30 - $B$5)/30) + N(I30) * $B$24 * ($B$5/30) -> 541494.8 | K31: =K30 * $B$24 * (MAX(0, 30 - $B$5)/30) + N(J30) * $B$24 * ($B$5/30) -> 542461.37 | ... BK31: =BK30 * $B$24 * (MAX(0, 30 - $B$5)/30) + N(BJ30) * $B$24 * ($B$5/30) -> 459565.06
A32: Cobranza Booking.com | D32: =(D30 * $B$25 / (1 - $B$9)) * (MAX(0, 30 - $B$6)/30) + (N(C30) * $B$25 / (1 - $B$9)) * ($B$6/30) -> 241063.07 | E32: =(E30 * $B$25 / (1 - $B$9)) * (MAX(0, 30 - $B$6)/30) + (N(D30) * $B$25 / (1 - $B$9)) * ($B$6/30) -> 252299.71 | F32: =(F30 * $B$25 / (1 - $B$9)) * (MAX(0, 30 - $B$6)/30) + (N(E30) * $B$25 / (1 - $B$9)) * ($B$6/30) -> 256910.48 | G32: =(G30 * $B$25 / (1 - $B$9)) * (MAX(0, 30 - $B$6)/30) + (N(F30) * $B$25 / (1 - $B$9)) * ($B$6/30) -> 244106.87 | H32: =(H30 * $B$25 / (1 - $B$9)) * (MAX(0, 30 - $B$6)/30) + (N(G30) * $B$25 / (1 - $B$9)) * ($B$6/30) -> 249897.82 | I32: =(I30 * $B$25 / (1 - $B$9)) * (MAX(0, 30 - $B$6)/30) + (N(H30) * $B$25 / (1 - $B$9)) * ($B$6/30) -> 249461.19 | J32: =(J30 * $B$25 / (1 - $B$9)) * (MAX(0, 30 - $B$6)/30) + (N(I30) * $B$25 / (1 - $B$9)) * ($B$6/30) -> 262730.61 | K32: =(K30 * $B$25 / (1 - $B$9)) * (MAX(0, 30 - $B$6)/30) + (N(J30) * $B$25 / (1 - $B$9)) * ($B$6/30) -> 261226.64 | ... BK32: =(BK30 * $B$25 / (1 - $B$9)) * (MAX(0, 30 - $B$6)/30) + (N(BJ30) * $B$25 / (1 - $B$9)) * ($B$6/30) -> 218767.65
A33: Cobranza VRBO | D33: =D30 * $B$26 * (MAX(0, 30 - $B$7)/30) + N(C30) * $B$26 * ($B$7/30) -> 90037.055 | E33: =E30 * $B$26 * (MAX(0, 30 - $B$7)/30) + N(D30) * $B$26 * ($B$7/30) -> 104238.06 | F33: =F30 * $B$26 * (MAX(0, 30 - $B$7)/30) + N(E30) * $B$26 * ($B$7/30) -> 106426.5 | G33: =G30 * $B$26 * (MAX(0, 30 - $B$7)/30) + N(F30) * $B$26 * ($B$7/30) -> 101835.7 | H33: =H30 * $B$26 * (MAX(0, 30 - $B$7)/30) + N(G30) * $B$26 * ($B$7/30) -> 103467.27 | I33: =I30 * $B$26 * (MAX(0, 30 - $B$7)/30) + N(H30) * $B$26 * ($B$7/30) -> 103544.51 | J33: =J30 * $B$26 * (MAX(0, 30 - $B$7)/30) + N(I30) * $B$26 * ($B$7/30) -> 108482.52 | K33: =K30 * $B$26 * (MAX(0, 30 - $B$7)/30) + N(J30) * $B$26 * ($B$7/30) -> 108471.47 | ... BK33: =BK30 * $B$26 * (MAX(0, 30 - $B$7)/30) + N(BJ30) * $B$26 * ($B$7/30) -> 91631.903
A34: Cobranza Directo | D34: =D30 * $B$27 * (MAX(0, 30 + $B$8)/30) + E30 * $B$27 * (ABS($B$8)/30) -> 209408.76 | E34: =E30 * $B$27 * (MAX(0, 30 + $B$8)/30) + F30 * $B$27 * (ABS($B$8)/30) -> 213235.7 | F34: =F30 * $B$27 * (MAX(0, 30 + $B$8)/30) + G30 * $B$27 * (ABS($B$8)/30) -> 202608.71 | G34: =G30 * $B$27 * (MAX(0, 30 + $B$8)/30) + H30 * $B$27 * (ABS($B$8)/30) -> 207415.19 | H34: =H30 * $B$27 * (MAX(0, 30 + $B$8)/30) + I30 * $B$27 * (ABS($B$8)/30) -> 207052.78 | I34: =I30 * $B$27 * (MAX(0, 30 + $B$8)/30) + J30 * $B$27 * (ABS($B$8)/30) -> 218066.4 | J34: =J30 * $B$27 * (MAX(0, 30 + $B$8)/30) + K30 * $B$27 * (ABS($B$8)/30) -> 216818.11 | K34: =K30 * $B$27 * (MAX(0, 30 + $B$8)/30) + L30 * $B$27 * (ABS($B$8)/30) -> 186431.99 | ... BK34: =BK30 * $B$27 * (MAX(0, 30 + $B$8)/30) + BL30 * $B$27 * (ABS($B$8)/30) -> 0
A35: Total Entradas de Efectivo | D35: =SUM(D31:D34) -> 974020.63 | E35: =SUM(E31:E34) -> 1090186.6 | F35: =SUM(F31:F34) -> 1097759.3 | G35: =SUM(G31:G34) -> 1063421.9 | H35: =SUM(H31:H34) -> 1077353.7 | I35: =SUM(I31:I34) -> 1088824.9 | J35: =SUM(J31:J34) -> 1129526 | K35: =SUM(K31:K34) -> 1098591.5 | ... BK35: =SUM(BK31:BK34) -> 769964.62
A37: BLOQUE 2: SALIDAS DE EFECTIVO
A38: Reparto a Propietarios | D38: {=IFERROR(1*INDEX('Profit & Loss'!$1:$996, MATCH("Reparto a Propietarios*", 'Profit & Loss'!$B:$B, 0), COLUMN()-1), 0)} -> 0 | E38: {=IFERROR(1*INDEX('Profit & Loss'!$1:$996, MATCH("Reparto a Propietarios*", 'Profit & Loss'!$B:$B, 0), COLUMN()-1), 0)} -> 662588.45 | F38: {=IFERROR(1*INDEX('Profit & Loss'!$1:$996, MATCH("Reparto a Propietarios*", 'Profit & Loss'!$B:$B, 0), COLUMN()-1), 0)} -> 698022.29 | G38: {=IFERROR(1*INDEX('Profit & Loss'!$1:$996, MATCH("Reparto a Propietarios*", 'Profit & Loss'!$B:$B, 0), COLUMN()-1), 0)} -> 712786.52 | H38: {=IFERROR(1*INDEX('Profit & Loss'!$1:$996, MATCH("Reparto a Propietarios*", 'Profit & Loss'!$B:$B, 0), COLUMN()-1), 0)} -> 673390.49 | I38: {=IFERROR(1*INDEX('Profit & Loss'!$1:$996, MATCH("Reparto a Propietarios*", 'Profit & Loss'!$B:$B, 0), COLUMN()-1), 0)} -> 691853.06 | J38: {=IFERROR(1*INDEX('Profit & Loss'!$1:$996, MATCH("Reparto a Propietarios*", 'Profit & Loss'!$B:$B, 0), COLUMN()-1), 0)} -> 690944.55 | K38: {=IFERROR(1*INDEX('Profit & Loss'!$1:$996, MATCH("Reparto a Propietarios*", 'Profit & Loss'!$B:$B, 0), COLUMN()-1), 0)} -> 732679.36 | ... BK38: {=IFERROR(1*INDEX('Profit & Loss'!$1:$996, MATCH("Reparto a Propietarios*", 'Profit & Loss'!$B:$B, 0), COLUMN()-1), 0)} -> 679127.35
A39: Convenio Limpieza & Mantenimiento | D39: {=IFERROR(1*INDEX('Profit & Loss'!$1:$996, MATCH("Convenio Limpieza*", 'Profit & Loss'!$B:$B, 0), COLUMN()-1), 0)} -> 0 | E39: {=IFERROR(1*INDEX('Profit & Loss'!$1:$996, MATCH("Convenio Limpieza*", 'Profit & Loss'!$B:$B, 0), COLUMN()-1), 0)} -> 83334.296 | F39: {=IFERROR(1*INDEX('Profit & Loss'!$1:$996, MATCH("Convenio Limpieza*", 'Profit & Loss'!$B:$B, 0), COLUMN()-1), 0)} -> 87218.749 | G39: {=IFERROR(1*INDEX('Profit & Loss'!$1:$996, MATCH("Convenio Limpieza*", 'Profit & Loss'!$B:$B, 0), COLUMN()-1), 0)} -> 88812.668 | H39: {=IFERROR(1*INDEX('Profit & Loss'!$1:$996, MATCH("Convenio Limpieza*", 'Profit & Loss'!$B:$B, 0), COLUMN()-1), 0)} -> 84386.526 | I39: {=IFERROR(1*INDEX('Profit & Loss'!$1:$996, MATCH("Convenio Limpieza*", 'Profit & Loss'!$B:$B, 0), COLUMN()-1), 0)} -> 86388.427 | J39: {=IFERROR(1*INDEX('Profit & Loss'!$1:$996, MATCH("Convenio Limpieza*", 'Profit & Loss'!$B:$B, 0), COLUMN()-1), 0)} -> 86237.485 | K39: {=IFERROR(1*INDEX('Profit & Loss'!$1:$996, MATCH("Convenio Limpieza*", 'Profit & Loss'!$B:$B, 0), COLUMN()-1), 0)} -> 90824.657 | ... BK39: {=IFERROR(1*INDEX('Profit & Loss'!$1:$996, MATCH("Convenio Limpieza*", 'Profit & Loss'!$B:$B, 0), COLUMN()-1), 0)} -> 82651.794
A40: Gastos Operativos | D40: {=IFERROR(1*INDEX('Profit & Loss'!$1:$996, MATCH("Gastos Operativos*", 'Profit & Loss'!$A:$A, 0), COLUMN()-1), 0)} -> 0 | E40: {=IFERROR(1*INDEX('Profit & Loss'!$1:$996, MATCH("Gastos Operativos*", 'Profit & Loss'!$A:$A, 0), COLUMN()-1), 0)} -> 107990 | F40: {=IFERROR(1*INDEX('Profit & Loss'!$1:$996, MATCH("Gastos Operativos*", 'Profit & Loss'!$A:$A, 0), COLUMN()-1), 0)} -> 107990 | G40: {=IFERROR(1*INDEX('Profit & Loss'!$1:$996, MATCH("Gastos Operativos*", 'Profit & Loss'!$A:$A, 0), COLUMN()-1), 0)} -> 107990 | H40: {=IFERROR(1*INDEX('Profit & Loss'!$1:$996, MATCH("Gastos Operativos*", 'Profit & Loss'!$A:$A, 0), COLUMN()-1), 0)} -> 107990 | I40: {=IFERROR(1*INDEX('Profit & Loss'!$1:$996, MATCH("Gastos Operativos*", 'Profit & Loss'!$A:$A, 0), COLUMN()-1), 0)} -> 107990 | J40: {=IFERROR(1*INDEX('Profit & Loss'!$1:$996, MATCH("Gastos Operativos*", 'Profit & Loss'!$A:$A, 0), COLUMN()-1), 0)} -> 107990 | K40: {=IFERROR(1*INDEX('Profit & Loss'!$1:$996, MATCH("Gastos Operativos*", 'Profit & Loss'!$A:$A, 0), COLUMN()-1), 0)} -> 107990 | ... BK40: {=IFERROR(1*INDEX('Profit & Loss'!$1:$996, MATCH("Gastos Operativos*", 'Profit & Loss'!$A:$A, 0), COLUMN()-1), 0)} -> 128558.69
A41: Comisión Booking.com | D41: =(N(C30) * 0.5 + N(B30) * 0.5) * $B$25 / (1 - $B$9) * $B$9 -> 0 | E41: =(N(D30) * 0.5 + N(C30) * 0.5) * $B$25 / (1 - $B$9) * $B$9 -> 20490.361 | F41: =(N(E30) * 0.5 + N(D30) * 0.5) * $B$25 / (1 - $B$9) * $B$9 -> 41935.836 | G41: =(N(F30) * 0.5 + N(E30) * 0.5) * $B$25 / (1 - $B$9) * $B$9 -> 43282.866 | H41: =(N(G30) * 0.5 + N(F30) * 0.5) * $B$25 / (1 - $B$9) * $B$9 -> 42586.475 | I41: =(N(H30) * 0.5 + N(G30) * 0.5) * $B$25 / (1 - $B$9) * $B$9 -> 41990.399 | J41: =(N(I30) * 0.5 + N(H30) * 0.5) * $B$25 / (1 - $B$9) * $B$9 -> 42445.515 | K41: =(N(J30) * 0.5 + N(I30) * 0.5) * $B$25 / (1 - $B$9) * $B$9 -> 43536.302 | ... BK41: =(N(BJ30) * 0.5 + N(BI30) * 0.5) * $B$25 / (1 - $B$9) * $B$9 -> 37090.134
A42: ISR Provisional | D42: {=MAX(0, IFERROR(1*INDEX('Profit & Loss'!$1:$996, MATCH("UT. Operativa*", 'Profit & Loss'!$A:$A, 0), COLUMN()-1), 0)) * $B$11} -> 0 | E42: {=MAX(0, IFERROR(1*INDEX('Profit & Loss'!$1:$996, MATCH("UT. Operativa*", 'Profit & Loss'!$A:$A, 0), COLUMN()-1), 0)) * $B$11} -> 43949.692 | F42: {=MAX(0, IFERROR(1*INDEX('Profit & Loss'!$1:$996, MATCH("UT. Operativa*", 'Profit & Loss'!$A:$A, 0), COLUMN()-1), 0)) * $B$11} -> 46143.83 | G42: {=MAX(0, IFERROR(1*INDEX('Profit & Loss'!$1:$996, MATCH("UT. Operativa*", 'Profit & Loss'!$A:$A, 0), COLUMN()-1), 0)) * $B$11} -> 46976.792 | H42: {=MAX(0, IFERROR(1*INDEX('Profit & Loss'!$1:$996, MATCH("UT. Operativa*", 'Profit & Loss'!$A:$A, 0), COLUMN()-1), 0)) * $B$11} -> 44182.953 | I42: {=MAX(0, IFERROR(1*INDEX('Profit & Loss'!$1:$996, MATCH("UT. Operativa*", 'Profit & Loss'!$A:$A, 0), COLUMN()-1), 0)) * $B$11} -> 45253.341 | J42: {=MAX(0, IFERROR(1*INDEX('Profit & Loss'!$1:$996, MATCH("UT. Operativa*", 'Profit & Loss'!$A:$A, 0), COLUMN()-1), 0)) * $B$11} -> 45027.566 | K42: {=MAX(0, IFERROR(1*INDEX('Profit & Loss'!$1:$996, MATCH("UT. Operativa*", 'Profit & Loss'!$A:$A, 0), COLUMN()-1), 0)) * $B$11} -> 47651.4 | ... BK42: {=MAX(0, IFERROR(1*INDEX('Profit & Loss'!$1:$996, MATCH("UT. Operativa*", 'Profit & Loss'!$A:$A, 0), COLUMN()-1), 0)) * $B$11} -> 30564.176
A43: Total Salidas de Efectivo Operativas | D43: =SUM(D38:D42) -> 0 | E43: =SUM(E38:E42) -> 918352.8 | F43: =SUM(F38:F42) -> 981310.7 | G43: =SUM(G38:G42) -> 999848.84 | H43: =SUM(H38:H42) -> 952536.44 | I43: =SUM(I38:I42) -> 973475.22 | J43: =SUM(J38:J42) -> 972645.12 | K43: =SUM(K38:K42) -> 1022681.7 | ... BK43: =SUM(BK38:BK42) -> 957992.14
A45: BLOQUE 3: FLUJO OPERATIVO NETO
A46: Flujo Operativo (Directo) | D46: =D35 - D43 -> 974020.63 | E46: =E35 - E43 -> 171833.76 | F46: =F35 - F43 -> 116448.59 | G46: =G35 - G43 -> 63573.018 | H46: =H35 - H43 -> 124817.24 | I46: =I35 - I43 -> 115349.64 | J46: =J35 - J43 -> 156880.92 | K46: =K35 - K43 -> 75909.743 | ... BK46: =BK35 - BK43 -> -188027.52
A47: EBITDA | D47: {=IFERROR(1*INDEX('Profit & Loss'!$1:$996, MATCH("EBITDA*", 'Profit & Loss'!$A:$A, 0), COLUMN()), 0)} -> 146498.97 | E47: {=IFERROR(1*INDEX('Profit & Loss'!$1:$996, MATCH("EBITDA*", 'Profit & Loss'!$A:$A, 0), COLUMN()), 0)} -> 153812.77 | F47: {=IFERROR(1*INDEX('Profit & Loss'!$1:$996, MATCH("EBITDA*", 'Profit & Loss'!$A:$A, 0), COLUMN()), 0)} -> 156589.31 | G47: {=IFERROR(1*INDEX('Profit & Loss'!$1:$996, MATCH("EBITDA*", 'Profit & Loss'!$A:$A, 0), COLUMN()), 0)} -> 147276.51 | H47: {=IFERROR(1*INDEX('Profit & Loss'!$1:$996, MATCH("EBITDA*", 'Profit & Loss'!$A:$A, 0), COLUMN()), 0)} -> 150844.47 | I47: {=IFERROR(1*INDEX('Profit & Loss'!$1:$996, MATCH("EBITDA*", 'Profit & Loss'!$A:$A, 0), COLUMN()), 0)} -> 150091.89 | J47: {=IFERROR(1*INDEX('Profit & Loss'!$1:$996, MATCH("EBITDA*", 'Profit & Loss'!$A:$A, 0), COLUMN()), 0)} -> 158838 | K47: {=IFERROR(1*INDEX('Profit & Loss'!$1:$996, MATCH("EBITDA*", 'Profit & Loss'!$A:$A, 0), COLUMN()), 0)} -> 157351.66 | ... BK47: {=IFERROR(1*INDEX('Profit & Loss'!$1:$996, MATCH("EBITDA*", 'Profit & Loss'!$A:$A, 0), COLUMN()), 0)} -> 87492.419
A48: Variación en Capital de Trabajo | D48: =D46 - D47 -> 827521.65 | E48: =E46 - E47 -> 18020.998 | F48: =F46 - F47 -> -40140.722 | G48: =G46 - G47 -> -83703.491 | H48: =H46 - H47 -> -26027.225 | I48: =I46 - I47 -> -34742.243 | J48: =J46 - J47 -> -1957.0801 | K48: =K46 - K47 -> -81441.921 | ... BK48: =BK46 - BK47 -> -275519.94
A49: Flujo Operativo (Indirecto) | D49: =D47 + D48 -> 974020.63 | E49: =E47 + E48 -> 171833.76 | F49: =F47 + F48 -> 116448.59 | G49: =G47 + G48 -> 63573.018 | H49: =H47 + H48 -> 124817.24 | I49: =I47 + I48 -> 115349.64 | J49: =J47 + J48 -> 156880.92 | K49: =K47 + K48 -> 75909.743 | ... BK49: =BK47 + BK48 -> -188027.52
A50: Check (Directo = Indirecto) | D50: =ROUND(D46 - D49, 2) = 0 -> TRUE | E50: =ROUND(E46 - E49, 2) = 0 -> TRUE | F50: =ROUND(F46 - F49, 2) = 0 -> TRUE | G50: =ROUND(G46 - G49, 2) = 0 -> TRUE | H50: =ROUND(H46 - H49, 2) = 0 -> TRUE | I50: =ROUND(I46 - I49, 2) = 0 -> TRUE | J50: =ROUND(J46 - J49, 2) = 0 -> TRUE | K50: =ROUND(K46 - K49, 2) = 0 -> TRUE | ... BK50: =ROUND(BK46 - BK49, 2) = 0 -> TRUE
A52: BLOQUE 4: FLUJO DE INVERSIÓN (CAPEX)
A53: Inversión Rubro 1 | D53: =-'Paso 5 Resumen Desglose de Inve'!$D$25 * IF(COLUMN()=4, $C$19, IF(COLUMN()=5, $D$19, IF(COLUMN()=6, $E$19, 0))) -> -575958.55 | E53: =-'Paso 5 Resumen Desglose de Inve'!$D$25 * IF(COLUMN()=4, $C$19, IF(COLUMN()=5, $D$19, IF(COLUMN()=6, $E$19, 0))) -> -345575.13 | F53: =-'Paso 5 Resumen Desglose de Inve'!$D$25 * IF(COLUMN()=4, $C$19, IF(COLUMN()=5, $D$19, IF(COLUMN()=6, $E$19, 0))) -> -230383.42 | G53: =-'Paso 5 Resumen Desglose de Inve'!$D$25 * IF(COLUMN()=4, $C$19, IF(COLUMN()=5, $D$19, IF(COLUMN()=6, $E$19, 0))) -> 0 | H53: =-'Paso 5 Resumen Desglose de Inve'!$D$25 * IF(COLUMN()=4, $C$19, IF(COLUMN()=5, $D$19, IF(COLUMN()=6, $E$19, 0))) -> 0 | I53: =-'Paso 5 Resumen Desglose de Inve'!$D$25 * IF(COLUMN()=4, $C$19, IF(COLUMN()=5, $D$19, IF(COLUMN()=6, $E$19, 0))) -> 0 | J53: =-'Paso 5 Resumen Desglose de Inve'!$D$25 * IF(COLUMN()=4, $C$19, IF(COLUMN()=5, $D$19, IF(COLUMN()=6, $E$19, 0))) -> 0 | K53: =-'Paso 5 Resumen Desglose de Inve'!$D$25 * IF(COLUMN()=4, $C$19, IF(COLUMN()=5, $D$19, IF(COLUMN()=6, $E$19, 0))) -> 0 | ... BK53: =-'Paso 5 Resumen Desglose de Inve'!$D$25 * IF(COLUMN()=4, $C$19, IF(COLUMN()=5, $D$19, IF(COLUMN()=6, $E$19, 0))) -> 0
A54: Inversión Rubro 2 | D54: =-'Paso 5 Resumen Desglose de Inve'!$D$35 * IF(COLUMN()=4, $C$19, IF(COLUMN()=5, $D$19, IF(COLUMN()=6, $E$19, 0))) -> -142694.38 | E54: =-'Paso 5 Resumen Desglose de Inve'!$D$35 * IF(COLUMN()=4, $C$19, IF(COLUMN()=5, $D$19, IF(COLUMN()=6, $E$19, 0))) -> -85616.629 | F54: =-'Paso 5 Resumen Desglose de Inve'!$D$35 * IF(COLUMN()=4, $C$19, IF(COLUMN()=5, $D$19, IF(COLUMN()=6, $E$19, 0))) -> -57077.753 | G54: =-'Paso 5 Resumen Desglose de Inve'!$D$35 * IF(COLUMN()=4, $C$19, IF(COLUMN()=5, $D$19, IF(COLUMN()=6, $E$19, 0))) -> 0 | H54: =-'Paso 5 Resumen Desglose de Inve'!$D$35 * IF(COLUMN()=4, $C$19, IF(COLUMN()=5, $D$19, IF(COLUMN()=6, $E$19, 0))) -> 0 | I54: =-'Paso 5 Resumen Desglose de Inve'!$D$35 * IF(COLUMN()=4, $C$19, IF(COLUMN()=5, $D$19, IF(COLUMN()=6, $E$19, 0))) -> 0 | J54: =-'Paso 5 Resumen Desglose de Inve'!$D$35 * IF(COLUMN()=4, $C$19, IF(COLUMN()=5, $D$19, IF(COLUMN()=6, $E$19, 0))) -> 0 | K54: =-'Paso 5 Resumen Desglose de Inve'!$D$35 * IF(COLUMN()=4, $C$19, IF(COLUMN()=5, $D$19, IF(COLUMN()=6, $E$19, 0))) -> 0 | ... BK54: =-'Paso 5 Resumen Desglose de Inve'!$D$35 * IF(COLUMN()=4, $C$19, IF(COLUMN()=5, $D$19, IF(COLUMN()=6, $E$19, 0))) -> 0
A55: Inversión Rubro 3 | D55: =-'Paso 5 Resumen Desglose de Inve'!$D$50 * IF(COLUMN()=4, $C$19, IF(COLUMN()=5, $D$19, IF(COLUMN()=6, $E$19, 0))) -> -209585.5 | E55: =-'Paso 5 Resumen Desglose de Inve'!$D$50 * IF(COLUMN()=4, $C$19, IF(COLUMN()=5, $D$19, IF(COLUMN()=6, $E$19, 0))) -> -125751.3 | F55: =-'Paso 5 Resumen Desglose de Inve'!$D$50 * IF(COLUMN()=4, $C$19, IF(COLUMN()=5, $D$19, IF(COLUMN()=6, $E$19, 0))) -> -83834.2 | G55: =-'Paso 5 Resumen Desglose de Inve'!$D$50 * IF(COLUMN()=4, $C$19, IF(COLUMN()=5, $D$19, IF(COLUMN()=6, $E$19, 0))) -> 0 | H55: =-'Paso 5 Resumen Desglose de Inve'!$D$50 * IF(COLUMN()=4, $C$19, IF(COLUMN()=5, $D$19, IF(COLUMN()=6, $E$19, 0))) -> 0 | I55: =-'Paso 5 Resumen Desglose de Inve'!$D$50 * IF(COLUMN()=4, $C$19, IF(COLUMN()=5, $D$19, IF(COLUMN()=6, $E$19, 0))) -> 0 | J55: =-'Paso 5 Resumen Desglose de Inve'!$D$50 * IF(COLUMN()=4, $C$19, IF(COLUMN()=5, $D$19, IF(COLUMN()=6, $E$19, 0))) -> 0 | K55: =-'Paso 5 Resumen Desglose de Inve'!$D$50 * IF(COLUMN()=4, $C$19, IF(COLUMN()=5, $D$19, IF(COLUMN()=6, $E$19, 0))) -> 0 | ... BK55: =-'Paso 5 Resumen Desglose de Inve'!$D$50 * IF(COLUMN()=4, $C$19, IF(COLUMN()=5, $D$19, IF(COLUMN()=6, $E$19, 0))) -> 0
A56: Inversión Rubro 4 | D56: =-'Paso 5 Resumen Desglose de Inve'!$D$59 * IF(COLUMN()=4, $C$19, IF(COLUMN()=5, $D$19, IF(COLUMN()=6, $E$19, 0))) -> -291256.49 | E56: =-'Paso 5 Resumen Desglose de Inve'!$D$59 * IF(COLUMN()=4, $C$19, IF(COLUMN()=5, $D$19, IF(COLUMN()=6, $E$19, 0))) -> -174753.89 | F56: =-'Paso 5 Resumen Desglose de Inve'!$D$59 * IF(COLUMN()=4, $C$19, IF(COLUMN()=5, $D$19, IF(COLUMN()=6, $E$19, 0))) -> -116502.6 | G56: =-'Paso 5 Resumen Desglose de Inve'!$D$59 * IF(COLUMN()=4, $C$19, IF(COLUMN()=5, $D$19, IF(COLUMN()=6, $E$19, 0))) -> 0 | H56: =-'Paso 5 Resumen Desglose de Inve'!$D$59 * IF(COLUMN()=4, $C$19, IF(COLUMN()=5, $D$19, IF(COLUMN()=6, $E$19, 0))) -> 0 | I56: =-'Paso 5 Resumen Desglose de Inve'!$D$59 * IF(COLUMN()=4, $C$19, IF(COLUMN()=5, $D$19, IF(COLUMN()=6, $E$19, 0))) -> 0 | J56: =-'Paso 5 Resumen Desglose de Inve'!$D$59 * IF(COLUMN()=4, $C$19, IF(COLUMN()=5, $D$19, IF(COLUMN()=6, $E$19, 0))) -> 0 | K56: =-'Paso 5 Resumen Desglose de Inve'!$D$59 * IF(COLUMN()=4, $C$19, IF(COLUMN()=5, $D$19, IF(COLUMN()=6, $E$19, 0))) -> 0 | ... BK56: =-'Paso 5 Resumen Desglose de Inve'!$D$59 * IF(COLUMN()=4, $C$19, IF(COLUMN()=5, $D$19, IF(COLUMN()=6, $E$19, 0))) -> 0
A57: Inversión Rubro 5 | D57: =-'Paso 5 Resumen Desglose de Inve'!$D$68 * IF(COLUMN()=4, $C$19, IF(COLUMN()=5, $D$19, IF(COLUMN()=6, $E$19, 0))) -> -367190 | E57: =-'Paso 5 Resumen Desglose de Inve'!$D$68 * IF(COLUMN()=4, $C$19, IF(COLUMN()=5, $D$19, IF(COLUMN()=6, $E$19, 0))) -> -220314 | F57: =-'Paso 5 Resumen Desglose de Inve'!$D$68 * IF(COLUMN()=4, $C$19, IF(COLUMN()=5, $D$19, IF(COLUMN()=6, $E$19, 0))) -> -146876 | G57: =-'Paso 5 Resumen Desglose de Inve'!$D$68 * IF(COLUMN()=4, $C$19, IF(COLUMN()=5, $D$19, IF(COLUMN()=6, $E$19, 0))) -> 0 | H57: =-'Paso 5 Resumen Desglose de Inve'!$D$68 * IF(COLUMN()=4, $C$19, IF(COLUMN()=5, $D$19, IF(COLUMN()=6, $E$19, 0))) -> 0 | I57: =-'Paso 5 Resumen Desglose de Inve'!$D$68 * IF(COLUMN()=4, $C$19, IF(COLUMN()=5, $D$19, IF(COLUMN()=6, $E$19, 0))) -> 0 | J57: =-'Paso 5 Resumen Desglose de Inve'!$D$68 * IF(COLUMN()=4, $C$19, IF(COLUMN()=5, $D$19, IF(COLUMN()=6, $E$19, 0))) -> 0 | K57: =-'Paso 5 Resumen Desglose de Inve'!$D$68 * IF(COLUMN()=4, $C$19, IF(COLUMN()=5, $D$19, IF(COLUMN()=6, $E$19, 0))) -> 0 | ... BK57: =-'Paso 5 Resumen Desglose de Inve'!$D$68 * IF(COLUMN()=4, $C$19, IF(COLUMN()=5, $D$19, IF(COLUMN()=6, $E$19, 0))) -> 0
A58: CapEx de Reposición | D58: {=-IFERROR(1*INDEX('Profit & Loss'!$1:$996, MATCH("Ingreso Del Mar*", 'Profit & Loss'!$B:$B, 0), COLUMN()), 0) * 0.02 / 12} -> 0 | E58: {=-IFERROR(1*INDEX('Profit & Loss'!$1:$996, MATCH("Ingreso Del Mar*", 'Profit & Loss'!$B:$B, 0), COLUMN()), 0) * 0.02 / 12} -> 0 | F58: {=-IFERROR(1*INDEX('Profit & Loss'!$1:$996, MATCH("Ingreso Del Mar*", 'Profit & Loss'!$B:$B, 0), COLUMN()), 0) * 0.02 / 12} -> 0 | G58: {=-IFERROR(1*INDEX('Profit & Loss'!$1:$996, MATCH("Ingreso Del Mar*", 'Profit & Loss'!$B:$B, 0), COLUMN()), 0) * 0.02 / 12} -> 0 | H58: {=-IFERROR(1*INDEX('Profit & Loss'!$1:$996, MATCH("Ingreso Del Mar*", 'Profit & Loss'!$B:$B, 0), COLUMN()), 0) * 0.02 / 12} -> 0 | I58: {=-IFERROR(1*INDEX('Profit & Loss'!$1:$996, MATCH("Ingreso Del Mar*", 'Profit & Loss'!$B:$B, 0), COLUMN()), 0) * 0.02 / 12} -> 0 | J58: {=-IFERROR(1*INDEX('Profit & Loss'!$1:$996, MATCH("Ingreso Del Mar*", 'Profit & Loss'!$B:$B, 0), COLUMN()), 0) * 0.02 / 12} -> 0 | K58: {=-IFERROR(1*INDEX('Profit & Loss'!$1:$996, MATCH("Ingreso Del Mar*", 'Profit & Loss'!$B:$B, 0), COLUMN()), 0) * 0.02 / 12} -> 0 | ... BK58: {=-IFERROR(1*INDEX('Profit & Loss'!$1:$996, MATCH("Ingreso Del Mar*", 'Profit & Loss'!$B:$B, 0), COLUMN()), 0) * 0.02 / 12} -> 0
A59: Total Flujo de Inversión | D59: =SUM(D53:D58) -> -1586684.9 | E59: =SUM(E53:E58) -> -952010.95 | F59: =SUM(F53:F58) -> -634673.97 | G59: =SUM(G53:G58) -> 0 | H59: =SUM(H53:H58) -> 0 | I59: =SUM(I53:I58) -> 0 | J59: =SUM(J53:J58) -> 0 | K59: =SUM(K53:K58) -> 0 | ... BK59: =SUM(BK53:BK58) -> 0
A61: BLOQUE 5: FLUJO DE FINANCIAMIENTO
A62: Saldo Inicial Línea de Crédito | D62: =N(C66) -> 0 | E62: =N(D66) -> 500000 | F62: =N(E66) -> 500000 | G62: =N(F66) -> 500000 | H62: =N(G66) -> 500000 | I62: =N(H66) -> 500000 | J62: =N(I66) -> 500000 | K62: =N(J66) -> 500000 | ... BK62: =N(BJ66) -> 0
A63: Disposiciones | D63: =MIN($B$13 - D62, MAX(0, $B$15 - D72)) -> 500000 | E63: =MIN($B$13 - E62, MAX(0, $B$15 - E72)) -> 0 | F63: =MIN($B$13 - F62, MAX(0, $B$15 - F72)) -> 0 | G63: =MIN($B$13 - G62, MAX(0, $B$15 - G72)) -> 0 | H63: =MIN($B$13 - H62, MAX(0, $B$15 - H72)) -> 0 | I63: =MIN($B$13 - I62, MAX(0, $B$15 - I72)) -> 0 | J63: =MIN($B$13 - J62, MAX(0, $B$15 - J72)) -> 0 | K63: =MIN($B$13 - K62, MAX(0, $B$15 - K72)) -> 0 | ... BK63: =MIN($B$13 - BK62, MAX(0, $B$15 - BK72)) -> 0
A64: Pago Intereses | D64: =D62 * $B$14 / 12 -> 0 | E64: =E62 * $B$14 / 12 -> 6250 | F64: =F62 * $B$14 / 12 -> 6250 | G64: =G62 * $B$14 / 12 -> 6250 | H64: =H62 * $B$14 / 12 -> 6250 | I64: =I62 * $B$14 / 12 -> 6250 | J64: =J62 * $B$14 / 12 -> 6250 | K64: =K62 * $B$14 / 12 -> 6250 | ... BK64: =BK62 * $B$14 / 12 -> 0
A65: Pago Principal | D65: =MIN(D62, MAX(0, D72 - $B$15)) -> 0 | E65: =MIN(E62, MAX(0, E72 - $B$15)) -> 0 | F65: =MIN(F62, MAX(0, F72 - $B$15)) -> 0 | G65: =MIN(G62, MAX(0, G72 - $B$15)) -> 0 | H65: =MIN(H62, MAX(0, H72 - $B$15)) -> 0 | I65: =MIN(I62, MAX(0, I72 - $B$15)) -> 0 | J65: =MIN(J62, MAX(0, J72 - $B$15)) -> 0 | K65: =MIN(K62, MAX(0, K72 - $B$15)) -> 0 | ... BK65: =MIN(BK62, MAX(0, BK72 - $B$15)) -> 0
A66: Saldo Final Línea de Crédito | D66: =D62 + D63 - D65 -> 500000 | E66: =E62 + E63 - E65 -> 500000 | F66: =F62 + F63 - F65 -> 500000 | G66: =G62 + G63 - G65 -> 500000 | H66: =H62 + H63 - H65 -> 500000 | I66: =I62 + I63 - I65 -> 500000 | J66: =J62 + J63 - J65 -> 500000 | K66: =K62 + K63 - K65 -> 500000 | ... BK66: =BK62 + BK63 - BK65 -> 0
A67: Total Flujo de Financiamiento | D67: =D63 - D64 - D65 -> 500000 | E67: =E63 - E64 - E65 -> -6250 | F67: =F63 - F64 - F65 -> -6250 | G67: =G63 - G64 - G65 -> -6250 | H67: =H63 - H64 - H65 -> -6250 | I67: =I63 - I64 - I65 -> -6250 | J67: =J63 - J64 - J65 -> -6250 | K67: =K63 - K64 - K65 -> -6250 | ... BK67: =BK63 - BK64 - BK65 -> 0
A69: BLOQUE 6: POSICIÓN DE CAJA
A70: Caja Inicial | D70: =N(C74) -> 0 | E70: =N(D74) -> -112664.3 | F70: =N(E74) -> -899091.49 | G70: =N(F74) -> -1423566.9 | H70: =N(G74) -> -1366243.9 | I70: =N(H74) -> -1247676.6 | J70: =N(I74) -> -1138577 | K70: =N(J74) -> -987946.05 | ... BK70: =N(BJ74) -> 2576167.8
A71: Flujo Operativo + Inversión | D71: =D46 + D59 -> -612664.3 | E71: =E46 + E59 -> -780177.19 | F71: =F46 + F59 -> -518225.38 | G71: =G46 + G59 -> 63573.018 | H71: =H46 + H59 -> 124817.24 | I71: =I46 + I59 -> 115349.64 | J71: =J46 + J59 -> 156880.92 | K71: =K46 + K59 -> 75909.743 | ... BK71: =BK46 + BK59 -> -188027.52
A72: Caja antes de Financiamiento | D72: =D70 + D71 - D64 -> -612664.3 | E72: =E70 + E71 - E64 -> -899091.49 | F72: =F70 + F71 - F64 -> -1423566.9 | G72: =G70 + G71 - G64 -> -1366243.9 | H72: =H70 + H71 - H64 -> -1247676.6 | I72: =I70 + I71 - I64 -> -1138577 | J72: =J70 + J71 - J64 -> -987946.05 | K72: =K70 + K71 - K64 -> -918286.3 | ... BK72: =BK70 + BK71 - BK64 -> 2388140.3
A73: Flujo de Financiamiento | D73: =D67 -> 500000 | E73: =E67 -> -6250 | F73: =F67 -> -6250 | G73: =G67 -> -6250 | H73: =H67 -> -6250 | I73: =I67 -> -6250 | J73: =J67 -> -6250 | K73: =K67 -> -6250 | ... BK73: =BK67 -> 0
A74: Caja Final | D74: =D70 + D71 + D67 -> -112664.3 | E74: =E70 + E71 + E67 -> -899091.49 | F74: =F70 + F71 + F67 -> -1423566.9 | G74: =G70 + G71 + G67 -> -1366243.9 | H74: =H70 + H71 + H67 -> -1247676.6 | I74: =I70 + I71 + I67 -> -1138577 | J74: =J70 + J71 + J67 -> -987946.05 | K74: =K70 + K71 + K67 -> -918286.3 | ... BK74: =BK70 + BK71 + BK67 -> 2388140.3
A75: Saldo Mínimo Deseado | D75: =$B$15 -> 200000 | E75: =$B$15 -> 200000 | F75: =$B$15 -> 200000 | G75: =$B$15 -> 200000 | H75: =$B$15 -> 200000 | I75: =$B$15 -> 200000 | J75: =$B$15 -> 200000 | K75: =$B$15 -> 200000 | ... BK75: =$B$15 -> 200000
A76: Máximo Déficit Acumulado | B76: =MIN(0, MIN(D72:BK72)) -> -1423566.9
A77: Mes del Pico | B77: {=IF(B76=0, "-", INDEX(D3:BK3, 1, MATCH(B76, D72:BK72, 0)))} -> 45717
A78: Capital Total Requerido | B78: =-B76 -> 1423566.9
A80: BLOQUE 7: DINERO PROPIO VS TERCEROS
A81: Reparto Devengado (Acumulado) | D81: {=N(C81) + IFERROR(1*INDEX('Profit & Loss'!$1:$996, MATCH("Reparto a Propietarios*", 'Profit & Loss'!$B:$B, 0), COLUMN()), 0)} -> 662588.45 | E81: {=N(D81) + IFERROR(1*INDEX('Profit & Loss'!$1:$996, MATCH("Reparto a Propietarios*", 'Profit & Loss'!$B:$B, 0), COLUMN()), 0)} -> 1360610.7 | F81: {=N(E81) + IFERROR(1*INDEX('Profit & Loss'!$1:$996, MATCH("Reparto a Propietarios*", 'Profit & Loss'!$B:$B, 0), COLUMN()), 0)} -> 2073397.3 | G81: {=N(F81) + IFERROR(1*INDEX('Profit & Loss'!$1:$996, MATCH("Reparto a Propietarios*", 'Profit & Loss'!$B:$B, 0), COLUMN()), 0)} -> 2746787.7 | H81: {=N(G81) + IFERROR(1*INDEX('Profit & Loss'!$1:$996, MATCH("Reparto a Propietarios*", 'Profit & Loss'!$B:$B, 0), COLUMN()), 0)} -> 3438640.8 | I81: {=N(H81) + IFERROR(1*INDEX('Profit & Loss'!$1:$996, MATCH("Reparto a Propietarios*", 'Profit & Loss'!$B:$B, 0), COLUMN()), 0)} -> 4129585.4 | J81: {=N(I81) + IFERROR(1*INDEX('Profit & Loss'!$1:$996, MATCH("Reparto a Propietarios*", 'Profit & Loss'!$B:$B, 0), COLUMN()), 0)} -> 4862264.7 | K81: {=N(J81) + IFERROR(1*INDEX('Profit & Loss'!$1:$996, MATCH("Reparto a Propietarios*", 'Profit & Loss'!$B:$B, 0), COLUMN()), 0)} -> 5590708.8 | ... BK81: {=N(BJ81) + IFERROR(1*INDEX('Profit & Loss'!$1:$996, MATCH("Reparto a Propietarios*", 'Profit & Loss'!$B:$B, 0), COLUMN()), 0)} -> 39527097
A82: Reparto Pagado (Acumulado) | D82: =N(C82) + D38 -> 0 | E82: =N(D82) + E38 -> 662588.45 | F82: =N(E82) + F38 -> 1360610.7 | G82: =N(F82) + G38 -> 2073397.3 | H82: =N(G82) + H38 -> 2746787.7 | I82: =N(H82) + I38 -> 3438640.8 | J82: =N(I82) + J38 -> 4129585.4 | K82: =N(J82) + K38 -> 4862264.7 | ... BK82: =N(BJ82) + BK38 -> 38910889
A83: Flotante de Propietarios (Cuentas por Pagar) | D83: =D81 - D82 -> 662588.45 | E83: =E81 - E82 -> 698022.29 | F83: =F81 - F82 -> 712786.52 | G83: =G81 - G82 -> 673390.49 | H83: =H81 - H82 -> 691853.06 | I83: =I81 - I82 -> 690944.55 | J83: =J81 - J82 -> 732679.36 | K83: =K81 - K82 -> 728444.13 | ... BK83: =BK81 - BK82 -> 616207.77
A84: Caja Operativa Propia | D84: =D74 - D83 -> -775252.75 | E84: =E74 - E83 -> -1597113.8 | F84: =F74 - F83 -> -2136353.4 | G84: =G74 - G83 -> -2039634.3 | H84: =H74 - H83 -> -1939529.7 | I84: =I74 - I83 -> -1829521.5 | J84: =J74 - J83 -> -1720625.4 | K84: =K74 - K83 -> -1646730.4 | ... BK84: =BK74 - BK83 -> 1771932.5
A86: BLOQUE 8: KPIs DE LIQUIDEZ
A87: DSCR (Debt Service Coverage Ratio) | D87: =IF(D65+D64>0, D46 / (D65+D64), "N/A") -> N/A | E87: =IF(E65+E64>0, E46 / (E65+E64), "N/A") -> 27.493402 | F87: =IF(F65+F64>0, F46 / (F65+F64), "N/A") -> 18.631774 | G87: =IF(G65+G64>0, G46 / (G65+G64), "N/A") -> 10.171683 | H87: =IF(H65+H64>0, H46 / (H65+H64), "N/A") -> 19.970759 | I87: =IF(I65+I64>0, I46 / (I65+I64), "N/A") -> 18.455943 | J87: =IF(J65+J64>0, J46 / (J65+J64), "N/A") -> 25.100947 | K87: =IF(K65+K64>0, K46 / (K65+K64), "N/A") -> 12.145559 | ... BK87: =IF(BK65+BK64>0, BK46 / (BK65+BK64), "N/A") -> N/A
A88: Meses de Runway | D88: =IF(D71<0, D70 / ABS(D71), "N/A") -> 0 | E88: =IF(E71<0, E70 / ABS(E71), "N/A") -> -0.1444086 | F88: =IF(F71<0, F70 / ABS(F71), "N/A") -> -1.734943 | G88: =IF(G71<0, G70 / ABS(G71), "N/A") -> N/A | H88: =IF(H71<0, H70 / ABS(H71), "N/A") -> N/A | I88: =IF(I71<0, I70 / ABS(I71), "N/A") -> N/A | J88: =IF(J71<0, J70 / ABS(J71), "N/A") -> N/A | K88: =IF(K71<0, K70 / ABS(K71), "N/A") -> N/A | ... BK88: =IF(BK71<0, BK70 / ABS(BK71), "N/A") -> 13.701014
A89: Flujo Promedio (L3M) | D89: =AVERAGE(B71:D71) -> -612664.3 | E89: =AVERAGE(C71:E71) -> -696420.74 | F89: =AVERAGE(D71:F71) -> -637022.29 | G89: =AVERAGE(E71:G71) -> -411609.85 | H89: =AVERAGE(F71:H71) -> -109945.04 | I89: =AVERAGE(G71:I71) -> 101246.63 | J89: =AVERAGE(H71:J71) -> 132349.27 | K89: =AVERAGE(I71:K71) -> 116046.77 | ... BK89: =AVERAGE(BI71:BK71) -> 22960.148
A91: BLOQUE 9: RODANTE DE 13 SEMANAS (Aprox)
A92: Semana | D92: S1 | E92: S2 | F92: S3 | G92: S4 | H92: S5 | I92: S6 | J92: S7 | K92: S8 | L92: S9 | M92: S10 | N92: S11 | O92: S12 | P92: S13
A93: Entradas | D93: =($D$35+$E$35+$F$35)/13 -> 243228.19 | E93: =($D$35+$E$35+$F$35)/13 -> 243228.19 | F93: =($D$35+$E$35+$F$35)/13 -> 243228.19 | G93: =($D$35+$E$35+$F$35)/13 -> 243228.19 | H93: =($D$35+$E$35+$F$35)/13 -> 243228.19 | I93: =($D$35+$E$35+$F$35)/13 -> 243228.19 | J93: =($D$35+$E$35+$F$35)/13 -> 243228.19 | K93: =($D$35+$E$35+$F$35)/13 -> 243228.19 | ... P93: =($D$35+$E$35+$F$35)/13 -> 243228.19
A94: Salidas | D94: =($D$43+$E$43+$F$43)/13 -> 146127.96 | E94: =($D$43+$E$43+$F$43)/13 -> 146127.96 | F94: =($D$43+$E$43+$F$43)/13 -> 146127.96 | G94: =($D$43+$E$43+$F$43)/13 -> 146127.96 | H94: =($D$43+$E$43+$F$43)/13 -> 146127.96 | I94: =($D$43+$E$43+$F$43)/13 -> 146127.96 | J94: =($D$43+$E$43+$F$43)/13 -> 146127.96 | K94: =($D$43+$E$43+$F$43)/13 -> 146127.96 | ... P94: =($D$43+$E$43+$F$43)/13 -> 146127.96
A95: Flujo Neto | D95: =D93 - D94 -> 97100.229 | E95: =E93 - E94 -> 97100.229 | F95: =F93 - F94 -> 97100.229 | G95: =G93 - G94 -> 97100.229 | H95: =H93 - H94 -> 97100.229 | I95: =I93 - I94 -> 97100.229 | J95: =J93 - J94 -> 97100.229 | K95: =K93 - K94 -> 97100.229 | ... P95: =P93 - P94 -> 97100.229
A96: Caja Final | D96: =IF(COLUMN()=4, $D$70 + D95, N(C96) + D95) -> 97100.229 | E96: =IF(COLUMN()=4, $D$70 + E95, N(D96) + E95) -> 194200.46 | F96: =IF(COLUMN()=4, $D$70 + F95, N(E96) + F95) -> 291300.69 | G96: =IF(COLUMN()=4, $D$70 + G95, N(F96) + G95) -> 388400.92 | H96: =IF(COLUMN()=4, $D$70 + H95, N(G96) + H95) -> 485501.14 | I96: =IF(COLUMN()=4, $D$70 + I95, N(H96) + I95) -> 582601.37 | J96: =IF(COLUMN()=4, $D$70 + J95, N(I96) + J95) -> 679701.6 | K96: =IF(COLUMN()=4, $D$70 + K95, N(J96) + K95) -> 776801.83 | ... P96: =IF(COLUMN()=4, $D$70 + P95, N(O96) + P95) -> 1262303
A98: BLOQUE 10: ESTRÉS DE LIQUIDEZ
A99: Escenario | D99: Base | E99: -10% Cobranza | F99: +10% Gastos | G99: Ambos
A100: Déficit Máximo | D100: =$B$76 -> -1423566.9 | E100: {=MIN(0, MIN(SCAN(0, D71:BK71 - D35:BK35*0.1, LAMBDA(a, v, a+v))))} -> -889195.85 | F100: {=MIN(0, MIN(SCAN(0, D71:BK71 - D43:BK43*0.1, LAMBDA(a, v, a+v))))} -> -616356.45 | G100: {=MIN(0, MIN(SCAN(0, D71:BK71 - D35:BK35*0.1 - D43:BK43*0.1, LAMBDA(a, v, a+v))))} -> -142754.05
A102: BLOQUE 11: REVISIONES
A103: Cuadre de Caja Final vs Flujos Acumulados | D103: =IF(ROUND(BK74 - (D70 + SUM(D71:BK71) + SUM(D67:BK67)), 2) = 0, "OK", "ERROR") -> OK
A104: Check Directo = Indirecto | D104: =IF(COUNTIF(D50:BK50, FALSE)=0, "OK", "ERROR") -> OK
A105: Caja Propia >= 0 | D105: =IF(MIN(D84:BK84)>=0, "OK", "ERROR") -> ERROR

Sheet Unit Economics
A1: UNIT ECONOMICS
A2: Métrica | B2: 1H | G2: 2H
B3: Año 1 | C3: Año 2 | D3: Año 3 | E3: Año 4 | F3: Año 5 | G3: Año 1 | H3: Año 2 | I3: Año 3 | J3: Año 4 | K3: Año 5
A4: BLOQUE A: Unit Economics por Tipo de Llave (Anualizado)
A5: Promedio de Unidades (Llaves) | B5: =AVERAGE(OFFSET('Profit & Loss'!$A$1, MATCH("({UO} | AT-AMP-02) - Analisis de Mercado [No. 1 - KIVA]", 'Profit & Loss'!$B:$B, 0), (COLUMN()-2)*12 + 3, 1, 12)) -> 24.016385 | C5: =AVERAGE(OFFSET('Profit & Loss'!$A$1, MATCH("({UO} | AT-AMP-02) - Analisis de Mercado [No. 1 - KIVA]", 'Profit & Loss'!$B:$B, 0), (COLUMN()-2)*12 + 3, 1, 12)) -> 22.575402 | D5: =AVERAGE(OFFSET('Profit & Loss'!$A$1, MATCH("({UO} | AT-AMP-02) - Analisis de Mercado [No. 1 - KIVA]", 'Profit & Loss'!$B:$B, 0), (COLUMN()-2)*12 + 3, 1, 12)) -> 21.220878 | E5: =AVERAGE(OFFSET('Profit & Loss'!$A$1, MATCH("({UO} | AT-AMP-02) - Analisis de Mercado [No. 1 - KIVA]", 'Profit & Loss'!$B:$B, 0), (COLUMN()-2)*12 + 3, 1, 12)) -> 19.944822 | F5: =AVERAGE(OFFSET('Profit & Loss'!$A$1, MATCH("({UO} | AT-AMP-02) - Analisis de Mercado [No. 1 - KIVA]", 'Profit & Loss'!$B:$B, 0), (COLUMN()-2)*12 + 3, 1, 12)) -> 18.74759 | G5: =AVERAGE(OFFSET('Profit & Loss'!$A$1, MATCH("({UO} | AT-AMP-02) - Analisis de Mercado [No. 2 - KIVA]", 'Profit & Loss'!$B:$B, 0), (COLUMN()-7)*12 + 3, 1, 12)) -> 14.779314 | H5: =AVERAGE(OFFSET('Profit & Loss'!$A$1, MATCH("({UO} | AT-AMP-02) - Analisis de Mercado [No. 2 - KIVA]", 'Profit & Loss'!$B:$B, 0), (COLUMN()-7)*12 + 3, 1, 12)) -> 13.892555 | I5: =AVERAGE(OFFSET('Profit & Loss'!$A$1, MATCH("({UO} | AT-AMP-02) - Analisis de Mercado [No. 2 - KIVA]", 'Profit & Loss'!$B:$B, 0), (COLUMN()-7)*12 + 3, 1, 12)) -> 13.059002 | J5: =AVERAGE(OFFSET('Profit & Loss'!$A$1, MATCH("({UO} | AT-AMP-02) - Analisis de Mercado [No. 2 - KIVA]", 'Profit & Loss'!$B:$B, 0), (COLUMN()-7)*12 + 3, 1, 12)) -> 12.273737 | K5: =AVERAGE(OFFSET('Profit & Loss'!$A$1, MATCH("({UO} | AT-AMP-02) - Analisis de Mercado [No. 2 - KIVA]", 'Profit & Loss'!$B:$B, 0), (COLUMN()-7)*12 + 3, 1, 12)) -> 11.536978
